Workbook
Name Nom_Foyer: 'Paramètres'!$E$9
Name Responsable: 'Paramètres'!$E$10
Name Adresse_Entite: 'Paramètres'!$E$12
Name Ville_Entite: 'Paramètres'!$E$13
Name Pays_Entite: 'Paramètres'!$E$14
Name Tel_Entite: 'Paramètres'!$E$15
Name Email_Entite: 'Paramètres'!$E$16
Name Site_Entite: 'Paramètres'!$E$17
Name Devise_Base: 'Paramètres'!$E$24
Name Symbole_Base: 'Paramètres'!$E$26
Name Solde_Initial: 'Paramètres'!$E$33
Name Taux_Cible: 'Paramètres'!$E$34
Name Seuil_Alerte: 'Paramètres'!$E$35
Name Plafond_Mensuel: 'Paramètres'!$E$36
Name Liste_Comptes: 'Paramètres'!$C$41:$C$60
Name Annee_Travail: 'Tableau de Bord'!$D$4
Name Mois_Suivi: 'Tableau de Bord'!$G$4
Name Mois_Num: 'Tableau de Bord'!$H$4
Name Codes_Devises: 'Listes'!$B$6:$B$31
Name Noms_Devises: 'Listes'!$C$6:$C$31
Name Symboles_Devises: 'Listes'!$D$6:$D$31
Name Taux_Devises: 'Listes'!$G$6:$G$31
Name Facteurs_Frequence: 'Listes'!$AO$6:$AO$11
Name J_Date: 'Journal'!$B$13:$B$3012
Name J_Type: 'Journal'!$C$13:$C$3012
Name J_Module: 'Journal'!$D$13:$D$3012
Name J_Cat: 'Journal'!$E$13:$E$3012
Name J_Libelle: 'Journal'!$F$13:$F$3012
Name J_Compte: 'Journal'!$H$13:$H$3012
Name J_Entree: 'Journal'!$J$13:$J$3012
Name J_Sortie: 'Journal'!$K$13:$K$3012
Name J_Moyen: 'Journal'!$N$13:$N$3012
Name J_Projet: 'Journal'!$O$13:$O$3012
Name J_Nature: 'Journal'!$P$13:$P$3012
Name J_Statut: 'Journal'!$Q$13:$Q$3012
Name J_Montant: 'Journal'!$U$13:$U$3012
Name J_Mois: 'Journal'!$V$13:$V$3012
Name J_Annee: 'Journal'!$W$13:$W$3012
Name P_Annee: 'Estimation Annuelle'!$B$12:$B$211
Name P_Module: 'Estimation Annuelle'!$C$12:$C$211
Name P_Type: 'Estimation Annuelle'!$D$12:$D$211
Name P_Cat: 'Estimation Annuelle'!$E$12:$E$211
Name P_Total: 'Estimation Annuelle'!$R$12:$R$211
Name P_Mois: 'Estimation Annuelle'!$F$12:$Q$211
Name Liste_Projets: 'Calculs'!$B$246:$B$285
Name Dime_Active: 'Paramètres'!$E$68
Name Dime_Taux: 'Paramètres'!$E$69
Name Dime_Base: 'Paramètres'!$E$70
Name Perimetre: 'Paramètres'!$E$71
Name Perimetre_Filtre: 'Paramètres'!$K$71
Name P_M1: 'Estimation Annuelle'!$F$12:$F$211
Name P_M2: 'Estimation Annuelle'!$G$12:$G$211
Name P_M3: 'Estimation Annuelle'!$H$12:$H$211
Name P_M4: 'Estimation Annuelle'!$I$12:$I$211
Name P_M5: 'Estimation Annuelle'!$J$12:$J$211
Name P_M6: 'Estimation Annuelle'!$K$12:$K$211
Name P_M7: 'Estimation Annuelle'!$L$12:$L$211
Name P_M8: 'Estimation Annuelle'!$M$12:$M$211
Name P_M9: 'Estimation Annuelle'!$N$12:$N$211
Name P_M10: 'Estimation Annuelle'!$O$12:$O$211

Sheet Accueil
B7: Planification et suivi financier — général, mariage, immobilier & terrain, business
B9: ="Bonjour "&Nom_Foyer&" • période suivie : "&Mois_Suivi&" "&Annee_Travail&" • devise : "&Devise_Base&" ("&Symbole_Base&")"
B10: =TRIM(Adresse_Entite&IF(Adresse_Entite="","",", ")&Ville_Entite&IF(Pays_Entite="","",", "&Pays_Entite)&IF(Tel_Entite="",""," · "&Tel_Entite)&IF(Email_Entite="",""," · "&Email_Entite)&IF(Site_Entite="",""," · "&Site_Entite))
B12: VOTRE PARCOURS — DANS CET ORDRE
B13: ① REMPLIR MES INFORMATIONS | D13: ② ESTIMER MON ANNÉE | F13: ③ BUDGET SMART
B16: Nom, coordonnées, devise, comptes bancaires | D16: Charges fixes, variables et imprévus, mois par mois | F16: Mon journal de tous les jours — tout se synchronise
B18: Une fois vos informations et votre estimation posées, il ne reste plus qu'à tenir le journal : tableau de bord, budget 12 mois, synthèse et modules se remplissent tout seuls.
B20: MES MODULES — chacun sa feuille, aucun mélange
B21: MARIAGE | D21: PROJET | F21: IMMO
B23: Postes, devis, financement | D23: Business, chiffre d'affaires, marge | F23: Terrains, biens, travaux, loyers
B26: OÙ J'EN SUIS AUJOURD'HUI
B27: SOLDE DU MOIS | D27: DÉPENSES DU MOIS | F27: TRÉSORERIE DISPONIBLE
B28: =INDEX(Calculs!$J$6:$J$17,Mois_Num) | D28: =INDEX(Calculs!$E$6:$E$17,Mois_Num) | F28: =Paramètres!$H$61
B32: CONSULTER
B33: ➜ Tableau de bord | D33: ➜ Budget 12 mois | F33: ➜ Synthèse annuelle
B35: ➜ Objectifs & épargne | D35: ➜ Dettes & crédits | F35: ➜ Charges récurrentes
B37: ➜ Guide d'utilisation | D37: ➜ Référentiels & listes
B39: Les cases sur fond jaune pâle sont les seules à remplir. Tout le reste est calculé et verrouillé — mot de passe APEX-2026 si vous devez y toucher.
B42: APEX AFRICA — African Premium Experience · Abidjan, Côte d'Ivoire
B43: contact@apxafrica.com · www.apxafrica.com
B44: © 2026 APEX AFRICA. « Budget Smart » et son logo sont la propriété d'APEX AFRICA. Tous droits réservés — reproduction, diffusion ou revente interdites sans autorisation écrite.
B45: BUDGET SMART by APEX AFRICA v1.0 — feuilles protégées, aucune macro.

Sheet Paramètres
B1: MES INFORMATIONS
B2: Étape ① — renseignez ceci une seule fois : tout le classeur s'y adapte
B3: ⌂ ACCUEIL | D3: ① MES INFOS | F3: ② ESTIMATION | H3: ③ BUDGET SMART | J3: TABLEAU DE BORD
C5: Seules les cases sur fond JAUNE PÂLE sont modifiables. Le reste de la feuille est verrouillé pour protéger les formules — mot de passe APEX-2026 (Révision ▸ Ôter la protection de la feuille).
C7: ① IDENTITÉ & COORDONNÉES
C9: Raison sociale / Nom | E9: APEX AFRICA | G9: Apparaît en tête du tableau de bord et des synthèses.
C10: Responsable / Titulaire | G10: La personne qui tient le budget.
C11: Activité / Fonction
C12: Adresse
C13: Ville | E13: Abidjan
C14: Pays | E14: Côte d'Ivoire
C15: Téléphone | G15: Saisissez-le tel quel, avec l'indicatif : +225 …
C16: Email | E16: contact@apxafrica.com
C17: Site web | E17: www.apxafrica.com
C18: RCCM / IFU / N° d'identification | G18: Facultatif — utile si le classeur sert à une structure.
C19: Situation familiale | G19: Pour un budget personnel. Laissez vide sinon.
C20: Personnes à charge | E20: 0 | G20: Sert au calcul de la dépense moyenne par personne.
C22: ② DEVISE & PÉRIODE
C24: Devise de base | E24: XOF | G24: Toutes les synthèses sont exprimées dans cette devise. Changez-la : symboles, taux et totaux suivent. À fixer avant de commencer à saisir.
C25: Nom de la devise | E25: =IFERROR(INDEX(Noms_Devises,MATCH(Devise_Base,Codes_Devises,0)),"")
C26: Symbole | E26: =IFERROR(INDEX(Symboles_Devises,MATCH(Devise_Base,Codes_Devises,0)),"")
C27: Année de travail | E27: =Annee_Travail | G27: Se règle en haut du Tableau de bord — toutes les feuilles suivent.
C28: Mois de suivi | E28: =Mois_Suivi | G28: Se règle également en haut du Tableau de bord.
C29: Mois de démarrage du budget | E29: Janvier | G29: Utile si votre exercice ne démarre pas en janvier.
C31: ③ SOLDES & OBJECTIFS
C33: Trésorerie initiale | E33: 0 | G33: Total de vos disponibilités au 1er janvier de l'année de travail.
C34: Taux d'épargne cible | E34: 0.2 | G34: Part des revenus que vous visez à épargner chaque mois.
C35: Seuil d'alerte budget | E35: 0.9 | G35: Au-delà de ce pourcentage du budget consommé, l'alerte passe au rouge.
C36: Plafond de dépenses mensuel | E36: 0 | G36: Laissez 0 si vous n'en fixez pas.
C38: ④ COMPTES, CAISSES & PORTEFEUILLES
C40: Compte / Portefeuille | D40: Nature | E40: Devise | F40: Solde d'ouverture | G40: Mouvements enregistrés | H40: Solde actuel calculé
C41: Compte courant principal | E41: =IF($C41="","",Devise_Base) | F41: 0 | G41: =IF($C41="","",SUMIFS(J_Montant,J_Compte,$C41,J_Type,"Revenu",J_Statut,"<>Annulé",J_Statut,"<>Prévu")-SUMIFS(J_Montant,J_Compte,$C41,J_Type,"Dépense",J_Statut,"<>Annulé",J_Statut,"<>Prévu")-SUMIFS(J_Montant,J_Compte,$C41,J_Type,"Épargne",J_Statut,"<>Annulé",J_Statut,"<>Prévu")-SUMIFS(J_Montant,J_Compte,$C41,J_Type,"Investissement",J_Statut,"<>Annulé",J_Statut,"<>Prévu")-SUMIFS(J_Montant,J_Compte,$C41,J_Type,"Remboursement crédit",J_Statut,"<>Annulé",J_Statut,"<>Prévu")) | H41: =IF($C41="","",N($F41)+N($G41))
C42: Compte courant secondaire | E42: =IF($C42="","",Devise_Base) | F42: 0 | G42: =IF($C42="","",SUMIFS(J_Montant,J_Compte,$C42,J_Type,"Revenu",J_Statut,"<>Annulé",J_Statut,"<>Prévu")-SUMIFS(J_Montant,J_Compte,$C42,J_Type,"Dépense",J_Statut,"<>Annulé",J_Statut,"<>Prévu")-SUMIFS(J_Montant,J_Compte,$C42,J_Type,"Épargne",J_Statut,"<>Annulé",J_Statut,"<>Prévu")-SUMIFS(J_Montant,J_Compte,$C42,J_Type,"Investissement",J_Statut,"<>Annulé",J_Statut,"<>Prévu")-SUMIFS(J_Montant,J_Compte,$C42,J_Type,"Remboursement crédit",J_Statut,"<>Annulé",J_Statut,"<>Prévu")) | H42: =IF($C42="","",N($F42)+N($G42))
C43: Mobile Money 1 | E43: =IF($C43="","",Devise_Base) | F43: 0 | G43: =IF($C43="","",SUMIFS(J_Montant,J_Compte,$C43,J_Type,"Revenu",J_Statut,"<>Annulé",J_Statut,"<>Prévu")-SUMIFS(J_Montant,J_Compte,$C43,J_Type,"Dépense",J_Statut,"<>Annulé",J_Statut,"<>Prévu")-SUMIFS(J_Montant,J_Compte,$C43,J_Type,"Épargne",J_Statut,"<>Annulé",J_Statut,"<>Prévu")-SUMIFS(J_Montant,J_Compte,$C43,J_Type,"Investissement",J_Statut,"<>Annulé",J_Statut,"<>Prévu")-SUMIFS(J_Montant,J_Compte,$C43,J_Type,"Remboursement crédit",J_Statut,"<>Annulé",J_Statut,"<>Prévu")) | H43: =IF($C43="","",N($F43)+N($G43))
C44: Mobile Money 2 | E44: =IF($C44="","",Devise_Base) | F44: 0 | G44: =IF($C44="","",SUMIFS(J_Montant,J_Compte,$C44,J_Type,"Revenu",J_Statut,"<>Annulé",J_Statut,"<>Prévu")-SUMIFS(J_Montant,J_Compte,$C44,J_Type,"Dépense",J_Statut,"<>Annulé",J_Statut,"<>Prévu")-SUMIFS(J_Montant,J_Compte,$C44,J_Type,"Épargne",J_Statut,"<>Annulé",J_Statut,"<>Prévu")-SUMIFS(J_Montant,J_Compte,$C44,J_Type,"Investissement",J_Statut,"<>Annulé",J_Statut,"<>Prévu")-SUMIFS(J_Montant,J_Compte,$C44,J_Type,"Remboursement crédit",J_Statut,"<>Annulé",J_Statut,"<>Prévu")) | H44: =IF($C44="","",N($F44)+N($G44))
C45: Espèces / Caisse | E45: =IF($C45="","",Devise_Base) | F45: 0 | G45: =IF($C45="","",SUMIFS(J_Montant,J_Compte,$C45,J_Type,"Revenu",J_Statut,"<>Annulé",J_Statut,"<>Prévu")-SUMIFS(J_Montant,J_Compte,$C45,J_Type,"Dépense",J_Statut,"<>Annulé",J_Statut,"<>Prévu")-SUMIFS(J_Montant,J_Compte,$C45,J_Type,"Épargne",J_Statut,"<>Annulé",J_Statut,"<>Prévu")-SUMIFS(J_Montant,J_Compte,$C45,J_Type,"Investissement",J_Statut,"<>Annulé",J_Statut,"<>Prévu")-SUMIFS(J_Montant,J_Compte,$C45,J_Type,"Remboursement crédit",J_Statut,"<>Annulé",J_Statut,"<>Prévu")) | H45: =IF($C45="","",N($F45)+N($G45))
C46: Compte épargne | E46: =IF($C46="","",Devise_Base) | F46: 0 | G46: =IF($C46="","",SUMIFS(J_Montant,J_Compte,$C46,J_Type,"Revenu",J_Statut,"<>Annulé",J_Statut,"<>Prévu")-SUMIFS(J_Montant,J_Compte,$C46,J_Type,"Dépense",J_Statut,"<>Annulé",J_Statut,"<>Prévu")-SUMIFS(J_Montant,J_Compte,$C46,J_Type,"Épargne",J_Statut,"<>Annulé",J_Statut,"<>Prévu")-SUMIFS(J_Montant,J_Compte,$C46,J_Type,"Investissement",J_Statut,"<>Annulé",J_Statut,"<>Prévu")-SUMIFS(J_Montant,J_Compte,$C46,J_Type,"Remboursement crédit",J_Statut,"<>Annulé",J_Statut,"<>Prévu")) | H46: =IF($C46="","",N($F46)+N($G46))
C47: Compte projet | E47: =IF($C47="","",Devise_Base) | F47: 0 | G47: =IF($C47="","",SUMIFS(J_Montant,J_Compte,$C47,J_Type,"Revenu",J_Statut,"<>Annulé",J_Statut,"<>Prévu")-SUMIFS(J_Montant,J_Compte,$C47,J_Type,"Dépense",J_Statut,"<>Annulé",J_Statut,"<>Prévu")-SUMIFS(J_Montant,J_Compte,$C47,J_Type,"Épargne",J_Statut,"<>Annulé",J_Statut,"<>Prévu")-SUMIFS(J_Montant,J_Compte,$C47,J_Type,"Investissement",J_Statut,"<>Annulé",J_Statut,"<>Prévu")-SUMIFS(J_Montant,J_Compte,$C47,J_Type,"Remboursement crédit",J_Statut,"<>Annulé",J_Statut,"<>Prévu")) | H47: =IF($C47="","",N($F47)+N($G47))
C48: Compte business | E48: =IF($C48="","",Devise_Base) | F48: 0 | G48: =IF($C48="","",SUMIFS(J_Montant,J_Compte,$C48,J_Type,"Revenu",J_Statut,"<>Annulé",J_Statut,"<>Prévu")-SUMIFS(J_Montant,J_Compte,$C48,J_Type,"Dépense",J_Statut,"<>Annulé",J_Statut,"<>Prévu")-SUMIFS(J_Montant,J_Compte,$C48,J_Type,"Épargne",J_Statut,"<>Annulé",J_Statut,"<>Prévu")-SUMIFS(J_Montant,J_Compte,$C48,J_Type,"Investissement",J_Statut,"<>Annulé",J_Statut,"<>Prévu")-SUMIFS(J_Montant,J_Compte,$C48,J_Type,"Remboursement crédit",J_Statut,"<>Annulé",J_Statut,"<>Prévu")) | H48: =IF($C48="","",N($F48)+N($G48))
E49: =IF($C49="","",Devise_Base) | G49: =IF($C49="","",SUMIFS(J_Montant,J_Compte,$C49,J_Type,"Revenu",J_Statut,"<>Annulé",J_Statut,"<>Prévu")-SUMIFS(J_Montant,J_Compte,$C49,J_Type,"Dépense",J_Statut,"<>Annulé",J_Statut,"<>Prévu")-SUMIFS(J_Montant,J_Compte,$C49,J_Type,"Épargne",J_Statut,"<>Annulé",J_Statut,"<>Prévu")-SUMIFS(J_Montant,J_Compte,$C49,J_Type,"Investissement",J_Statut,"<>Annulé",J_Statut,"<>Prévu")-SUMIFS(J_Montant,J_Compte,$C49,J_Type,"Remboursement crédit",J_Statut,"<>Annulé",J_Statut,"<>Prévu")) | H49: =IF($C49="","",N($F49)+N($G49))
E50: =IF($C50="","",Devise_Base) | G50: =IF($C50="","",SUMIFS(J_Montant,J_Compte,$C50,J_Type,"Revenu",J_Statut,"<>Annulé",J_Statut,"<>Prévu")-SUMIFS(J_Montant,J_Compte,$C50,J_Type,"Dépense",J_Statut,"<>Annulé",J_Statut,"<>Prévu")-SUMIFS(J_Montant,J_Compte,$C50,J_Type,"Épargne",J_Statut,"<>Annulé",J_Statut,"<>Prévu")-SUMIFS(J_Montant,J_Compte,$C50,J_Type,"Investissement",J_Statut,"<>Annulé",J_Statut,"<>Prévu")-SUMIFS(J_Montant,J_Compte,$C50,J_Type,"Remboursement crédit",J_Statut,"<>Annulé",J_Statut,"<>Prévu")) | H50: =IF($C50="","",N($F50)+N($G50))
E51: =IF($C51="","",Devise_Base) | G51: =IF($C51="","",SUMIFS(J_Montant,J_Compte,$C51,J_Type,"Revenu",J_Statut,"<>Annulé",J_Statut,"<>Prévu")-SUMIFS(J_Montant,J_Compte,$C51,J_Type,"Dépense",J_Statut,"<>Annulé",J_Statut,"<>Prévu")-SUMIFS(J_Montant,J_Compte,$C51,J_Type,"Épargne",J_Statut,"<>Annulé",J_Statut,"<>Prévu")-SUMIFS(J_Montant,J_Compte,$C51,J_Type,"Investissement",J_Statut,"<>Annulé",J_Statut,"<>Prévu")-SUMIFS(J_Montant,J_Compte,$C51,J_Type,"Remboursement crédit",J_Statut,"<>Annulé",J_Statut,"<>Prévu")) | H51: =IF($C51="","",N($F51)+N($G51))
E52: =IF($C52="","",Devise_Base) | G52: =IF($C52="","",SUMIFS(J_Montant,J_Compte,$C52,J_Type,"Revenu",J_Statut,"<>Annulé",J_Statut,"<>Prévu")-SUMIFS(J_Montant,J_Compte,$C52,J_Type,"Dépense",J_Statut,"<>Annulé",J_Statut,"<>Prévu")-SUMIFS(J_Montant,J_Compte,$C52,J_Type,"Épargne",J_Statut,"<>Annulé",J_Statut,"<>Prévu")-SUMIFS(J_Montant,J_Compte,$C52,J_Type,"Investissement",J_Statut,"<>Annulé",J_Statut,"<>Prévu")-SUMIFS(J_Montant,J_Compte,$C52,J_Type,"Remboursement crédit",J_Statut,"<>Annulé",J_Statut,"<>Prévu")) | H52: =IF($C52="","",N($F52)+N($G52))
E53: =IF($C53="","",Devise_Base) | G53: =IF($C53="","",SUMIFS(J_Montant,J_Compte,$C53,J_Type,"Revenu",J_Statut,"<>Annulé",J_Statut,"<>Prévu")-SUMIFS(J_Montant,J_Compte,$C53,J_Type,"Dépense",J_Statut,"<>Annulé",J_Statut,"<>Prévu")-SUMIFS(J_Montant,J_Compte,$C53,J_Type,"Épargne",J_Statut,"<>Annulé",J_Statut,"<>Prévu")-SUMIFS(J_Montant,J_Compte,$C53,J_Type,"Investissement",J_Statut,"<>Annulé",J_Statut,"<>Prévu")-SUMIFS(J_Montant,J_Compte,$C53,J_Type,"Remboursement crédit",J_Statut,"<>Annulé",J_Statut,"<>Prévu")) | H53: =IF($C53="","",N($F53)+N($G53))
E54: =IF($C54="","",Devise_Base) | G54: =IF($C54="","",SUMIFS(J_Montant,J_Compte,$C54,J_Type,"Revenu",J_Statut,"<>Annulé",J_Statut,"<>Prévu")-SUMIFS(J_Montant,J_Compte,$C54,J_Type,"Dépense",J_Statut,"<>Annulé",J_Statut,"<>Prévu")-SUMIFS(J_Montant,J_Compte,$C54,J_Type,"Épargne",J_Statut,"<>Annulé",J_Statut,"<>Prévu")-SUMIFS(J_Montant,J_Compte,$C54,J_Type,"Investissement",J_Statut,"<>Annulé",J_Statut,"<>Prévu")-SUMIFS(J_Montant,J_Compte,$C54,J_Type,"Remboursement crédit",J_Statut,"<>Annulé",J_Statut,"<>Prévu")) | H54: =IF($C54="","",N($F54)+N($G54))
E55: =IF($C55="","",Devise_Base) | G55: =IF($C55="","",SUMIFS(J_Montant,J_Compte,$C55,J_Type,"Revenu",J_Statut,"<>Annulé",J_Statut,"<>Prévu")-SUMIFS(J_Montant,J_Compte,$C55,J_Type,"Dépense",J_Statut,"<>Annulé",J_Statut,"<>Prévu")-SUMIFS(J_Montant,J_Compte,$C55,J_Type,"Épargne",J_Statut,"<>Annulé",J_Statut,"<>Prévu")-SUMIFS(J_Montant,J_Compte,$C55,J_Type,"Investissement",J_Statut,"<>Annulé",J_Statut,"<>Prévu")-SUMIFS(J_Montant,J_Compte,$C55,J_Type,"Remboursement crédit",J_Statut,"<>Annulé",J_Statut,"<>Prévu")) | H55: =IF($C55="","",N($F55)+N($G55))
E56: =IF($C56="","",Devise_Base) | G56: =IF($C56="","",SUMIFS(J_Montant,J_Compte,$C56,J_Type,"Revenu",J_Statut,"<>Annulé",J_Statut,"<>Prévu")-SUMIFS(J_Montant,J_Compte,$C56,J_Type,"Dépense",J_Statut,"<>Annulé",J_Statut,"<>Prévu")-SUMIFS(J_Montant,J_Compte,$C56,J_Type,"Épargne",J_Statut,"<>Annulé",J_Statut,"<>Prévu")-SUMIFS(J_Montant,J_Compte,$C56,J_Type,"Investissement",J_Statut,"<>Annulé",J_Statut,"<>Prévu")-SUMIFS(J_Montant,J_Compte,$C56,J_Type,"Remboursement crédit",J_Statut,"<>Annulé",J_Statut,"<>Prévu")) | H56: =IF($C56="","",N($F56)+N($G56))
E57: =IF($C57="","",Devise_Base) | G57: =IF($C57="","",SUMIFS(J_Montant,J_Compte,$C57,J_Type,"Revenu",J_Statut,"<>Annulé",J_Statut,"<>Prévu")-SUMIFS(J_Montant,J_Compte,$C57,J_Type,"Dépense",J_Statut,"<>Annulé",J_Statut,"<>Prévu")-SUMIFS(J_Montant,J_Compte,$C57,J_Type,"Épargne",J_Statut,"<>Annulé",J_Statut,"<>Prévu")-SUMIFS(J_Montant,J_Compte,$C57,J_Type,"Investissement",J_Statut,"<>Annulé",J_Statut,"<>Prévu")-SUMIFS(J_Montant,J_Compte,$C57,J_Type,"Remboursement crédit",J_Statut,"<>Annulé",J_Statut,"<>Prévu")) | H57: =IF($C57="","",N($F57)+N($G57))
E58: =IF($C58="","",Devise_Base) | G58: =IF($C58="","",SUMIFS(J_Montant,J_Compte,$C58,J_Type,"Revenu",J_Statut,"<>Annulé",J_Statut,"<>Prévu")-SUMIFS(J_Montant,J_Compte,$C58,J_Type,"Dépense",J_Statut,"<>Annulé",J_Statut,"<>Prévu")-SUMIFS(J_Montant,J_Compte,$C58,J_Type,"Épargne",J_Statut,"<>Annulé",J_Statut,"<>Prévu")-SUMIFS(J_Montant,J_Compte,$C58,J_Type,"Investissement",J_Statut,"<>Annulé",J_Statut,"<>Prévu")-SUMIFS(J_Montant,J_Compte,$C58,J_Type,"Remboursement crédit",J_Statut,"<>Annulé",J_Statut,"<>Prévu")) | H58: =IF($C58="","",N($F58)+N($G58))
E59: =IF($C59="","",Devise_Base) | G59: =IF($C59="","",SUMIFS(J_Montant,J_Compte,$C59,J_Type,"Revenu",J_Statut,"<>Annulé",J_Statut,"<>Prévu")-SUMIFS(J_Montant,J_Compte,$C59,J_Type,"Dépense",J_Statut,"<>Annulé",J_Statut,"<>Prévu")-SUMIFS(J_Montant,J_Compte,$C59,J_Type,"Épargne",J_Statut,"<>Annulé",J_Statut,"<>Prévu")-SUMIFS(J_Montant,J_Compte,$C59,J_Type,"Investissement",J_Statut,"<>Annulé",J_Statut,"<>Prévu")-SUMIFS(J_Montant,J_Compte,$C59,J_Type,"Remboursement crédit",J_Statut,"<>Annulé",J_Statut,"<>Prévu")) | H59: =IF($C59="","",N($F59)+N($G59))
E60: =IF($C60="","",Devise_Base) | G60: =IF($C60="","",SUMIFS(J_Montant,J_Compte,$C60,J_Type,"Revenu",J_Statut,"<>Annulé",J_Statut,"<>Prévu")-SUMIFS(J_Montant,J_Compte,$C60,J_Type,"Dépense",J_Statut,"<>Annulé",J_Statut,"<>Prévu")-SUMIFS(J_Montant,J_Compte,$C60,J_Type,"Épargne",J_Statut,"<>Annulé",J_Statut,"<>Prévu")-SUMIFS(J_Montant,J_Compte,$C60,J_Type,"Investissement",J_Statut,"<>Annulé",J_Statut,"<>Prévu")-SUMIFS(J_Montant,J_Compte,$C60,J_Type,"Remboursement crédit",J_Statut,"<>Annulé",J_Statut,"<>Prévu")) | H60: =IF($C60="","",N($F60)+N($G60))
C61: TOTAL DISPONIBLE | H61: =SUM(H41:H60)
C63: Astuce : le solde de chaque compte se met à jour tout seul à partir du Journal. Les transferts entre vos propres comptes sont neutres et ne modifient pas le total.
C66: ⑤ DÎME & PÉRIMÈTRE D'ANALYSE
C68: Dîme activée | E68: Oui | G68: Si Oui, le classeur calcule seul la dîme due chaque mois et suit ce qui a été versé.
C69: Taux de la dîme | E69: 0.1 | G69: 10 % par défaut.
C70: Assiette de calcul | E70: Tous les revenus | G70: Sur quels revenus la dîme est calculée.
C71: Périmètre d'analyse | E71: Général seul | G71: Ce que comptent le tableau de bord et la synthèse annuelle. « Général seul » laisse le mariage, l'immobilier et le business à leurs propres feuilles. | K71: =IF($E$71="Tout confondu","*",IF($E$71="Général seul","Général",$E$71))
C73: ➜ Journal des opérations
C74: ➜ Plan annuel
C75: ➜ Tableau de bord
C76: ➜ Cours des devises

Sheet Estimation Annuelle
B1: ESTIMATION ANNUELLE
B2: Étape ② — ce que vous prévoyez pour l'année, mois par mois. Le réalisé remonte tout seul du Journal.
B3: ⌂ ACCUEIL | E3: ① MES INFOS | H3: ② ESTIMATION | K3: ③ BUDGET SMART | N3: TABLEAU DE BORD | Q3: BUDGET 12 MOIS
B5: Une ligne = une catégorie budgétée pour une année. Dupliquez les lignes en changeant l'année pour préparer l'exercice suivant : l'historique reste intact. « Écart » est toujours favorable quand il est positif.
B7: REVENUS PRÉVUS | E7: DÉPENSES PRÉVUES | H7: ÉPARGNE PRÉVUE | K7: SOLDE PRÉVISIONNEL | N7: RÉALISÉ / PRÉVU (dépenses)
B8: =SUMIFS($R$12:$R$211,$B$12:$B$211,Annee_Travail,$D$12:$D$211,"Revenu") | E8: =SUMIFS($R$12:$R$211,$B$12:$B$211,Annee_Travail,$D$12:$D$211,"Dépense") | H8: =SUMIFS($R$12:$R$211,$B$12:$B$211,Annee_Travail,$D$12:$D$211,"Épargne")+SUMIFS($R$12:$R$211,$B$12:$B$211,Annee_Travail,$D$12:$D$211,"Investissement") | K8: =SUMIFS($R$12:$R$211,$B$12:$B$211,Annee_Travail,$D$12:$D$211,"Revenu")-SUMIFS($R$12:$R$211,$B$12:$B$211,Annee_Travail,$D$12:$D$211,"Dépense")-SUMIFS($R$12:$R$211,$B$12:$B$211,Annee_Travail,$D$12:$D$211,"Remboursement crédit") | N8: =IFERROR(SUMIFS($S$12:$S$211,$B$12:$B$211,Annee_Travail,$D$12:$D$211,"Dépense")/SUMIFS($R$12:$R$211,$B$12:$B$211,Annee_Travail,$D$12:$D$211,"Dépense"),0)
B11: Année | C11: Module | D11: Type | E11: Catégorie | F11: Jan | G11: Fév | H11: Mar | I11: Avr | J11: Mai | K11: Juin | L11: Juil | M11: Août | N11: Sep | O11: Oct | P11: Nov | Q11: Déc | R11: Total prévu | S11: Réalisé | T11: Écart | U11: % consommé | V11: Commentaire
B12: =Annee_Travail | C12: Général | D12: Revenu | E12: Salaire | R12: =IF($E12="","",SUM($F12:$Q12)) | S12: =IF($E12="","",SUMIFS(J_Montant,J_Annee,$B12,J_Module,$C12,J_Type,$D12,J_Cat,$E12,J_Statut,"<>Annulé",J_Statut,"<>Prévu")) | T12: =IF($E12="","",IF($D12="Revenu",$S12-$R12,$R12-$S12)) | U12: =IF(OR($E12="",$R12=0),"",$S12/$R12)
B13: =Annee_Travail | C13: Général | D13: Revenu | E13: Prime / 13e mois | R13: =IF($E13="","",SUM($F13:$Q13)) | S13: =IF($E13="","",SUMIFS(J_Montant,J_Annee,$B13,J_Module,$C13,J_Type,$D13,J_Cat,$E13,J_Statut,"<>Annulé",J_Statut,"<>Prévu")) | T13: =IF($E13="","",IF($D13="Revenu",$S13-$R13,$R13-$S13)) | U13: =IF(OR($E13="",$R13=0),"",$S13/$R13)
B14: =Annee_Travail | C14: Général | D14: Revenu | E14: Freelance / Consulting | R14: =IF($E14="","",SUM($F14:$Q14)) | S14: =IF($E14="","",SUMIFS(J_Montant,J_Annee,$B14,J_Module,$C14,J_Type,$D14,J_Cat,$E14,J_Statut,"<>Annulé",J_Statut,"<>Prévu")) | T14: =IF($E14="","",IF($D14="Revenu",$S14-$R14,$R14-$S14)) | U14: =IF(OR($E14="",$R14=0),"",$S14/$R14)
B15: =Annee_Travail | C15: Général | D15: Revenu | E15: Commerce / Ventes | R15: =IF($E15="","",SUM($F15:$Q15)) | S15: =IF($E15="","",SUMIFS(J_Montant,J_Annee,$B15,J_Module,$C15,J_Type,$D15,J_Cat,$E15,J_Statut,"<>Annulé",J_Statut,"<>Prévu")) | T15: =IF($E15="","",IF($D15="Revenu",$S15-$R15,$R15-$S15)) | U15: =IF(OR($E15="",$R15=0),"",$S15/$R15)
B16: =Annee_Travail | C16: Général | D16: Revenu | E16: Loyers perçus | R16: =IF($E16="","",SUM($F16:$Q16)) | S16: =IF($E16="","",SUMIFS(J_Montant,J_Annee,$B16,J_Module,$C16,J_Type,$D16,J_Cat,$E16,J_Statut,"<>Annulé",J_Statut,"<>Prévu")) | T16: =IF($E16="","",IF($D16="Revenu",$S16-$R16,$R16-$S16)) | U16: =IF(OR($E16="",$R16=0),"",$S16/$R16)
B17: =Annee_Travail | C17: Général | D17: Revenu | E17: Autre revenu | R17: =IF($E17="","",SUM($F17:$Q17)) | S17: =IF($E17="","",SUMIFS(J_Montant,J_Annee,$B17,J_Module,$C17,J_Type,$D17,J_Cat,$E17,J_Statut,"<>Annulé",J_Statut,"<>Prévu")) | T17: =IF($E17="","",IF($D17="Revenu",$S17-$R17,$R17-$S17)) | U17: =IF(OR($E17="",$R17=0),"",$S17/$R17)
B18: =Annee_Travail | C18: Général | D18: Dépense | E18: Loyer | R18: =IF($E18="","",SUM($F18:$Q18)) | S18: =IF($E18="","",SUMIFS(J_Montant,J_Annee,$B18,J_Module,$C18,J_Type,$D18,J_Cat,$E18,J_Statut,"<>Annulé",J_Statut,"<>Prévu")) | T18: =IF($E18="","",IF($D18="Revenu",$S18-$R18,$R18-$S18)) | U18: =IF(OR($E18="",$R18=0),"",$S18/$R18)
B19: =Annee_Travail | C19: Général | D19: Dépense | E19: Électricité | R19: =IF($E19="","",SUM($F19:$Q19)) | S19: =IF($E19="","",SUMIFS(J_Montant,J_Annee,$B19,J_Module,$C19,J_Type,$D19,J_Cat,$E19,J_Statut,"<>Annulé",J_Statut,"<>Prévu")) | T19: =IF($E19="","",IF($D19="Revenu",$S19-$R19,$R19-$S19)) | U19: =IF(OR($E19="",$R19=0),"",$S19/$R19)
B20: =Annee_Travail | C20: Général | D20: Dépense | E20: Eau | R20: =IF($E20="","",SUM($F20:$Q20)) | S20: =IF($E20="","",SUMIFS(J_Montant,J_Annee,$B20,J_Module,$C20,J_Type,$D20,J_Cat,$E20,J_Statut,"<>Annulé",J_Statut,"<>Prévu")) | T20: =IF($E20="","",IF($D20="Revenu",$S20-$R20,$R20-$S20)) | U20: =IF(OR($E20="",$R20=0),"",$S20/$R20)
B21: =Annee_Travail | C21: Général | D21: Dépense | E21: Internet / Box | R21: =IF($E21="","",SUM($F21:$Q21)) | S21: =IF($E21="","",SUMIFS(J_Montant,J_Annee,$B21,J_Module,$C21,J_Type,$D21,J_Cat,$E21,J_Statut,"<>Annulé",J_Statut,"<>Prévu")) | T21: =IF($E21="","",IF($D21="Revenu",$S21-$R21,$R21-$S21)) | U21: =IF(OR($E21="",$R21=0),"",$S21/$R21)
B22: =Annee_Travail | C22: Général | D22: Dépense | E22: Téléphone | R22: =IF($E22="","",SUM($F22:$Q22)) | S22: =IF($E22="","",SUMIFS(J_Montant,J_Annee,$B22,J_Module,$C22,J_Type,$D22,J_Cat,$E22,J_Statut,"<>Annulé",J_Statut,"<>Prévu")) | T22: =IF($E22="","",IF($D22="Revenu",$S22-$R22,$R22-$S22)) | U22: =IF(OR($E22="",$R22=0),"",$S22/$R22)
B23: =Annee_Travail | C23: Général | D23: Dépense | E23: Alimentation / Courses | R23: =IF($E23="","",SUM($F23:$Q23)) | S23: =IF($E23="","",SUMIFS(J_Montant,J_Annee,$B23,J_Module,$C23,J_Type,$D23,J_Cat,$E23,J_Statut,"<>Annulé",J_Statut,"<>Prévu")) | T23: =IF($E23="","",IF($D23="Revenu",$S23-$R23,$R23-$S23)) | U23: =IF(OR($E23="",$R23=0),"",$S23/$R23)
... B78: =Annee_Travail | C78: Business | D78: Dépense | E78: Divers business | R78: =IF($E78="","",SUM($F78:$Q78)) | S78: =IF($E78="","",SUMIFS(J_Montant,J_Annee,$B78,J_Module,$C78,J_Type,$D78,J_Cat,$E78,J_Statut,"<>Annulé",J_Statut,"<>Prévu")) | T78: =IF($E78="","",IF($D78="Revenu",$S78-$R78,$R78-$S78)) | U78: =IF(OR($E78="",$R78=0),"",$S78/$R78)
B79: =Annee_Travail | R79: =IF($E79="","",SUM($F79:$Q79)) | S79: =IF($E79="","",SUMIFS(J_Montant,J_Annee,$B79,J_Module,$C79,J_Type,$D79,J_Cat,$E79,J_Statut,"<>Annulé",J_Statut,"<>Prévu")) | T79: =IF($E79="","",IF($D79="Revenu",$S79-$R79,$R79-$S79)) | U79: =IF(OR($E79="",$R79=0),"",$S79/$R79)
B80: =Annee_Travail | R80: =IF($E80="","",SUM($F80:$Q80)) | S80: =IF($E80="","",SUMIFS(J_Montant,J_Annee,$B80,J_Module,$C80,J_Type,$D80,J_Cat,$E80,J_Statut,"<>Annulé",J_Statut,"<>Prévu")) | T80: =IF($E80="","",IF($D80="Revenu",$S80-$R80,$R80-$S80)) | U80: =IF(OR($E80="",$R80=0),"",$S80/$R80)
B81: =Annee_Travail | R81: =IF($E81="","",SUM($F81:$Q81)) | S81: =IF($E81="","",SUMIFS(J_Montant,J_Annee,$B81,J_Module,$C81,J_Type,$D81,J_Cat,$E81,J_Statut,"<>Annulé",J_Statut,"<>Prévu")) | T81: =IF($E81="","",IF($D81="Revenu",$S81-$R81,$R81-$S81)) | U81: =IF(OR($E81="",$R81=0),"",$S81/$R81)
B82: =Annee_Travail | R82: =IF($E82="","",SUM($F82:$Q82)) | S82: =IF($E82="","",SUMIFS(J_Montant,J_Annee,$B82,J_Module,$C82,J_Type,$D82,J_Cat,$E82,J_Statut,"<>Annulé",J_Statut,"<>Prévu")) | T82: =IF($E82="","",IF($D82="Revenu",$S82-$R82,$R82-$S82)) | U82: =IF(OR($E82="",$R82=0),"",$S82/$R82)
B83: =Annee_Travail | R83: =IF($E83="","",SUM($F83:$Q83)) | S83: =IF($E83="","",SUMIFS(J_Montant,J_Annee,$B83,J_Module,$C83,J_Type,$D83,J_Cat,$E83,J_Statut,"<>Annulé",J_Statut,"<>Prévu")) | T83: =IF($E83="","",IF($D83="Revenu",$S83-$R83,$R83-$S83)) | U83: =IF(OR($E83="",$R83=0),"",$S83/$R83)
B84: =Annee_Travail | R84: =IF($E84="","",SUM($F84:$Q84)) | S84: =IF($E84="","",SUMIFS(J_Montant,J_Annee,$B84,J_Module,$C84,J_Type,$D84,J_Cat,$E84,J_Statut,"<>Annulé",J_Statut,"<>Prévu")) | T84: =IF($E84="","",IF($D84="Revenu",$S84-$R84,$R84-$S84)) | U84: =IF(OR($E84="",$R84=0),"",$S84/$R84)
B85: =Annee_Travail | R85: =IF($E85="","",SUM($F85:$Q85)) | S85: =IF($E85="","",SUMIFS(J_Montant,J_Annee,$B85,J_Module,$C85,J_Type,$D85,J_Cat,$E85,J_Statut,"<>Annulé",J_Statut,"<>Prévu")) | T85: =IF($E85="","",IF($D85="Revenu",$S85-$R85,$R85-$S85)) | U85: =IF(OR($E85="",$R85=0),"",$S85/$R85)
B86: =Annee_Travail | R86: =IF($E86="","",SUM($F86:$Q86)) | S86: =IF($E86="","",SUMIFS(J_Montant,J_Annee,$B86,J_Module,$C86,J_Type,$D86,J_Cat,$E86,J_Statut,"<>Annulé",J_Statut,"<>Prévu")) | T86: =IF($E86="","",IF($D86="Revenu",$S86-$R86,$R86-$S86)) | U86: =IF(OR($E86="",$R86=0),"",$S86/$R86)
B87: =Annee_Travail | R87: =IF($E87="","",SUM($F87:$Q87)) | S87: =IF($E87="","",SUMIFS(J_Montant,J_Annee,$B87,J_Module,$C87,J_Type,$D87,J_Cat,$E87,J_Statut,"<>Annulé",J_Statut,"<>Prévu")) | T87: =IF($E87="","",IF($D87="Revenu",$S87-$R87,$R87-$S87)) | U87: =IF(OR($E87="",$R87=0),"",$S87/$R87)
B88: =Annee_Travail | R88: =IF($E88="","",SUM($F88:$Q88)) | S88: =IF($E88="","",SUMIFS(J_Montant,J_Annee,$B88,J_Module,$C88,J_Type,$D88,J_Cat,$E88,J_Statut,"<>Annulé",J_Statut,"<>Prévu")) | T88: =IF($E88="","",IF($D88="Revenu",$S88-$R88,$R88-$S88)) | U88: =IF(OR($E88="",$R88=0),"",$S88/$R88)
B89: =Annee_Travail | R89: =IF($E89="","",SUM($F89:$Q89)) | S89: =IF($E89="","",SUMIFS(J_Montant,J_Annee,$B89,J_Module,$C89,J_Type,$D89,J_Cat,$E89,J_Statut,"<>Annulé",J_Statut,"<>Prévu")) | T89: =IF($E89="","",IF($D89="Revenu",$S89-$R89,$R89-$S89)) | U89: =IF(OR($E89="",$R89=0),"",$S89/$R89)
B90: =Annee_Travail | R90: =IF($E90="","",SUM($F90:$Q90)) | S90: =IF($E90="","",SUMIFS(J_Montant,J_Annee,$B90,J_Module,$C90,J_Type,$D90,J_Cat,$E90,J_Statut,"<>Annulé",J_Statut,"<>Prévu")) | T90: =IF($E90="","",IF($D90="Revenu",$S90-$R90,$R90-$S90)) | U90: =IF(OR($E90="",$R90=0),"",$S90/$R90)
... B211: =Annee_Travail | R211: =IF($E211="","",SUM($F211:$Q211)) | S211: =IF($E211="","",SUMIFS(J_Montant,J_Annee,$B211,J_Module,$C211,J_Type,$D211,J_Cat,$E211,J_Statut,"<>Annulé",J_Statut,"<>Prévu")) | T211: =IF($E211="","",IF($D211="Revenu",$S211-$R211,$R211-$S211)) | U211: =IF(OR($E211="",$R211=0),"",$S211/$R211)

Sheet Journal
B1: BUDGET SMART — JOURNAL QUOTIDIEN
B2: Une ligne par opération. Vous ne remplissez que le premier bloc ; le sens, l'entrée, la sortie et le solde se calculent seuls.
B3: ⌂ ACCUEIL | E3: ① MES INFOS | H3: ② ESTIMATION | K3: ③ BUDGET SMART | N3: TABLEAU DE BORD | Q3: BUDGET 12 MOIS
B5: Saisissez toujours un montant POSITIF dans « Montant ». C'est la colonne « Type » qui dit si l'argent entre ou sort : le classeur remplit alors tout seul les colonnes ENTRÉE, SORTIE et SOLDE CUMULÉ. Statut « Prévu » = engagement futur, compté à part. Les cases jaunes sont les seules à remplir.
B7: ÉCRITURES SAISIES | E7: TOTAL DES ENTRÉES | H7: TOTAL DES SORTIES | K7: SOLDE DE L'ANNÉE | N7: MIS DE CÔTÉ | Q7: EN ATTENTE / PRÉVU
B8: =COUNT(J_Date) | E8: =SUMIFS(J_Montant,J_Annee,Annee_Travail,J_Type,"Revenu",J_Statut,"<>Annulé",J_Statut,"<>Prévu") | H8: =SUMIFS(J_Montant,J_Annee,Annee_Travail,J_Type,"<>Revenu",J_Type,"<>Transfert",J_Statut,"<>Annulé",J_Statut,"<>Prévu") | K8: =SUMIFS(J_Montant,J_Annee,Annee_Travail,J_Type,"Revenu",J_Statut,"<>Annulé",J_Statut,"<>Prévu")-SUMIFS(J_Montant,J_Annee,Annee_Travail,J_Type,"<>Revenu",J_Type,"<>Transfert",J_Statut,"<>Annulé",J_Statut,"<>Prévu") | N8: =SUMIFS(J_Montant,J_Annee,Annee_Travail,J_Type,"Épargne",J_Statut,"<>Annulé",J_Statut,"<>Prévu")+SUMIFS(J_Montant,J_Annee,Annee_Travail,J_Type,"Investissement",J_Statut,"<>Annulé",J_Statut,"<>Prévu") | Q8: =SUMIFS(J_Montant,J_Annee,Annee_Travail,J_Statut,"Prévu")+SUMIFS(J_Montant,J_Annee,Annee_Travail,J_Statut,"En attente")
B9: ="Dernière saisie : "&IF(COUNT(J_Date)=0,"—",RIGHT("0"&DAY(MAX(J_Date)),2)&"/"&RIGHT("0"&MONTH(MAX(J_Date)),2)&"/"&YEAR(MAX(J_Date))) | E9: ="Année "&Annee_Travail | H9: Dépenses + épargne + crédits | N9: Épargne + investissement | Q9: Engagements non décaissés
B11: ① À REMPLIR | I11: ② CALCULÉ POUR VOUS | M11: ③ COMPLÉMENTS — facultatifs | T11: ④ TECHNIQUE
B12: Date | C12: Type d'opération | D12: Module | E12: Catégorie | F12: Libellé / Description | G12: Montant | H12: Compte | I12: Sens | J12: ENTRÉE | K12: SORTIE | L12: Solde cumulé | M12: Devise | N12: Moyen de paiement | O12: Projet / Bien | P12: Nature | Q12: Statut | R12: Récurrent | S12: Notes | T12: Taux | U12: Montant (devise de base) | V12: Mois | W12: Année
I13: =IF($C13="","",IFERROR(INDEX(Sens_Types,MATCH($C13,Liste_Types,0)),"")) | J13: =IF($I13="▲ ENTRÉE",$U13,"") | K13: =IF($I13="▼ SORTIE",$U13,"") | L13: =Solde_Initial+N($J13)-N($K13) | T13: =IF($G13="","",IFERROR(INDEX(Taux_Devises,MATCH(IF($M13="",Devise_Base,$M13),Codes_Devises,0)),1)) | U13: =IF($G13="","",ROUND($G13*$T13,2)) | V13: =IF($B13="","",MONTH($B13)) | W13: =IF($B13="","",YEAR($B13))
I14: =IF($C14="","",IFERROR(INDEX(Sens_Types,MATCH($C14,Liste_Types,0)),"")) | J14: =IF($I14="▲ ENTRÉE",$U14,"") | K14: =IF($I14="▼ SORTIE",$U14,"") | L14: =$L13+N($J14)-N($K14) | T14: =IF($G14="","",IFERROR(INDEX(Taux_Devises,MATCH(IF($M14="",Devise_Base,$M14),Codes_Devises,0)),1)) | U14: =IF($G14="","",ROUND($G14*$T14,2)) | V14: =IF($B14="","",MONTH($B14)) | W14: =IF($B14="","",YEAR($B14))
I15: =IF($C15="","",IFERROR(INDEX(Sens_Types,MATCH($C15,Liste_Types,0)),"")) | J15: =IF($I15="▲ ENTRÉE",$U15,"") | K15: =IF($I15="▼ SORTIE",$U15,"") | L15: =$L14+N($J15)-N($K15) | T15: =IF($G15="","",IFERROR(INDEX(Taux_Devises,MATCH(IF($M15="",Devise_Base,$M15),Codes_Devises,0)),1)) | U15: =IF($G15="","",ROUND($G15*$T15,2)) | V15: =IF($B15="","",MONTH($B15)) | W15: =IF($B15="","",YEAR($B15))
I16: =IF($C16="","",IFERROR(INDEX(Sens_Types,MATCH($C16,Liste_Types,0)),"")) | J16: =IF($I16="▲ ENTRÉE",$U16,"") | K16: =IF($I16="▼ SORTIE",$U16,"") | L16: =$L15+N($J16)-N($K16) | T16: =IF($G16="","",IFERROR(INDEX(Taux_Devises,MATCH(IF($M16="",Devise_Base,$M16),Codes_Devises,0)),1)) | U16: =IF($G16="","",ROUND($G16*$T16,2)) | V16: =IF($B16="","",MONTH($B16)) | W16: =IF($B16="","",YEAR($B16))
I17: =IF($C17="","",IFERROR(INDEX(Sens_Types,MATCH($C17,Liste_Types,0)),"")) | J17: =IF($I17="▲ ENTRÉE",$U17,"") | K17: =IF($I17="▼ SORTIE",$U17,"") | L17: =$L16+N($J17)-N($K17) | T17: =IF($G17="","",IFERROR(INDEX(Taux_Devises,MATCH(IF($M17="",Devise_Base,$M17),Codes_Devises,0)),1)) | U17: =IF($G17="","",ROUND($G17*$T17,2)) | V17: =IF($B17="","",MONTH($B17)) | W17: =IF($B17="","",YEAR($B17))
I18: =IF($C18="","",IFERROR(INDEX(Sens_Types,MATCH($C18,Liste_Types,0)),"")) | J18: =IF($I18="▲ ENTRÉE",$U18,"") | K18: =IF($I18="▼ SORTIE",$U18,"") | L18: =$L17+N($J18)-N($K18) | T18: =IF($G18="","",IFERROR(INDEX(Taux_Devises,MATCH(IF($M18="",Devise_Base,$M18),Codes_Devises,0)),1)) | U18: =IF($G18="","",ROUND($G18*$T18,2)) | V18: =IF($B18="","",MONTH($B18)) | W18: =IF($B18="","",YEAR($B18))
I19: =IF($C19="","",IFERROR(INDEX(Sens_Types,MATCH($C19,Liste_Types,0)),"")) | J19: =IF($I19="▲ ENTRÉE",$U19,"") | K19: =IF($I19="▼ SORTIE",$U19,"") | L19: =$L18+N($J19)-N($K19) | T19: =IF($G19="","",IFERROR(INDEX(Taux_Devises,MATCH(IF($M19="",Devise_Base,$M19),Codes_Devises,0)),1)) | U19: =IF($G19="","",ROUND($G19*$T19,2)) | V19: =IF($B19="","",MONTH($B19)) | W19: =IF($B19="","",YEAR($B19))
I20: =IF($C20="","",IFERROR(INDEX(Sens_Types,MATCH($C20,Liste_Types,0)),"")) | J20: =IF($I20="▲ ENTRÉE",$U20,"") | K20: =IF($I20="▼ SORTIE",$U20,"") | L20: =$L19+N($J20)-N($K20) | T20: =IF($G20="","",IFERROR(INDEX(Taux_Devises,MATCH(IF($M20="",Devise_Base,$M20),Codes_Devises,0)),1)) | U20: =IF($G20="","",ROUND($G20*$T20,2)) | V20: =IF($B20="","",MONTH($B20)) | W20: =IF($B20="","",YEAR($B20))
I21: =IF($C21="","",IFERROR(INDEX(Sens_Types,MATCH($C21,Liste_Types,0)),"")) | J21: =IF($I21="▲ ENTRÉE",$U21,"") | K21: =IF($I21="▼ SORTIE",$U21,"") | L21: =$L20+N($J21)-N($K21) | T21: =IF($G21="","",IFERROR(INDEX(Taux_Devises,MATCH(IF($M21="",Devise_Base,$M21),Codes_Devises,0)),1)) | U21: =IF($G21="","",ROUND($G21*$T21,2)) | V21: =IF($B21="","",MONTH($B21)) | W21: =IF($B21="","",YEAR($B21))
I22: =IF($C22="","",IFERROR(INDEX(Sens_Types,MATCH($C22,Liste_Types,0)),"")) | J22: =IF($I22="▲ ENTRÉE",$U22,"") | K22: =IF($I22="▼ SORTIE",$U22,"") | L22: =$L21+N($J22)-N($K22) | T22: =IF($G22="","",IFERROR(INDEX(Taux_Devises,MATCH(IF($M22="",Devise_Base,$M22),Codes_Devises,0)),1)) | U22: =IF($G22="","",ROUND($G22*$T22,2)) | V22: =IF($B22="","",MONTH($B22)) | W22: =IF($B22="","",YEAR($B22))
I23: =IF($C23="","",IFERROR(INDEX(Sens_Types,MATCH($C23,Liste_Types,0)),"")) | J23: =IF($I23="▲ ENTRÉE",$U23,"") | K23: =IF($I23="▼ SORTIE",$U23,"") | L23: =$L22+N($J23)-N($K23) | T23: =IF($G23="","",IFERROR(INDEX(Taux_Devises,MATCH(IF($M23="",Devise_Base,$M23),Codes_Devises,0)),1)) | U23: =IF($G23="","",ROUND($G23*$T23,2)) | V23: =IF($B23="","",MONTH($B23)) | W23: =IF($B23="","",YEAR($B23))
I24: =IF($C24="","",IFERROR(INDEX(Sens_Types,MATCH($C24,Liste_Types,0)),"")) | J24: =IF($I24="▲ ENTRÉE",$U24,"") | K24: =IF($I24="▼ SORTIE",$U24,"") | L24: =$L23+N($J24)-N($K24) | T24: =IF($G24="","",IFERROR(INDEX(Taux_Devises,MATCH(IF($M24="",Devise_Base,$M24),Codes_Devises,0)),1)) | U24: =IF($G24="","",ROUND($G24*$T24,2)) | V24: =IF($B24="","",MONTH($B24)) | W24: =IF($B24="","",YEAR($B24))
I25: =IF($C25="","",IFERROR(INDEX(Sens_Types,MATCH($C25,Liste_Types,0)),"")) | J25: =IF($I25="▲ ENTRÉE",$U25,"") | K25: =IF($I25="▼ SORTIE",$U25,"") | L25: =$L24+N($J25)-N($K25) | T25: =IF($G25="","",IFERROR(INDEX(Taux_Devises,MATCH(IF($M25="",Devise_Base,$M25),Codes_Devises,0)),1)) | U25: =IF($G25="","",ROUND($G25*$T25,2)) | V25: =IF($B25="","",MONTH($B25)) | W25: =IF($B25="","",YEAR($B25))
... I3012: =IF($C3012="","",IFERROR(INDEX(Sens_Types,MATCH($C3012,Liste_Types,0)),"")) | J3012: =IF($I3012="▲ ENTRÉE",$U3012,"") | K3012: =IF($I3012="▼ SORTIE",$U3012,"") | L3012: =$L3011+N($J3012)-N($K3012) | T3012: =IF($G3012="","",IFERROR(INDEX(Taux_Devises,MATCH(IF($M3012="",Devise_Base,$M3012),Codes_Devises,0)),1)) | U3012: =IF($G3012="","",ROUND($G3012*$T3012,2)) | V3012: =IF($B3012="","",MONTH($B3012)) | W3012: =IF($B3012="","",YEAR($B3012))

Sheet Tableau de Bord
B1: TABLEAU DE BORD MENSUEL
B2: ="Suivi de "&Nom_Foyer&" • "&Mois_Suivi&" "&Annee_Travail&" • périmètre : "&Perimetre&" • montants en "&Devise_Base
B3: ⌂ ACCUEIL | D3: ① MES INFOS | F3: ② ESTIMATION | H3: ③ BUDGET SMART | J3: TABLEAU DE BORD | L3: BUDGET 12 MOIS
B4: PÉRIODE ANALYSÉE | D4: 2026 | E4: ◄ année | F4: mois ► | G4: Janvier | H4: =IFERROR(MATCH($G$4,Liste_Mois,0),1) | I4: ="Mise à jour au "&RIGHT("0"&DAY(TODAY()),2)&"/"&RIGHT("0"&MONTH(TODAY()),2)&"/"&YEAR(TODAY())&" • "&COUNT(J_Date)&" écritures enregistrées • Devise : "&Devise_Base&" ("&Symbole_Base&")"
B6: REVENUS DU MOIS | E6: DÉPENSES DU MOIS | H6: ÉPARGNE + INVESTI. | K6: SOLDE DU MOIS | N6: TAUX D'ÉPARGNE
B7: =INDEX(Calculs!$D$6:$O$17,Mois_Num,1) | E7: =INDEX(Calculs!$D$6:$O$17,Mois_Num,2) | H7: =INDEX(Calculs!$D$6:$O$17,Mois_Num,3)+INDEX(Calculs!$D$6:$O$17,Mois_Num,4) | K7: =INDEX(Calculs!$D$6:$O$17,Mois_Num,7) | N7: =INDEX(Calculs!$D$6:$O$17,Mois_Num,9)
B8: ="Prévu : "&FIXED(INDEX(Calculs!$D$6:$O$17,Mois_Num,12),0) | E8: ="Budget : "&FIXED(INDEX(Calculs!$D$6:$O$17,Mois_Num,10),0) | H8: ="Objectif : "&FIXED(Taux_Cible*INDEX(Calculs!$D$6:$O$17,Mois_Num,1),0) | K8: =IF(INDEX(Calculs!$D$6:$O$17,Mois_Num,7)>=0,"Excédent","Déficit à couvrir") | N8: ="Cible : "&ROUND(Taux_Cible*100,0)&" %"
B10: BUDGET CONSOMMÉ | E10: TRÉSORERIE CUMULÉE | H10: CHARGES FIXES DU MOIS | K10: RESTE À VIVRE | N10: DÉPENSE MOYENNE / JOUR
B11: =IFERROR(INDEX(Calculs!$D$6:$O$17,Mois_Num,2)/INDEX(Calculs!$D$6:$O$17,Mois_Num,10),0) | E11: =INDEX(Calculs!$D$6:$O$17,Mois_Num,8) | H11: =SUMIFS(J_Montant,J_Annee,Annee_Travail,J_Mois,Mois_Num,J_Nature,"Fixe",J_Type,"<>Revenu",J_Type,"<>Transfert",J_Module,Perimetre_Filtre,J_Statut,"<>Annulé",J_Statut,"<>Prévu") | K11: =INDEX(Calculs!$D$6:$O$17,Mois_Num,1)-SUMIFS(J_Montant,J_Annee,Annee_Travail,J_Mois,Mois_Num,J_Nature,"Fixe",J_Type,"<>Revenu",J_Type,"<>Transfert",J_Module,Perimetre_Filtre,J_Statut,"<>Annulé",J_Statut,"<>Prévu") | N11: =IFERROR(INDEX(Calculs!$D$6:$O$17,Mois_Num,2)/DAY(EOMONTH(DATE(Annee_Travail,Mois_Num,1),0)),0)
B12: ="Écart : "&FIXED(INDEX(Calculs!$D$6:$O$17,Mois_Num,11),0) | E12: ="Dont comptes : "&FIXED(Paramètres!$H$61,0) | H12: Loyer, abonnements, mensualités | K12: Revenus – charges fixes | N12: Sur le mois sélectionné
B14: RÉPARTITION DU MOIS SÉLECTIONNÉ
K15: Top 10 des dépenses du mois | M15: Montant | O15: Part
K16: =IF(Calculs!$C$183="","—",Calculs!$C$183) | M16: =Calculs!$D$183 | O16: =Calculs!$E$183
K17: =IF(Calculs!$C$184="","—",Calculs!$C$184) | M17: =Calculs!$D$184 | O17: =Calculs!$E$184
K18: =IF(Calculs!$C$185="","—",Calculs!$C$185) | M18: =Calculs!$D$185 | O18: =Calculs!$E$185
K19: =IF(Calculs!$C$186="","—",Calculs!$C$186) | M19: =Calculs!$D$186 | O19: =Calculs!$E$186
K20: =IF(Calculs!$C$187="","—",Calculs!$C$187) | M20: =Calculs!$D$187 | O20: =Calculs!$E$187
K21: =IF(Calculs!$C$188="","—",Calculs!$C$188) | M21: =Calculs!$D$188 | O21: =Calculs!$E$188
K22: =IF(Calculs!$C$189="","—",Calculs!$C$189) | M22: =Calculs!$D$189 | O22: =Calculs!$E$189
K23: =IF(Calculs!$C$190="","—",Calculs!$C$190) | M23: =Calculs!$D$190 | O23: =Calculs!$E$190
K24: =IF(Calculs!$C$191="","—",Calculs!$C$191) | M24: =Calculs!$D$191 | O24: =Calculs!$E$191
K25: =IF(Calculs!$C$192="","—",Calculs!$C$192) | M25: =Calculs!$D$192 | O25: =Calculs!$E$192
B28: PRÉVU vs RÉALISÉ — MOIS SÉLECTIONNÉ
C29: Module | D29: Prévu | E29: Réalisé | F29: Écart | G29: % consommé | H29: Statut
C30: Général | D30: =Calculs!$C$301 | E30: =Calculs!$D$301 | F30: =Calculs!$E$301 | G30: =IFERROR($E30/$D30,0) | H30: =IF($D30=0,"Non budgété",IF($G30>1,"⚠ Dépassement",IF($G30>Seuil_Alerte,"Vigilance","✓ Sous contrôle")))
C31: Mariage | D31: =Calculs!$C$302 | E31: =Calculs!$D$302 | F31: =Calculs!$E$302 | G31: =IFERROR($E31/$D31,0) | H31: =IF($D31=0,"Non budgété",IF($G31>1,"⚠ Dépassement",IF($G31>Seuil_Alerte,"Vigilance","✓ Sous contrôle")))
C32: Immobilier | D32: =Calculs!$C$303 | E32: =Calculs!$D$303 | F32: =Calculs!$E$303 | G32: =IFERROR($E32/$D32,0) | H32: =IF($D32=0,"Non budgété",IF($G32>1,"⚠ Dépassement",IF($G32>Seuil_Alerte,"Vigilance","✓ Sous contrôle")))
C33: Business | D33: =Calculs!$C$304 | E33: =Calculs!$D$304 | F33: =Calculs!$E$304 | G33: =IFERROR($E33/$D33,0) | H33: =IF($D33=0,"Non budgété",IF($G33>1,"⚠ Dépassement",IF($G33>Seuil_Alerte,"Vigilance","✓ Sous contrôle")))
C34: TOTAL | D34: =SUM(D30:D33) | E34: =SUM(E30:E33) | F34: =SUM(F30:F33) | G34: =IFERROR(E34/D34,0)
B38: DÎME DU MOIS
C39: Revenus soumis à la dîme | F39: =INDEX(Calculs!$C$308:$C$319,Mois_Num)
C40: Dîme due | F40: =INDEX(Calculs!$D$308:$D$319,Mois_Num)
C41: Déjà versée | F41: =INDEX(Calculs!$E$308:$E$319,Mois_Num)
C42: Reste à verser | F42: =INDEX(Calculs!$F$308:$F$319,Mois_Num)
C43: =IF(Dime_Active<>"Oui","Dîme désactivée dans Paramètres.",IF($F$40=0,"Aucun revenu soumis ce mois-ci.",IF($F$42<=0,"✓ Dîme du mois entièrement versée.","Il reste "&FIXED($F$42,0)&" "&Symbole_Base&" à verser.")))
B46: ALERTES & SIGNAUX AUTOMATIQUES
B47: =IF(INDEX(Calculs!$D$6:$O$17,Mois_Num,7)<0,"🔴 Le mois est déficitaire de "&FIXED(ABS(INDEX(Calculs!$D$6:$O$17,Mois_Num,7)),0)&" "&Symbole_Base&". Réduisez les postes variables ou puisez dans vos réserves.","🟢 Le mois est excédentaire.")
B48: =IF(INDEX(Calculs!$D$6:$O$17,Mois_Num,9)<Taux_Cible,"🟠 Taux d'épargne de "&ROUND(INDEX(Calculs!$D$6:$O$17,Mois_Num,9)*100,1)&" %"&" contre "&ROUND(Taux_Cible*100,0)&" %"&" visé.","🟢 Objectif d'épargne atteint.")
B49: =IF(AND(INDEX(Calculs!$D$6:$O$17,Mois_Num,10)>0,INDEX(Calculs!$D$6:$O$17,Mois_Num,2)>INDEX(Calculs!$D$6:$O$17,Mois_Num,10)),"🔴 Budget de dépenses dépassé de "&FIXED(INDEX(Calculs!$D$6:$O$17,Mois_Num,2)-INDEX(Calculs!$D$6:$O$17,Mois_Num,10),0)&" "&Symbole_Base&".",IF(INDEX(Calculs!$D$6:$O$17,Mois_Num,10)=0,"⚪ Aucun budget saisi pour ce mois dans le Estimation annuelle.","🟢 Dépenses contenues dans le budget."))
B50: =IF(COUNTIFS(Récurrents!$J$8:$J$57,"Oui",Récurrents!$H$8:$H$57,"<"&TODAY())>0,"🔴 "&COUNTIFS(Récurrents!$J$8:$J$57,"Oui",Récurrents!$H$8:$H$57,"<"&TODAY())&" échéance(s) récurrente(s) en retard.","🟢 Aucune échéance récurrente en retard.")
B51: =IF(SUMIFS(J_Montant,J_Annee,Annee_Travail,J_Statut,"Prévu")>0,"🟠 "&FIXED(SUMIFS(J_Montant,J_Annee,Annee_Travail,J_Statut,"Prévu"),0)&" "&Symbole_Base&" d'engagements prévus non encore décaissés.","🟢 Aucun engagement en attente.")
B52: =IF(Paramètres!$H$61<0,"🔴 Trésorerie de vos comptes négative.",IF(Paramètres!$H$61<INDEX(Calculs!$D$6:$O$17,Mois_Num,2),"🟠 Votre trésorerie couvre moins d'un mois de dépenses.","🟢 Trésorerie confortable."))
B53: =IF(Dime_Active<>"Oui","⚪ Dîme désactivée.",IF(INDEX(Calculs!$F$308:$F$319,Mois_Num)>0,"🟠 Dîme : il reste "&FIXED(INDEX(Calculs!$F$308:$F$319,Mois_Num),0)&" "&Symbole_Base&" à verser ce mois-ci.","🟢 Dîme du mois à jour."))
B54: =IF(COUNT(J_Date)=0,"⚪ Commencez par saisir vos premières opérations dans le Journal.","🟢 "&COUNT(J_Date)&" opérations enregistrées depuis le début.")
B56: Changez l'année ou le mois en haut de cette feuille : tous les indicateurs, graphiques et alertes se recalculent instantanément à partir du Journal.
B78: GRAPHIQUES

Sheet Budget 12 Mois
B1: BUDGET 12 MOIS — ENTRÉES & SORTIES
B2: ="Année "&Annee_Travail&" • "&Nom_Foyer&" • Prévu issu du Estimation annuelle, Réel issu du Journal • montants en "&Devise_Base
B3: ⌂ ACCUEIL | G3: ① MES INFOS | L3: ② ESTIMATION | Q3: ③ BUDGET SMART | V3: TABLEAU DE BORD | AA3: BUDGET 12 MOIS
B5: Cette feuille ne se remplit pas à la main. Colonne « Prévu » = ce que vous avez inscrit dans le Estimation annuelle. Colonne « Réel » = ce que vous avez enregistré dans le Journal. Changez l'année en haut du Tableau de bord.
B8: POSTE | D8: Janvier | F8: Février | H8: Mars | J8: Avril | L8: Mai | N8: Juin | P8: Juillet | R8: Août | T8: Septembre | V8: Octobre | X8: Novembre | Z8: Décembre | AB8: TOTAL DE L'ANNÉE
D9: Prévu | E9: Réel | F9: Prévu | G9: Réel | H9: Prévu | I9: Réel | J9: Prévu | K9: Réel | L9: Prévu | M9: Réel | N9: Prévu | O9: Réel | P9: Prévu | Q9: Réel | R9: Prévu | S9: Réel | T9: Prévu | U9: Réel | V9: Prévu | W9: Réel | X9: Prévu | Y9: Réel | Z9: Prévu | AA9: Réel | AB9: Prévu | AC9: Réel | AD9: Écart | AE9: % consommé
B10: A ▸ ENTRÉES — REVENUS
B11: 1 | C11: Salaire | D11: =IF($C11="",0,SUMIFS(P_M1,P_Annee,Annee_Travail,P_Cat,$C11,P_Type,"Revenu")) | E11: =IF($C11="",0,SUMIFS(J_Montant,J_Annee,Annee_Travail,J_Mois,1,J_Cat,$C11,J_Type,"Revenu",J_Statut,"<>Annulé",J_Statut,"<>Prévu")) | F11: =IF($C11="",0,SUMIFS(P_M2,P_Annee,Annee_Travail,P_Cat,$C11,P_Type,"Revenu")) | G11: =IF($C11="",0,SUMIFS(J_Montant,J_Annee,Annee_Travail,J_Mois,2,J_Cat,$C11,J_Type,"Revenu",J_Statut,"<>Annulé",J_Statut,"<>Prévu")) | H11: =IF($C11="",0,SUMIFS(P_M3,P_Annee,Annee_Travail,P_Cat,$C11,P_Type,"Revenu")) | I11: =IF($C11="",0,SUMIFS(J_Montant,J_Annee,Annee_Travail,J_Mois,3,J_Cat,$C11,J_Type,"Revenu",J_Statut,"<>Annulé",J_Statut,"<>Prévu")) | J11: =IF($C11="",0,SUMIFS(P_M4,P_Annee,Annee_Travail,P_Cat,$C11,P_Type,"Revenu")) | K11: =IF($C11="",0,SUMIFS(J_Montant,J_Annee,Annee_Travail,J_Mois,4,J_Cat,$C11,J_Type,"Revenu",J_Statut,"<>Annulé",J_Statut,"<>Prévu")) | L11: =IF($C11="",0,SUMIFS(P_M5,P_Annee,Annee_Travail,P_Cat,$C11,P_Type,"Revenu")) | M11: =IF($C11="",0,SUMIFS(J_Montant,J_Annee,Annee_Travail,J_Mois,5,J_Cat,$C11,J_Type,"Revenu",J_Statut,"<>Annulé",J_Statut,"<>Prévu")) | N11: =IF($C11="",0,SUMIFS(P_M6,P_Annee,Annee_Travail,P_Cat,$C11,P_Type,"Revenu")) | O11: =IF($C11="",0,SUMIFS(J_Montant,J_Annee,Annee_Travail,J_Mois,6,J_Cat,$C11,J_Type,"Revenu",J_Statut,"<>Annulé",J_Statut,"<>Prévu")) | P11: =IF($C11="",0,SUMIFS(P_M7,P_Annee,Annee_Travail,P_Cat,$C11,P_Type,"Revenu")) | Q11: =IF($C11="",0,SUMIFS(J_Montant,J_Annee,Annee_Travail,J_Mois,7,J_Cat,$C11,J_Type,"Revenu",J_Statut,"<>Annulé",J_Statut,"<>Prévu")) | R11: =IF($C11="",0,SUMIFS(P_M8,P_Annee,Annee_Travail,P_Cat,$C11,P_Type,"Revenu")) | S11: =IF($C11="",0,SUMIFS(J_Montant,J_Annee,Annee_Travail,J_Mois,8,J_Cat,$C11,J_Type,"Revenu",J_Statut,"<>Annulé",J_Statut,"<>Prévu")) | T11: =IF($C11="",0,SUMIFS(P_M9,P_Annee,Annee_Travail,P_Cat,$C11,P_Type,"Revenu")) | U11: =IF($C11="",0,SUMIFS(J_Montant,J_Annee,Annee_Travail,J_Mois,9,J_Cat,$C11,J_Type,"Revenu",J_Statut,"<>Annulé",J_Statut,"<>Prévu")) | V11: =IF($C11="",0,SUMIFS(P_M10,P_Annee,Annee_Travail,P_Cat,$C11,P_Type,"Revenu")) | W11: =IF($C11="",0,SUMIFS(J_Montant,J_Annee,Annee_Travail,J_Mois,10,J_Cat,$C11,J_Type,"Revenu",J_Statut,"<>Annulé",J_Statut,"<>Prévu")) | X11: =IF($C11="",0,SUMIFS(P_M11,P_Annee,Annee_Travail,P_Cat,$C11,P_Type,"Revenu")) | Y11: =IF($C11="",0,SUMIFS(J_Montant,J_Annee,Annee_Travail,J_Mois,11,J_Cat,$C11,J_Type,"Revenu",J_Statut,"<>Annulé",J_Statut,"<>Prévu")) | Z11: =IF($C11="",0,SUMIFS(P_M12,P_Annee,Annee_Travail,P_Cat,$C11,P_Type,"Revenu")) | AA11: =IF($C11="",0,SUMIFS(J_Montant,J_Annee,Annee_Travail,J_Mois,12,J_Cat,$C11,J_Type,"Revenu",J_Statut,"<>Annulé",J_Statut,"<>Prévu")) | AB11: =D11+F11+H11+J11+L11+N11+P11+R11+T11+V11+X11+Z11 | AC11: =E11+G11+I11+K11+M11+O11+Q11+S11+U11+W11+Y11+AA11 | AD11: =$AC11-$AB11 | AE11: =IFERROR($AC11/$AB11,0)
B12: 2 | C12: Prime / 13e mois | D12: =IF($C12="",0,SUMIFS(P_M1,P_Annee,Annee_Travail,P_Cat,$C12,P_Type,"Revenu")) | E12: =IF($C12="",0,SUMIFS(J_Montant,J_Annee,Annee_Travail,J_Mois,1,J_Cat,$C12,J_Type,"Revenu",J_Statut,"<>Annulé",J_Statut,"<>Prévu")) | F12: =IF($C12="",0,SUMIFS(P_M2,P_Annee,Annee_Travail,P_Cat,$C12,P_Type,"Revenu")) | G12: =IF($C12="",0,SUMIFS(J_Montant,J_Annee,Annee_Travail,J_Mois,2,J_Cat,$C12,J_Type,"Revenu",J_Statut,"<>Annulé",J_Statut,"<>Prévu")) | H12: =IF($C12="",0,SUMIFS(P_M3,P_Annee,Annee_Travail,P_Cat,$C12,P_Type,"Revenu")) | I12: =IF($C12="",0,SUMIFS(J_Montant,J_Annee,Annee_Travail,J_Mois,3,J_Cat,$C12,J_Type,"Revenu",J_Statut,"<>Annulé",J_Statut,"<>Prévu")) | J12: =IF($C12="",0,SUMIFS(P_M4,P_Annee,Annee_Travail,P_Cat,$C12,P_Type,"Revenu")) | K12: =IF($C12="",0,SUMIFS(J_Montant,J_Annee,Annee_Travail,J_Mois,4,J_Cat,$C12,J_Type,"Revenu",J_Statut,"<>Annulé",J_Statut,"<>Prévu")) | L12: =IF($C12="",0,SUMIFS(P_M5,P_Annee,Annee_Travail,P_Cat,$C12,P_Type,"Revenu")) | M12: =IF($C12="",0,SUMIFS(J_Montant,J_Annee,Annee_Travail,J_Mois,5,J_Cat,$C12,J_Type,"Revenu",J_Statut,"<>Annulé",J_Statut,"<>Prévu")) | N12: =IF($C12="",0,SUMIFS(P_M6,P_Annee,Annee_Travail,P_Cat,$C12,P_Type,"Revenu")) | O12: =IF($C12="",0,SUMIFS(J_Montant,J_Annee,Annee_Travail,J_Mois,6,J_Cat,$C12,J_Type,"Revenu",J_Statut,"<>Annulé",J_Statut,"<>Prévu")) | P12: =IF($C12="",0,SUMIFS(P_M7,P_Annee,Annee_Travail,P_Cat,$C12,P_Type,"Revenu")) | Q12: =IF($C12="",0,SUMIFS(J_Montant,J_Annee,Annee_Travail,J_Mois,7,J_Cat,$C12,J_Type,"Revenu",J_Statut,"<>Annulé",J_Statut,"<>Prévu")) | R12: =IF($C12="",0,SUMIFS(P_M8,P_Annee,Annee_Travail,P_Cat,$C12,P_Type,"Revenu")) | S12: =IF($C12="",0,SUMIFS(J_Montant,J_Annee,Annee_Travail,J_Mois,8,J_Cat,$C12,J_Type,"Revenu",J_Statut,"<>Annulé",J_Statut,"<>Prévu")) | T12: =IF($C12="",0,SUMIFS(P_M9,P_Annee,Annee_Travail,P_Cat,$C12,P_Type,"Revenu")) | U12: =IF($C12="",0,SUMIFS(J_Montant,J_Annee,Annee_Travail,J_Mois,9,J_Cat,$C12,J_Type,"Revenu",J_Statut,"<>Annulé",J_Statut,"<>Prévu")) | V12: =IF($C12="",0,SUMIFS(P_M10,P_Annee,Annee_Travail,P_Cat,$C12,P_Type,"Revenu")) | W12: =IF($C12="",0,SUMIFS(J_Montant,J_Annee,Annee_Travail,J_Mois,10,J_Cat,$C12,J_Type,"Revenu",J_Statut,"<>Annulé",J_Statut,"<>Prévu")) | X12: =IF($C12="",0,SUMIFS(P_M11,P_Annee,Annee_Travail,P_Cat,$C12,P_Type,"Revenu")) | Y12: =IF($C12="",0,SUMIFS(J_Montant,J_Annee,Annee_Travail,J_Mois,11,J_Cat,$C12,J_Type,"Revenu",J_Statut,"<>Annulé",J_Statut,"<>Prévu")) | Z12: =IF($C12="",0,SUMIFS(P_M12,P_Annee,Annee_Travail,P_Cat,$C12,P_Type,"Revenu")) | AA12: =IF($C12="",0,SUMIFS(J_Montant,J_Annee,Annee_Travail,J_Mois,12,J_Cat,$C12,J_Type,"Revenu",J_Statut,"<>Annulé",J_Statut,"<>Prévu")) | AB12: =D12+F12+H12+J12+L12+N12+P12+R12+T12+V12+X12+Z12 | AC12: =E12+G12+I12+K12+M12+O12+Q12+S12+U12+W12+Y12+AA12 | AD12: =$AC12-$AB12 | AE12: =IFERROR($AC12/$AB12,0)
B13: 3 | C13: Freelance / Consulting | D13: =IF($C13="",0,SUMIFS(P_M1,P_Annee,Annee_Travail,P_Cat,$C13,P_Type,"Revenu")) | E13: =IF($C13="",0,SUMIFS(J_Montant,J_Annee,Annee_Travail,J_Mois,1,J_Cat,$C13,J_Type,"Revenu",J_Statut,"<>Annulé",J_Statut,"<>Prévu")) | F13: =IF($C13="",0,SUMIFS(P_M2,P_Annee,Annee_Travail,P_Cat,$C13,P_Type,"Revenu")) | G13: =IF($C13="",0,SUMIFS(J_Montant,J_Annee,Annee_Travail,J_Mois,2,J_Cat,$C13,J_Type,"Revenu",J_Statut,"<>Annulé",J_Statut,"<>Prévu")) | H13: =IF($C13="",0,SUMIFS(P_M3,P_Annee,Annee_Travail,P_Cat,$C13,P_Type,"Revenu")) | I13: =IF($C13="",0,SUMIFS(J_Montant,J_Annee,Annee_Travail,J_Mois,3,J_Cat,$C13,J_Type,"Revenu",J_Statut,"<>Annulé",J_Statut,"<>Prévu")) | J13: =IF($C13="",0,SUMIFS(P_M4,P_Annee,Annee_Travail,P_Cat,$C13,P_Type,"Revenu")) | K13: =IF($C13="",0,SUMIFS(J_Montant,J_Annee,Annee_Travail,J_Mois,4,J_Cat,$C13,J_Type,"Revenu",J_Statut,"<>Annulé",J_Statut,"<>Prévu")) | L13: =IF($C13="",0,SUMIFS(P_M5,P_Annee,Annee_Travail,P_Cat,$C13,P_Type,"Revenu")) | M13: =IF($C13="",0,SUMIFS(J_Montant,J_Annee,Annee_Travail,J_Mois,5,J_Cat,$C13,J_Type,"Revenu",J_Statut,"<>Annulé",J_Statut,"<>Prévu")) | N13: =IF($C13="",0,SUMIFS(P_M6,P_Annee,Annee_Travail,P_Cat,$C13,P_Type,"Revenu")) | O13: =IF($C13="",0,SUMIFS(J_Montant,J_Annee,Annee_Travail,J_Mois,6,J_Cat,$C13,J_Type,"Revenu",J_Statut,"<>Annulé",J_Statut,"<>Prévu")) | P13: =IF($C13="",0,SUMIFS(P_M7,P_Annee,Annee_Travail,P_Cat,$C13,P_Type,"Revenu")) | Q13: =IF($C13="",0,SUMIFS(J_Montant,J_Annee,Annee_Travail,J_Mois,7,J_Cat,$C13,J_Type,"Revenu",J_Statut,"<>Annulé",J_Statut,"<>Prévu")) | R13: =IF($C13="",0,SUMIFS(P_M8,P_Annee,Annee_Travail,P_Cat,$C13,P_Type,"Revenu")) | S13: =IF($C13="",0,SUMIFS(J_Montant,J_Annee,Annee_Travail,J_Mois,8,J_Cat,$C13,J_Type,"Revenu",J_Statut,"<>Annulé",J_Statut,"<>Prévu")) | T13: =IF($C13="",0,SUMIFS(P_M9,P_Annee,Annee_Travail,P_Cat,$C13,P_Type,"Revenu")) | U13: =IF($C13="",0,SUMIFS(J_Montant,J_Annee,Annee_Travail,J_Mois,9,J_Cat,$C13,J_Type,"Revenu",J_Statut,"<>Annulé",J_Statut,"<>Prévu")) | V13: =IF($C13="",0,SUMIFS(P_M10,P_Annee,Annee_Travail,P_Cat,$C13,P_Type,"Revenu")) | W13: =IF($C13="",0,SUMIFS(J_Montant,J_Annee,Annee_Travail,J_Mois,10,J_Cat,$C13,J_Type,"Revenu",J_Statut,"<>Annulé",J_Statut,"<>Prévu")) | X13: =IF($C13="",0,SUMIFS(P_M11,P_Annee,Annee_Travail,P_Cat,$C13,P_Type,"Revenu")) | Y13: =IF($C13="",0,SUMIFS(J_Montant,J_Annee,Annee_Travail,J_Mois,11,J_Cat,$C13,J_Type,"Revenu",J_Statut,"<>Annulé",J_Statut,"<>Prévu")) | Z13: =IF($C13="",0,SUMIFS(P_M12,P_Annee,Annee_Travail,P_Cat,$C13,P_Type,"Revenu")) | AA13: =IF($C13="",0,SUMIFS(J_Montant,J_Annee,Annee_Travail,J_Mois,12,J_Cat,$C13,J_Type,"Revenu",J_Statut,"<>Annulé",J_Statut,"<>Prévu")) | AB13: =D13+F13+H13+J13+L13+N13+P13+R13+T13+V13+X13+Z13 | AC13: =E13+G13+I13+K13+M13+O13+Q13+S13+U13+W13+Y13+AA13 | AD13: =$AC13-$AB13 | AE13: =IFERROR($AC13/$AB13,0)
B14: 4 | C14: Commerce / Ventes | D14: =IF($C14="",0,SUMIFS(P_M1,P_Annee,Annee_Travail,P_Cat,$C14,P_Type,"Revenu")) | E14: =IF($C14="",0,SUMIFS(J_Montant,J_Annee,Annee_Travail,J_Mois,1,J_Cat,$C14,J_Type,"Revenu",J_Statut,"<>Annulé",J_Statut,"<>Prévu")) | F14: =IF($C14="",0,SUMIFS(P_M2,P_Annee,Annee_Travail,P_Cat,$C14,P_Type,"Revenu")) | G14: =IF($C14="",0,SUMIFS(J_Montant,J_Annee,Annee_Travail,J_Mois,2,J_Cat,$C14,J_Type,"Revenu",J_Statut,"<>Annulé",J_Statut,"<>Prévu")) | H14: =IF($C14="",0,SUMIFS(P_M3,P_Annee,Annee_Travail,P_Cat,$C14,P_Type,"Revenu")) | I14: =IF($C14="",0,SUMIFS(J_Montant,J_Annee,Annee_Travail,J_Mois,3,J_Cat,$C14,J_Type,"Revenu",J_Statut,"<>Annulé",J_Statut,"<>Prévu")) | J14: =IF($C14="",0,SUMIFS(P_M4,P_Annee,Annee_Travail,P_Cat,$C14,P_Type,"Revenu")) | K14: =IF($C14="",0,SUMIFS(J_Montant,J_Annee,Annee_Travail,J_Mois,4,J_Cat,$C14,J_Type,"Revenu",J_Statut,"<>Annulé",J_Statut,"<>Prévu")) | L14: =IF($C14="",0,SUMIFS(P_M5,P_Annee,Annee_Travail,P_Cat,$C14,P_Type,"Revenu")) | M14: =IF($C14="",0,SUMIFS(J_Montant,J_Annee,Annee_Travail,J_Mois,5,J_Cat,$C14,J_Type,"Revenu",J_Statut,"<>Annulé",J_Statut,"<>Prévu")) | N14: =IF($C14="",0,SUMIFS(P_M6,P_Annee,Annee_Travail,P_Cat,$C14,P_Type,"Revenu")) | O14: =IF($C14="",0,SUMIFS(J_Montant,J_Annee,Annee_Travail,J_Mois,6,J_Cat,$C14,J_Type,"Revenu",J_Statut,"<>Annulé",J_Statut,"<>Prévu")) | P14: =IF($C14="",0,SUMIFS(P_M7,P_Annee,Annee_Travail,P_Cat,$C14,P_Type,"Revenu")) | Q14: =IF($C14="",0,SUMIFS(J_Montant,J_Annee,Annee_Travail,J_Mois,7,J_Cat,$C14,J_Type,"Revenu",J_Statut,"<>Annulé",J_Statut,"<>Prévu")) | R14: =IF($C14="",0,SUMIFS(P_M8,P_Annee,Annee_Travail,P_Cat,$C14,P_Type,"Revenu")) | S14: =IF($C14="",0,SUMIFS(J_Montant,J_Annee,Annee_Travail,J_Mois,8,J_Cat,$C14,J_Type,"Revenu",J_Statut,"<>Annulé",J_Statut,"<>Prévu")) | T14: =IF($C14="",0,SUMIFS(P_M9,P_Annee,Annee_Travail,P_Cat,$C14,P_Type,"Revenu")) | U14: =IF($C14="",0,SUMIFS(J_Montant,J_Annee,Annee_Travail,J_Mois,9,J_Cat,$C14,J_Type,"Revenu",J_Statut,"<>Annulé",J_Statut,"<>Prévu")) | V14: =IF($C14="",0,SUMIFS(P_M10,P_Annee,Annee_Travail,P_Cat,$C14,P_Type,"Revenu")) | W14: =IF($C14="",0,SUMIFS(J_Montant,J_Annee,Annee_Travail,J_Mois,10,J_Cat,$C14,J_Type,"Revenu",J_Statut,"<>Annulé",J_Statut,"<>Prévu")) | X14: =IF($C14="",0,SUMIFS(P_M11,P_Annee,Annee_Travail,P_Cat,$C14,P_Type,"Revenu")) | Y14: =IF($C14="",0,SUMIFS(J_Montant,J_Annee,Annee_Travail,J_Mois,11,J_Cat,$C14,J_Type,"Revenu",J_Statut,"<>Annulé",J_Statut,"<>Prévu")) | Z14: =IF($C14="",0,SUMIFS(P_M12,P_Annee,Annee_Travail,P_Cat,$C14,P_Type,"Revenu")) | AA14: =IF($C14="",0,SUMIFS(J_Montant,J_Annee,Annee_Travail,J_Mois,12,J_Cat,$C14,J_Type,"Revenu",J_Statut,"<>Annulé",J_Statut,"<>Prévu")) | AB14: =D14+F14+H14+J14+L14+N14+P14+R14+T14+V14+X14+Z14 | AC14: =E14+G14+I14+K14+M14+O14+Q14+S14+U14+W14+Y14+AA14 | AD14: =$AC14-$AB14 | AE14: =IFERROR($AC14/$AB14,0)
B15: 5 | C15: Loyers perçus | D15: =IF($C15="",0,SUMIFS(P_M1,P_Annee,Annee_Travail,P_Cat,$C15,P_Type,"Revenu")) | E15: =IF($C15="",0,SUMIFS(J_Montant,J_Annee,Annee_Travail,J_Mois,1,J_Cat,$C15,J_Type,"Revenu",J_Statut,"<>Annulé",J_Statut,"<>Prévu")) | F15: =IF($C15="",0,SUMIFS(P_M2,P_Annee,Annee_Travail,P_Cat,$C15,P_Type,"Revenu")) | G15: =IF($C15="",0,SUMIFS(J_Montant,J_Annee,Annee_Travail,J_Mois,2,J_Cat,$C15,J_Type,"Revenu",J_Statut,"<>Annulé",J_Statut,"<>Prévu")) | H15: =IF($C15="",0,SUMIFS(P_M3,P_Annee,Annee_Travail,P_Cat,$C15,P_Type,"Revenu")) | I15: =IF($C15="",0,SUMIFS(J_Montant,J_Annee,Annee_Travail,J_Mois,3,J_Cat,$C15,J_Type,"Revenu",J_Statut,"<>Annulé",J_Statut,"<>Prévu")) | J15: =IF($C15="",0,SUMIFS(P_M4,P_Annee,Annee_Travail,P_Cat,$C15,P_Type,"Revenu")) | K15: =IF($C15="",0,SUMIFS(J_Montant,J_Annee,Annee_Travail,J_Mois,4,J_Cat,$C15,J_Type,"Revenu",J_Statut,"<>Annulé",J_Statut,"<>Prévu")) | L15: =IF($C15="",0,SUMIFS(P_M5,P_Annee,Annee_Travail,P_Cat,$C15,P_Type,"Revenu")) | M15: =IF($C15="",0,SUMIFS(J_Montant,J_Annee,Annee_Travail,J_Mois,5,J_Cat,$C15,J_Type,"Revenu",J_Statut,"<>Annulé",J_Statut,"<>Prévu")) | N15: =IF($C15="",0,SUMIFS(P_M6,P_Annee,Annee_Travail,P_Cat,$C15,P_Type,"Revenu")) | O15: =IF($C15="",0,SUMIFS(J_Montant,J_Annee,Annee_Travail,J_Mois,6,J_Cat,$C15,J_Type,"Revenu",J_Statut,"<>Annulé",J_Statut,"<>Prévu")) | P15: =IF($C15="",0,SUMIFS(P_M7,P_Annee,Annee_Travail,P_Cat,$C15,P_Type,"Revenu")) | Q15: =IF($C15="",0,SUMIFS(J_Montant,J_Annee,Annee_Travail,J_Mois,7,J_Cat,$C15,J_Type,"Revenu",J_Statut,"<>Annulé",J_Statut,"<>Prévu")) | R15: =IF($C15="",0,SUMIFS(P_M8,P_Annee,Annee_Travail,P_Cat,$C15,P_Type,"Revenu")) | S15: =IF($C15="",0,SUMIFS(J_Montant,J_Annee,Annee_Travail,J_Mois,8,J_Cat,$C15,J_Type,"Revenu",J_Statut,"<>Annulé",J_Statut,"<>Prévu")) | T15: =IF($C15="",0,SUMIFS(P_M9,P_Annee,Annee_Travail,P_Cat,$C15,P_Type,"Revenu")) | U15: =IF($C15="",0,SUMIFS(J_Montant,J_Annee,Annee_Travail,J_Mois,9,J_Cat,$C15,J_Type,"Revenu",J_Statut,"<>Annulé",J_Statut,"<>Prévu")) | V15: =IF($C15="",0,SUMIFS(P_M10,P_Annee,Annee_Travail,P_Cat,$C15,P_Type,"Revenu")) | W15: =IF($C15="",0,SUMIFS(J_Montant,J_Annee,Annee_Travail,J_Mois,10,J_Cat,$C15,J_Type,"Revenu",J_Statut,"<>Annulé",J_Statut,"<>Prévu")) | X15: =IF($C15="",0,SUMIFS(P_M11,P_Annee,Annee_Travail,P_Cat,$C15,P_Type,"Revenu")) | Y15: =IF($C15="",0,SUMIFS(J_Montant,J_Annee,Annee_Travail,J_Mois,11,J_Cat,$C15,J_Type,"Revenu",J_Statut,"<>Annulé",J_Statut,"<>Prévu")) | Z15: =IF($C15="",0,SUMIFS(P_M12,P_Annee,Annee_Travail,P_Cat,$C15,P_Type,"Revenu")) | AA15: =IF($C15="",0,SUMIFS(J_Montant,J_Annee,Annee_Travail,J_Mois,12,J_Cat,$C15,J_Type,"Revenu",J_Statut,"<>Annulé",J_Statut,"<>Prévu")) | AB15: =D15+F15+H15+J15+L15+N15+P15+R15+T15+V15+X15+Z15 | AC15: =E15+G15+I15+K15+M15+O15+Q15+S15+U15+W15+Y15+AA15 | AD15: =$AC15-$AB15 | AE15: =IFERROR($AC15/$AB15,0)
B16: 6 | C16: Dividendes | D16: =IF($C16="",0,SUMIFS(P_M1,P_Annee,Annee_Travail,P_Cat,$C16,P_Type,"Revenu")) | E16: =IF($C16="",0,SUMIFS(J_Montant,J_Annee,Annee_Travail,J_Mois,1,J_Cat,$C16,J_Type,"Revenu",J_Statut,"<>Annulé",J_Statut,"<>Prévu")) | F16: =IF($C16="",0,SUMIFS(P_M2,P_Annee,Annee_Travail,P_Cat,$C16,P_Type,"Revenu")) | G16: =IF($C16="",0,SUMIFS(J_Montant,J_Annee,Annee_Travail,J_Mois,2,J_Cat,$C16,J_Type,"Revenu",J_Statut,"<>Annulé",J_Statut,"<>Prévu")) | H16: =IF($C16="",0,SUMIFS(P_M3,P_Annee,Annee_Travail,P_Cat,$C16,P_Type,"Revenu")) | I16: =IF($C16="",0,SUMIFS(J_Montant,J_Annee,Annee_Travail,J_Mois,3,J_Cat,$C16,J_Type,"Revenu",J_Statut,"<>Annulé",J_Statut,"<>Prévu")) | J16: =IF($C16="",0,SUMIFS(P_M4,P_Annee,Annee_Travail,P_Cat,$C16,P_Type,"Revenu")) | K16: =IF($C16="",0,SUMIFS(J_Montant,J_Annee,Annee_Travail,J_Mois,4,J_Cat,$C16,J_Type,"Revenu",J_Statut,"<>Annulé",J_Statut,"<>Prévu")) | L16: =IF($C16="",0,SUMIFS(P_M5,P_Annee,Annee_Travail,P_Cat,$C16,P_Type,"Revenu")) | M16: =IF($C16="",0,SUMIFS(J_Montant,J_Annee,Annee_Travail,J_Mois,5,J_Cat,$C16,J_Type,"Revenu",J_Statut,"<>Annulé",J_Statut,"<>Prévu")) | N16: =IF($C16="",0,SUMIFS(P_M6,P_Annee,Annee_Travail,P_Cat,$C16,P_Type,"Revenu")) | O16: =IF($C16="",0,SUMIFS(J_Montant,J_Annee,Annee_Travail,J_Mois,6,J_Cat,$C16,J_Type,"Revenu",J_Statut,"<>Annulé",J_Statut,"<>Prévu")) | P16: =IF($C16="",0,SUMIFS(P_M7,P_Annee,Annee_Travail,P_Cat,$C16,P_Type,"Revenu")) | Q16: =IF($C16="",0,SUMIFS(J_Montant,J_Annee,Annee_Travail,J_Mois,7,J_Cat,$C16,J_Type,"Revenu",J_Statut,"<>Annulé",J_Statut,"<>Prévu")) | R16: =IF($C16="",0,SUMIFS(P_M8,P_Annee,Annee_Travail,P_Cat,$C16,P_Type,"Revenu")) | S16: =IF($C16="",0,SUMIFS(J_Montant,J_Annee,Annee_Travail,J_Mois,8,J_Cat,$C16,J_Type,"Revenu",J_Statut,"<>Annulé",J_Statut,"<>Prévu")) | T16: =IF($C16="",0,SUMIFS(P_M9,P_Annee,Annee_Travail,P_Cat,$C16,P_Type,"Revenu")) | U16: =IF($C16="",0,SUMIFS(J_Montant,J_Annee,Annee_Travail,J_Mois,9,J_Cat,$C16,J_Type,"Revenu",J_Statut,"<>Annulé",J_Statut,"<>Prévu")) | V16: =IF($C16="",0,SUMIFS(P_M10,P_Annee,Annee_Travail,P_Cat,$C16,P_Type,"Revenu")) | W16: =IF($C16="",0,SUMIFS(J_Montant,J_Annee,Annee_Travail,J_Mois,10,J_Cat,$C16,J_Type,"Revenu",J_Statut,"<>Annulé",J_Statut,"<>Prévu")) | X16: =IF($C16="",0,SUMIFS(P_M11,P_Annee,Annee_Travail,P_Cat,$C16,P_Type,"Revenu")) | Y16: =IF($C16="",0,SUMIFS(J_Montant,J_Annee,Annee_Travail,J_Mois,11,J_Cat,$C16,J_Type,"Revenu",J_Statut,"<>Annulé",J_Statut,"<>Prévu")) | Z16: =IF($C16="",0,SUMIFS(P_M12,P_Annee,Annee_Travail,P_Cat,$C16,P_Type,"Revenu")) | AA16: =IF($C16="",0,SUMIFS(J_Montant,J_Annee,Annee_Travail,J_Mois,12,J_Cat,$C16,J_Type,"Revenu",J_Statut,"<>Annulé",J_Statut,"<>Prévu")) | AB16: =D16+F16+H16+J16+L16+N16+P16+R16+T16+V16+X16+Z16 | AC16: =E16+G16+I16+K16+M16+O16+Q16+S16+U16+W16+Y16+AA16 | AD16: =$AC16-$AB16 | AE16: =IFERROR($AC16/$AB16,0)
B17: 7 | C17: Intérêts perçus | D17: =IF($C17="",0,SUMIFS(P_M1,P_Annee,Annee_Travail,P_Cat,$C17,P_Type,"Revenu")) | E17: =IF($C17="",0,SUMIFS(J_Montant,J_Annee,Annee_Travail,J_Mois,1,J_Cat,$C17,J_Type,"Revenu",J_Statut,"<>Annulé",J_Statut,"<>Prévu")) | F17: =IF($C17="",0,SUMIFS(P_M2,P_Annee,Annee_Travail,P_Cat,$C17,P_Type,"Revenu")) | G17: =IF($C17="",0,SUMIFS(J_Montant,J_Annee,Annee_Travail,J_Mois,2,J_Cat,$C17,J_Type,"Revenu",J_Statut,"<>Annulé",J_Statut,"<>Prévu")) | H17: =IF($C17="",0,SUMIFS(P_M3,P_Annee,Annee_Travail,P_Cat,$C17,P_Type,"Revenu")) | I17: =IF($C17="",0,SUMIFS(J_Montant,J_Annee,Annee_Travail,J_Mois,3,J_Cat,$C17,J_Type,"Revenu",J_Statut,"<>Annulé",J_Statut,"<>Prévu")) | J17: =IF($C17="",0,SUMIFS(P_M4,P_Annee,Annee_Travail,P_Cat,$C17,P_Type,"Revenu")) | K17: =IF($C17="",0,SUMIFS(J_Montant,J_Annee,Annee_Travail,J_Mois,4,J_Cat,$C17,J_Type,"Revenu",J_Statut,"<>Annulé",J_Statut,"<>Prévu")) | L17: =IF($C17="",0,SUMIFS(P_M5,P_Annee,Annee_Travail,P_Cat,$C17,P_Type,"Revenu")) | M17: =IF($C17="",0,SUMIFS(J_Montant,J_Annee,Annee_Travail,J_Mois,5,J_Cat,$C17,J_Type,"Revenu",J_Statut,"<>Annulé",J_Statut,"<>Prévu")) | N17: =IF($C17="",0,SUMIFS(P_M6,P_Annee,Annee_Travail,P_Cat,$C17,P_Type,"Revenu")) | O17: =IF($C17="",0,SUMIFS(J_Montant,J_Annee,Annee_Travail,J_Mois,6,J_Cat,$C17,J_Type,"Revenu",J_Statut,"<>Annulé",J_Statut,"<>Prévu")) | P17: =IF($C17="",0,SUMIFS(P_M7,P_Annee,Annee_Travail,P_Cat,$C17,P_Type,"Revenu")) | Q17: =IF($C17="",0,SUMIFS(J_Montant,J_Annee,Annee_Travail,J_Mois,7,J_Cat,$C17,J_Type,"Revenu",J_Statut,"<>Annulé",J_Statut,"<>Prévu")) | R17: =IF($C17="",0,SUMIFS(P_M8,P_Annee,Annee_Travail,P_Cat,$C17,P_Type,"Revenu")) | S17: =IF($C17="",0,SUMIFS(J_Montant,J_Annee,Annee_Travail,J_Mois,8,J_Cat,$C17,J_Type,"Revenu",J_Statut,"<>Annulé",J_Statut,"<>Prévu")) | T17: =IF($C17="",0,SUMIFS(P_M9,P_Annee,Annee_Travail,P_Cat,$C17,P_Type,"Revenu")) | U17: =IF($C17="",0,SUMIFS(J_Montant,J_Annee,Annee_Travail,J_Mois,9,J_Cat,$C17,J_Type,"Revenu",J_Statut,"<>Annulé",J_Statut,"<>Prévu")) | V17: =IF($C17="",0,SUMIFS(P_M10,P_Annee,Annee_Travail,P_Cat,$C17,P_Type,"Revenu")) | W17: =IF($C17="",0,SUMIFS(J_Montant,J_Annee,Annee_Travail,J_Mois,10,J_Cat,$C17,J_Type,"Revenu",J_Statut,"<>Annulé",J_Statut,"<>Prévu")) | X17: =IF($C17="",0,SUMIFS(P_M11,P_Annee,Annee_Travail,P_Cat,$C17,P_Type,"Revenu")) | Y17: =IF($C17="",0,SUMIFS(J_Montant,J_Annee,Annee_Travail,J_Mois,11,J_Cat,$C17,J_Type,"Revenu",J_Statut,"<>Annulé",J_Statut,"<>Prévu")) | Z17: =IF($C17="",0,SUMIFS(P_M12,P_Annee,Annee_Travail,P_Cat,$C17,P_Type,"Revenu")) | AA17: =IF($C17="",0,SUMIFS(J_Montant,J_Annee,Annee_Travail,J_Mois,12,J_Cat,$C17,J_Type,"Revenu",J_Statut,"<>Annulé",J_Statut,"<>Prévu")) | AB17: =D17+F17+H17+J17+L17+N17+P17+R17+T17+V17+X17+Z17 | AC17: =E17+G17+I17+K17+M17+O17+Q17+S17+U17+W17+Y17+AA17 | AD17: =$AC17-$AB17 | AE17: =IFERROR($AC17/$AB17,0)
B18: 8 | C18: Aide familiale | D18: =IF($C18="",0,SUMIFS(P_M1,P_Annee,Annee_Travail,P_Cat,$C18,P_Type,"Revenu")) | E18: =IF($C18="",0,SUMIFS(J_Montant,J_Annee,Annee_Travail,J_Mois,1,J_Cat,$C18,J_Type,"Revenu",J_Statut,"<>Annulé",J_Statut,"<>Prévu")) | F18: =IF($C18="",0,SUMIFS(P_M2,P_Annee,Annee_Travail,P_Cat,$C18,P_Type,"Revenu")) | G18: =IF($C18="",0,SUMIFS(J_Montant,J_Annee,Annee_Travail,J_Mois,2,J_Cat,$C18,J_Type,"Revenu",J_Statut,"<>Annulé",J_Statut,"<>Prévu")) | H18: =IF($C18="",0,SUMIFS(P_M3,P_Annee,Annee_Travail,P_Cat,$C18,P_Type,"Revenu")) | I18: =IF($C18="",0,SUMIFS(J_Montant,J_Annee,Annee_Travail,J_Mois,3,J_Cat,$C18,J_Type,"Revenu",J_Statut,"<>Annulé",J_Statut,"<>Prévu")) | J18: =IF($C18="",0,SUMIFS(P_M4,P_Annee,Annee_Travail,P_Cat,$C18,P_Type,"Revenu")) | K18: =IF($C18="",0,SUMIFS(J_Montant,J_Annee,Annee_Travail,J_Mois,4,J_Cat,$C18,J_Type,"Revenu",J_Statut,"<>Annulé",J_Statut,"<>Prévu")) | L18: =IF($C18="",0,SUMIFS(P_M5,P_Annee,Annee_Travail,P_Cat,$C18,P_Type,"Revenu")) | M18: =IF($C18="",0,SUMIFS(J_Montant,J_Annee,Annee_Travail,J_Mois,5,J_Cat,$C18,J_Type,"Revenu",J_Statut,"<>Annulé",J_Statut,"<>Prévu")) | N18: =IF($C18="",0,SUMIFS(P_M6,P_Annee,Annee_Travail,P_Cat,$C18,P_Type,"Revenu")) | O18: =IF($C18="",0,SUMIFS(J_Montant,J_Annee,Annee_Travail,J_Mois,6,J_Cat,$C18,J_Type,"Revenu",J_Statut,"<>Annulé",J_Statut,"<>Prévu")) | P18: =IF($C18="",0,SUMIFS(P_M7,P_Annee,Annee_Travail,P_Cat,$C18,P_Type,"Revenu")) | Q18: =IF($C18="",0,SUMIFS(J_Montant,J_Annee,Annee_Travail,J_Mois,7,J_Cat,$C18,J_Type,"Revenu",J_Statut,"<>Annulé",J_Statut,"<>Prévu")) | R18: =IF($C18="",0,SUMIFS(P_M8,P_Annee,Annee_Travail,P_Cat,$C18,P_Type,"Revenu")) | S18: =IF($C18="",0,SUMIFS(J_Montant,J_Annee,Annee_Travail,J_Mois,8,J_Cat,$C18,J_Type,"Revenu",J_Statut,"<>Annulé",J_Statut,"<>Prévu")) | T18: =IF($C18="",0,SUMIFS(P_M9,P_Annee,Annee_Travail,P_Cat,$C18,P_Type,"Revenu")) | U18: =IF($C18="",0,SUMIFS(J_Montant,J_Annee,Annee_Travail,J_Mois,9,J_Cat,$C18,J_Type,"Revenu",J_Statut,"<>Annulé",J_Statut,"<>Prévu")) | V18: =IF($C18="",0,SUMIFS(P_M10,P_Annee,Annee_Travail,P_Cat,$C18,P_Type,"Revenu")) | W18: =IF($C18="",0,SUMIFS(J_Montant,J_Annee,Annee_Travail,J_Mois,10,J_Cat,$C18,J_Type,"Revenu",J_Statut,"<>Annulé",J_Statut,"<>Prévu")) | X18: =IF($C18="",0,SUMIFS(P_M11,P_Annee,Annee_Travail,P_Cat,$C18,P_Type,"Revenu")) | Y18: =IF($C18="",0,SUMIFS(J_Montant,J_Annee,Annee_Travail,J_Mois,11,J_Cat,$C18,J_Type,"Revenu",J_Statut,"<>Annulé",J_Statut,"<>Prévu")) | Z18: =IF($C18="",0,SUMIFS(P_M12,P_Annee,Annee_Travail,P_Cat,$C18,P_Type,"Revenu")) | AA18: =IF($C18="",0,SUMIFS(J_Montant,J_Annee,Annee_Travail,J_Mois,12,J_Cat,$C18,J_Type,"Revenu",J_Statut,"<>Annulé",J_Statut,"<>Prévu")) | AB18: =D18+F18+H18+J18+L18+N18+P18+R18+T18+V18+X18+Z18 | AC18: =E18+G18+I18+K18+M18+O18+Q18+S18+U18+W18+Y18+AA18 | AD18: =$AC18-$AB18 | AE18: =IFERROR($AC18/$AB18,0)
B19: 9 | C19: Remboursement reçu | D19: =IF($C19="",0,SUMIFS(P_M1,P_Annee,Annee_Travail,P_Cat,$C19,P_Type,"Revenu")) | E19: =IF($C19="",0,SUMIFS(J_Montant,J_Annee,Annee_Travail,J_Mois,1,J_Cat,$C19,J_Type,"Revenu",J_Statut,"<>Annulé",J_Statut,"<>Prévu")) | F19: =IF($C19="",0,SUMIFS(P_M2,P_Annee,Annee_Travail,P_Cat,$C19,P_Type,"Revenu")) | G19: =IF($C19="",0,SUMIFS(J_Montant,J_Annee,Annee_Travail,J_Mois,2,J_Cat,$C19,J_Type,"Revenu",J_Statut,"<>Annulé",J_Statut,"<>Prévu")) | H19: =IF($C19="",0,SUMIFS(P_M3,P_Annee,Annee_Travail,P_Cat,$C19,P_Type,"Revenu")) | I19: =IF($C19="",0,SUMIFS(J_Montant,J_Annee,Annee_Travail,J_Mois,3,J_Cat,$C19,J_Type,"Revenu",J_Statut,"<>Annulé",J_Statut,"<>Prévu")) | J19: =IF($C19="",0,SUMIFS(P_M4,P_Annee,Annee_Travail,P_Cat,$C19,P_Type,"Revenu")) | K19: =IF($C19="",0,SUMIFS(J_Montant,J_Annee,Annee_Travail,J_Mois,4,J_Cat,$C19,J_Type,"Revenu",J_Statut,"<>Annulé",J_Statut,"<>Prévu")) | L19: =IF($C19="",0,SUMIFS(P_M5,P_Annee,Annee_Travail,P_Cat,$C19,P_Type,"Revenu")) | M19: =IF($C19="",0,SUMIFS(J_Montant,J_Annee,Annee_Travail,J_Mois,5,J_Cat,$C19,J_Type,"Revenu",J_Statut,"<>Annulé",J_Statut,"<>Prévu")) | N19: =IF($C19="",0,SUMIFS(P_M6,P_Annee,Annee_Travail,P_Cat,$C19,P_Type,"Revenu")) | O19: =IF($C19="",0,SUMIFS(J_Montant,J_Annee,Annee_Travail,J_Mois,6,J_Cat,$C19,J_Type,"Revenu",J_Statut,"<>Annulé",J_Statut,"<>Prévu")) | P19: =IF($C19="",0,SUMIFS(P_M7,P_Annee,Annee_Travail,P_Cat,$C19,P_Type,"Revenu")) | Q19: =IF($C19="",0,SUMIFS(J_Montant,J_Annee,Annee_Travail,J_Mois,7,J_Cat,$C19,J_Type,"Revenu",J_Statut,"<>Annulé",J_Statut,"<>Prévu")) | R19: =IF($C19="",0,SUMIFS(P_M8,P_Annee,Annee_Travail,P_Cat,$C19,P_Type,"Revenu")) | S19: =IF($C19="",0,SUMIFS(J_Montant,J_Annee,Annee_Travail,J_Mois,8,J_Cat,$C19,J_Type,"Revenu",J_Statut,"<>Annulé",J_Statut,"<>Prévu")) | T19: =IF($C19="",0,SUMIFS(P_M9,P_Annee,Annee_Travail,P_Cat,$C19,P_Type,"Revenu")) | U19: =IF($C19="",0,SUMIFS(J_Montant,J_Annee,Annee_Travail,J_Mois,9,J_Cat,$C19,J_Type,"Revenu",J_Statut,"<>Annulé",J_Statut,"<>Prévu")) | V19: =IF($C19="",0,SUMIFS(P_M10,P_Annee,Annee_Travail,P_Cat,$C19,P_Type,"Revenu")) | W19: =IF($C19="",0,SUMIFS(J_Montant,J_Annee,Annee_Travail,J_Mois,10,J_Cat,$C19,J_Type,"Revenu",J_Statut,"<>Annulé",J_Statut,"<>Prévu")) | X19: =IF($C19="",0,SUMIFS(P_M11,P_Annee,Annee_Travail,P_Cat,$C19,P_Type,"Revenu")) | Y19: =IF($C19="",0,SUMIFS(J_Montant,J_Annee,Annee_Travail,J_Mois,11,J_Cat,$C19,J_Type,"Revenu",J_Statut,"<>Annulé",J_Statut,"<>Prévu")) | Z19: =IF($C19="",0,SUMIFS(P_M12,P_Annee,Annee_Travail,P_Cat,$C19,P_Type,"Revenu")) | AA19: =IF($C19="",0,SUMIFS(J_Montant,J_Annee,Annee_Travail,J_Mois,12,J_Cat,$C19,J_Type,"Revenu",J_Statut,"<>Annulé",J_Statut,"<>Prévu")) | AB19: =D19+F19+H19+J19+L19+N19+P19+R19+T19+V19+X19+Z19 | AC19: =E19+G19+I19+K19+M19+O19+Q19+S19+U19+W19+Y19+AA19 | AD19: =$AC19-$AB19 | AE19: =IFERROR($AC19/$AB19,0)
B20: 10 | C20: Vente d'actifs | D20: =IF($C20="",0,SUMIFS(P_M1,P_Annee,Annee_Travail,P_Cat,$C20,P_Type,"Revenu")) | E20: =IF($C20="",0,SUMIFS(J_Montant,J_Annee,Annee_Travail,J_Mois,1,J_Cat,$C20,J_Type,"Revenu",J_Statut,"<>Annulé",J_Statut,"<>Prévu")) | F20: =IF($C20="",0,SUMIFS(P_M2,P_Annee,Annee_Travail,P_Cat,$C20,P_Type,"Revenu")) | G20: =IF($C20="",0,SUMIFS(J_Montant,J_Annee,Annee_Travail,J_Mois,2,J_Cat,$C20,J_Type,"Revenu",J_Statut,"<>Annulé",J_Statut,"<>Prévu")) | H20: =IF($C20="",0,SUMIFS(P_M3,P_Annee,Annee_Travail,P_Cat,$C20,P_Type,"Revenu")) | I20: =IF($C20="",0,SUMIFS(J_Montant,J_Annee,Annee_Travail,J_Mois,3,J_Cat,$C20,J_Type,"Revenu",J_Statut,"<>Annulé",J_Statut,"<>Prévu")) | J20: =IF($C20="",0,SUMIFS(P_M4,P_Annee,Annee_Travail,P_Cat,$C20,P_Type,"Revenu")) | K20: =IF($C20="",0,SUMIFS(J_Montant,J_Annee,Annee_Travail,J_Mois,4,J_Cat,$C20,J_Type,"Revenu",J_Statut,"<>Annulé",J_Statut,"<>Prévu")) | L20: =IF($C20="",0,SUMIFS(P_M5,P_Annee,Annee_Travail,P_Cat,$C20,P_Type,"Revenu")) | M20: =IF($C20="",0,SUMIFS(J_Montant,J_Annee,Annee_Travail,J_Mois,5,J_Cat,$C20,J_Type,"Revenu",J_Statut,"<>Annulé",J_Statut,"<>Prévu")) | N20: =IF($C20="",0,SUMIFS(P_M6,P_Annee,Annee_Travail,P_Cat,$C20,P_Type,"Revenu")) | O20: =IF($C20="",0,SUMIFS(J_Montant,J_Annee,Annee_Travail,J_Mois,6,J_Cat,$C20,J_Type,"Revenu",J_Statut,"<>Annulé",J_Statut,"<>Prévu")) | P20: =IF($C20="",0,SUMIFS(P_M7,P_Annee,Annee_Travail,P_Cat,$C20,P_Type,"Revenu")) | Q20: =IF($C20="",0,SUMIFS(J_Montant,J_Annee,Annee_Travail,J_Mois,7,J_Cat,$C20,J_Type,"Revenu",J_Statut,"<>Annulé",J_Statut,"<>Prévu")) | R20: =IF($C20="",0,SUMIFS(P_M8,P_Annee,Annee_Travail,P_Cat,$C20,P_Type,"Revenu")) | S20: =IF($C20="",0,SUMIFS(J_Montant,J_Annee,Annee_Travail,J_Mois,8,J_Cat,$C20,J_Type,"Revenu",J_Statut,"<>Annulé",J_Statut,"<>Prévu")) | T20: =IF($C20="",0,SUMIFS(P_M9,P_Annee,Annee_Travail,P_Cat,$C20,P_Type,"Revenu")) | U20: =IF($C20="",0,SUMIFS(J_Montant,J_Annee,Annee_Travail,J_Mois,9,J_Cat,$C20,J_Type,"Revenu",J_Statut,"<>Annulé",J_Statut,"<>Prévu")) | V20: =IF($C20="",0,SUMIFS(P_M10,P_Annee,Annee_Travail,P_Cat,$C20,P_Type,"Revenu")) | W20: =IF($C20="",0,SUMIFS(J_Montant,J_Annee,Annee_Travail,J_Mois,10,J_Cat,$C20,J_Type,"Revenu",J_Statut,"<>Annulé",J_Statut,"<>Prévu")) | X20: =IF($C20="",0,SUMIFS(P_M11,P_Annee,Annee_Travail,P_Cat,$C20,P_Type,"Revenu")) | Y20: =IF($C20="",0,SUMIFS(J_Montant,J_Annee,Annee_Travail,J_Mois,11,J_Cat,$C20,J_Type,"Revenu",J_Statut,"<>Annulé",J_Statut,"<>Prévu")) | Z20: =IF($C20="",0,SUMIFS(P_M12,P_Annee,Annee_Travail,P_Cat,$C20,P_Type,"Revenu")) | AA20: =IF($C20="",0,SUMIFS(J_Montant,J_Annee,Annee_Travail,J_Mois,12,J_Cat,$C20,J_Type,"Revenu",J_Statut,"<>Annulé",J_Statut,"<>Prévu")) | AB20: =D20+F20+H20+J20+L20+N20+P20+R20+T20+V20+X20+Z20 | AC20: =E20+G20+I20+K20+M20+O20+Q20+S20+U20+W20+Y20+AA20 | AD20: =$AC20-$AB20 | AE20: =IFERROR($AC20/$AB20,0)
B21: 11 | C21: Autre revenu | D21: =IF($C21="",0,SUMIFS(P_M1,P_Annee,Annee_Travail,P_Cat,$C21,P_Type,"Revenu")) | E21: =IF($C21="",0,SUMIFS(J_Montant,J_Annee,Annee_Travail,J_Mois,1,J_Cat,$C21,J_Type,"Revenu",J_Statut,"<>Annulé",J_Statut,"<>Prévu")) | F21: =IF($C21="",0,SUMIFS(P_M2,P_Annee,Annee_Travail,P_Cat,$C21,P_Type,"Revenu")) | G21: =IF($C21="",0,SUMIFS(J_Montant,J_Annee,Annee_Travail,J_Mois,2,J_Cat,$C21,J_Type,"Revenu",J_Statut,"<>Annulé",J_Statut,"<>Prévu")) | H21: =IF($C21="",0,SUMIFS(P_M3,P_Annee,Annee_Travail,P_Cat,$C21,P_Type,"Revenu")) | I21: =IF($C21="",0,SUMIFS(J_Montant,J_Annee,Annee_Travail,J_Mois,3,J_Cat,$C21,J_Type,"Revenu",J_Statut,"<>Annulé",J_Statut,"<>Prévu")) | J21: =IF($C21="",0,SUMIFS(P_M4,P_Annee,Annee_Travail,P_Cat,$C21,P_Type,"Revenu")) | K21: =IF($C21="",0,SUMIFS(J_Montant,J_Annee,Annee_Travail,J_Mois,4,J_Cat,$C21,J_Type,"Revenu",J_Statut,"<>Annulé",J_Statut,"<>Prévu")) | L21: =IF($C21="",0,SUMIFS(P_M5,P_Annee,Annee_Travail,P_Cat,$C21,P_Type,"Revenu")) | M21: =IF($C21="",0,SUMIFS(J_Montant,J_Annee,Annee_Travail,J_Mois,5,J_Cat,$C21,J_Type,"Revenu",J_Statut,"<>Annulé",J_Statut,"<>Prévu")) | N21: =IF($C21="",0,SUMIFS(P_M6,P_Annee,Annee_Travail,P_Cat,$C21,P_Type,"Revenu")) | O21: =IF($C21="",0,SUMIFS(J_Montant,J_Annee,Annee_Travail,J_Mois,6,J_Cat,$C21,J_Type,"Revenu",J_Statut,"<>Annulé",J_Statut,"<>Prévu")) | P21: =IF($C21="",0,SUMIFS(P_M7,P_Annee,Annee_Travail,P_Cat,$C21,P_Type,"Revenu")) | Q21: =IF($C21="",0,SUMIFS(J_Montant,J_Annee,Annee_Travail,J_Mois,7,J_Cat,$C21,J_Type,"Revenu",J_Statut,"<>Annulé",J_Statut,"<>Prévu")) | R21: =IF($C21="",0,SUMIFS(P_M8,P_Annee,Annee_Travail,P_Cat,$C21,P_Type,"Revenu")) | S21: =IF($C21="",0,SUMIFS(J_Montant,J_Annee,Annee_Travail,J_Mois,8,J_Cat,$C21,J_Type,"Revenu",J_Statut,"<>Annulé",J_Statut,"<>Prévu")) | T21: =IF($C21="",0,SUMIFS(P_M9,P_Annee,Annee_Travail,P_Cat,$C21,P_Type,"Revenu")) | U21: =IF($C21="",0,SUMIFS(J_Montant,J_Annee,Annee_Travail,J_Mois,9,J_Cat,$C21,J_Type,"Revenu",J_Statut,"<>Annulé",J_Statut,"<>Prévu")) | V21: =IF($C21="",0,SUMIFS(P_M10,P_Annee,Annee_Travail,P_Cat,$C21,P_Type,"Revenu")) | W21: =IF($C21="",0,SUMIFS(J_Montant,J_Annee,Annee_Travail,J_Mois,10,J_Cat,$C21,J_Type,"Revenu",J_Statut,"<>Annulé",J_Statut,"<>Prévu")) | X21: =IF($C21="",0,SUMIFS(P_M11,P_Annee,Annee_Travail,P_Cat,$C21,P_Type,"Revenu")) | Y21: =IF($C21="",0,SUMIFS(J_Montant,J_Annee,Annee_Travail,J_Mois,11,J_Cat,$C21,J_Type,"Revenu",J_Statut,"<>Annulé",J_Statut,"<>Prévu")) | Z21: =IF($C21="",0,SUMIFS(P_M12,P_Annee,Annee_Travail,P_Cat,$C21,P_Type,"Revenu")) | AA21: =IF($C21="",0,SUMIFS(J_Montant,J_Annee,Annee_Travail,J_Mois,12,J_Cat,$C21,J_Type,"Revenu",J_Statut,"<>Annulé",J_Statut,"<>Prévu")) | AB21: =D21+F21+H21+J21+L21+N21+P21+R21+T21+V21+X21+Z21 | AC21: =E21+G21+I21+K21+M21+O21+Q21+S21+U21+W21+Y21+AA21 | AD21: =$AC21-$AB21 | AE21: =IFERROR($AC21/$AB21,0)
B22: 12 | C22: Chiffre d'affaires | D22: =IF($C22="",0,SUMIFS(P_M1,P_Annee,Annee_Travail,P_Cat,$C22,P_Type,"Revenu")) | E22: =IF($C22="",0,SUMIFS(J_Montant,J_Annee,Annee_Travail,J_Mois,1,J_Cat,$C22,J_Type,"Revenu",J_Statut,"<>Annulé",J_Statut,"<>Prévu")) | F22: =IF($C22="",0,SUMIFS(P_M2,P_Annee,Annee_Travail,P_Cat,$C22,P_Type,"Revenu")) | G22: =IF($C22="",0,SUMIFS(J_Montant,J_Annee,Annee_Travail,J_Mois,2,J_Cat,$C22,J_Type,"Revenu",J_Statut,"<>Annulé",J_Statut,"<>Prévu")) | H22: =IF($C22="",0,SUMIFS(P_M3,P_Annee,Annee_Travail,P_Cat,$C22,P_Type,"Revenu")) | I22: =IF($C22="",0,SUMIFS(J_Montant,J_Annee,Annee_Travail,J_Mois,3,J_Cat,$C22,J_Type,"Revenu",J_Statut,"<>Annulé",J_Statut,"<>Prévu")) | J22: =IF($C22="",0,SUMIFS(P_M4,P_Annee,Annee_Travail,P_Cat,$C22,P_Type,"Revenu")) | K22: =IF($C22="",0,SUMIFS(J_Montant,J_Annee,Annee_Travail,J_Mois,4,J_Cat,$C22,J_Type,"Revenu",J_Statut,"<>Annulé",J_Statut,"<>Prévu")) | L22: =IF($C22="",0,SUMIFS(P_M5,P_Annee,Annee_Travail,P_Cat,$C22,P_Type,"Revenu")) | M22: =IF($C22="",0,SUMIFS(J_Montant,J_Annee,Annee_Travail,J_Mois,5,J_Cat,$C22,J_Type,"Revenu",J_Statut,"<>Annulé",J_Statut,"<>Prévu")) | N22: =IF($C22="",0,SUMIFS(P_M6,P_Annee,Annee_Travail,P_Cat,$C22,P_Type,"Revenu")) | O22: =IF($C22="",0,SUMIFS(J_Montant,J_Annee,Annee_Travail,J_Mois,6,J_Cat,$C22,J_Type,"Revenu",J_Statut,"<>Annulé",J_Statut,"<>Prévu")) | P22: =IF($C22="",0,SUMIFS(P_M7,P_Annee,Annee_Travail,P_Cat,$C22,P_Type,"Revenu")) | Q22: =IF($C22="",0,SUMIFS(J_Montant,J_Annee,Annee_Travail,J_Mois,7,J_Cat,$C22,J_Type,"Revenu",J_Statut,"<>Annulé",J_Statut,"<>Prévu")) | R22: =IF($C22="",0,SUMIFS(P_M8,P_Annee,Annee_Travail,P_Cat,$C22,P_Type,"Revenu")) | S22: =IF($C22="",0,SUMIFS(J_Montant,J_Annee,Annee_Travail,J_Mois,8,J_Cat,$C22,J_Type,"Revenu",J_Statut,"<>Annulé",J_Statut,"<>Prévu")) | T22: =IF($C22="",0,SUMIFS(P_M9,P_Annee,Annee_Travail,P_Cat,$C22,P_Type,"Revenu")) | U22: =IF($C22="",0,SUMIFS(J_Montant,J_Annee,Annee_Travail,J_Mois,9,J_Cat,$C22,J_Type,"Revenu",J_Statut,"<>Annulé",J_Statut,"<>Prévu")) | V22: =IF($C22="",0,SUMIFS(P_M10,P_Annee,Annee_Travail,P_Cat,$C22,P_Type,"Revenu")) | W22: =IF($C22="",0,SUMIFS(J_Montant,J_Annee,Annee_Travail,J_Mois,10,J_Cat,$C22,J_Type,"Revenu",J_Statut,"<>Annulé",J_Statut,"<>Prévu")) | X22: =IF($C22="",0,SUMIFS(P_M11,P_Annee,Annee_Travail,P_Cat,$C22,P_Type,"Revenu")) | Y22: =IF($C22="",0,SUMIFS(J_Montant,J_Annee,Annee_Travail,J_Mois,11,J_Cat,$C22,J_Type,"Revenu",J_Statut,"<>Annulé",J_Statut,"<>Prévu")) | Z22: =IF($C22="",0,SUMIFS(P_M12,P_Annee,Annee_Travail,P_Cat,$C22,P_Type,"Revenu")) | AA22: =IF($C22="",0,SUMIFS(J_Montant,J_Annee,Annee_Travail,J_Mois,12,J_Cat,$C22,J_Type,"Revenu",J_Statut,"<>Annulé",J_Statut,"<>Prévu")) | AB22: =D22+F22+H22+J22+L22+N22+P22+R22+T22+V22+X22+Z22 | AC22: =E22+G22+I22+K22+M22+O22+Q22+S22+U22+W22+Y22+AA22 | AD22: =$AC22-$AB22 | AE22: =IFERROR($AC22/$AB22,0)
... B24: 14 | C24: Vente de produits | D24: =IF($C24="",0,SUMIFS(P_M1,P_Annee,Annee_Travail,P_Cat,$C24,P_Type,"Revenu")) | E24: =IF($C24="",0,SUMIFS(J_Montant,J_Annee,Annee_Travail,J_Mois,1,J_Cat,$C24,J_Type,"Revenu",J_Statut,"<>Annulé",J_Statut,"<>Prévu")) | F24: =IF($C24="",0,SUMIFS(P_M2,P_Annee,Annee_Travail,P_Cat,$C24,P_Type,"Revenu")) | G24: =IF($C24="",0,SUMIFS(J_Montant,J_Annee,Annee_Travail,J_Mois,2,J_Cat,$C24,J_Type,"Revenu",J_Statut,"<>Annulé",J_Statut,"<>Prévu")) | H24: =IF($C24="",0,SUMIFS(P_M3,P_Annee,Annee_Travail,P_Cat,$C24,P_Type,"Revenu")) | I24: =IF($C24="",0,SUMIFS(J_Montant,J_Annee,Annee_Travail,J_Mois,3,J_Cat,$C24,J_Type,"Revenu",J_Statut,"<>Annulé",J_Statut,"<>Prévu")) | J24: =IF($C24="",0,SUMIFS(P_M4,P_Annee,Annee_Travail,P_Cat,$C24,P_Type,"Revenu")) | K24: =IF($C24="",0,SUMIFS(J_Montant,J_Annee,Annee_Travail,J_Mois,4,J_Cat,$C24,J_Type,"Revenu",J_Statut,"<>Annulé",J_Statut,"<>Prévu")) | L24: =IF($C24="",0,SUMIFS(P_M5,P_Annee,Annee_Travail,P_Cat,$C24,P_Type,"Revenu")) | M24: =IF($C24="",0,SUMIFS(J_Montant,J_Annee,Annee_Travail,J_Mois,5,J_Cat,$C24,J_Type,"Revenu",J_Statut,"<>Annulé",J_Statut,"<>Prévu")) | N24: =IF($C24="",0,SUMIFS(P_M6,P_Annee,Annee_Travail,P_Cat,$C24,P_Type,"Revenu")) | O24: =IF($C24="",0,SUMIFS(J_Montant,J_Annee,Annee_Travail,J_Mois,6,J_Cat,$C24,J_Type,"Revenu",J_Statut,"<>Annulé",J_Statut,"<>Prévu")) | P24: =IF($C24="",0,SUMIFS(P_M7,P_Annee,Annee_Travail,P_Cat,$C24,P_Type,"Revenu")) | Q24: =IF($C24="",0,SUMIFS(J_Montant,J_Annee,Annee_Travail,J_Mois,7,J_Cat,$C24,J_Type,"Revenu",J_Statut,"<>Annulé",J_Statut,"<>Prévu")) | R24: =IF($C24="",0,SUMIFS(P_M8,P_Annee,Annee_Travail,P_Cat,$C24,P_Type,"Revenu")) | S24: =IF($C24="",0,SUMIFS(J_Montant,J_Annee,Annee_Travail,J_Mois,8,J_Cat,$C24,J_Type,"Revenu",J_Statut,"<>Annulé",J_Statut,"<>Prévu")) | T24: =IF($C24="",0,SUMIFS(P_M9,P_Annee,Annee_Travail,P_Cat,$C24,P_Type,"Revenu")) | U24: =IF($C24="",0,SUMIFS(J_Montant,J_Annee,Annee_Travail,J_Mois,9,J_Cat,$C24,J_Type,"Revenu",J_Statut,"<>Annulé",J_Statut,"<>Prévu")) | V24: =IF($C24="",0,SUMIFS(P_M10,P_Annee,Annee_Travail,P_Cat,$C24,P_Type,"Revenu")) | W24: =IF($C24="",0,SUMIFS(J_Montant,J_Annee,Annee_Travail,J_Mois,10,J_Cat,$C24,J_Type,"Revenu",J_Statut,"<>Annulé",J_Statut,"<>Prévu")) | X24: =IF($C24="",0,SUMIFS(P_M11,P_Annee,Annee_Travail,P_Cat,$C24,P_Type,"Revenu")) | Y24: =IF($C24="",0,SUMIFS(J_Montant,J_Annee,Annee_Travail,J_Mois,11,J_Cat,$C24,J_Type,"Revenu",J_Statut,"<>Annulé",J_Statut,"<>Prévu")) | Z24: =IF($C24="",0,SUMIFS(P_M12,P_Annee,Annee_Travail,P_Cat,$C24,P_Type,"Revenu")) | AA24: =IF($C24="",0,SUMIFS(J_Montant,J_Annee,Annee_Travail,J_Mois,12,J_Cat,$C24,J_Type,"Revenu",J_Statut,"<>Annulé",J_Statut,"<>Prévu")) | AB24: =D24+F24+H24+J24+L24+N24+P24+R24+T24+V24+X24+Z24 | AC24: =E24+G24+I24+K24+M24+O24+Q24+S24+U24+W24+Y24+AA24 | AD24: =$AC24-$AB24 | AE24: =IFERROR($AC24/$AB24,0)
B25: 15 | D25: =IF($C25="",0,SUMIFS(P_M1,P_Annee,Annee_Travail,P_Cat,$C25,P_Type,"Revenu")) | E25: =IF($C25="",0,SUMIFS(J_Montant,J_Annee,Annee_Travail,J_Mois,1,J_Cat,$C25,J_Type,"Revenu",J_Statut,"<>Annulé",J_Statut,"<>Prévu")) | F25: =IF($C25="",0,SUMIFS(P_M2,P_Annee,Annee_Travail,P_Cat,$C25,P_Type,"Revenu")) | G25: =IF($C25="",0,SUMIFS(J_Montant,J_Annee,Annee_Travail,J_Mois,2,J_Cat,$C25,J_Type,"Revenu",J_Statut,"<>Annulé",J_Statut,"<>Prévu")) | H25: =IF($C25="",0,SUMIFS(P_M3,P_Annee,Annee_Travail,P_Cat,$C25,P_Type,"Revenu")) | I25: =IF($C25="",0,SUMIFS(J_Montant,J_Annee,Annee_Travail,J_Mois,3,J_Cat,$C25,J_Type,"Revenu",J_Statut,"<>Annulé",J_Statut,"<>Prévu")) | J25: =IF($C25="",0,SUMIFS(P_M4,P_Annee,Annee_Travail,P_Cat,$C25,P_Type,"Revenu")) | K25: =IF($C25="",0,SUMIFS(J_Montant,J_Annee,Annee_Travail,J_Mois,4,J_Cat,$C25,J_Type,"Revenu",J_Statut,"<>Annulé",J_Statut,"<>Prévu")) | L25: =IF($C25="",0,SUMIFS(P_M5,P_Annee,Annee_Travail,P_Cat,$C25,P_Type,"Revenu")) | M25: =IF($C25="",0,SUMIFS(J_Montant,J_Annee,Annee_Travail,J_Mois,5,J_Cat,$C25,J_Type,"Revenu",J_Statut,"<>Annulé",J_Statut,"<>Prévu")) | N25: =IF($C25="",0,SUMIFS(P_M6,P_Annee,Annee_Travail,P_Cat,$C25,P_Type,"Revenu")) | O25: =IF($C25="",0,SUMIFS(J_Montant,J_Annee,Annee_Travail,J_Mois,6,J_Cat,$C25,J_Type,"Revenu",J_Statut,"<>Annulé",J_Statut,"<>Prévu")) | P25: =IF($C25="",0,SUMIFS(P_M7,P_Annee,Annee_Travail,P_Cat,$C25,P_Type,"Revenu")) | Q25: =IF($C25="",0,SUMIFS(J_Montant,J_Annee,Annee_Travail,J_Mois,7,J_Cat,$C25,J_Type,"Revenu",J_Statut,"<>Annulé",J_Statut,"<>Prévu")) | R25: =IF($C25="",0,SUMIFS(P_M8,P_Annee,Annee_Travail,P_Cat,$C25,P_Type,"Revenu")) | S25: =IF($C25="",0,SUMIFS(J_Montant,J_Annee,Annee_Travail,J_Mois,8,J_Cat,$C25,J_Type,"Revenu",J_Statut,"<>Annulé",J_Statut,"<>Prévu")) | T25: =IF($C25="",0,SUMIFS(P_M9,P_Annee,Annee_Travail,P_Cat,$C25,P_Type,"Revenu")) | U25: =IF($C25="",0,SUMIFS(J_Montant,J_Annee,Annee_Travail,J_Mois,9,J_Cat,$C25,J_Type,"Revenu",J_Statut,"<>Annulé",J_Statut,"<>Prévu")) | V25: =IF($C25="",0,SUMIFS(P_M10,P_Annee,Annee_Travail,P_Cat,$C25,P_Type,"Revenu")) | W25: =IF($C25="",0,SUMIFS(J_Montant,J_Annee,Annee_Travail,J_Mois,10,J_Cat,$C25,J_Type,"Revenu",J_Statut,"<>Annulé",J_Statut,"<>Prévu")) | X25: =IF($C25="",0,SUMIFS(P_M11,P_Annee,Annee_Travail,P_Cat,$C25,P_Type,"Revenu")) | Y25: =IF($C25="",0,SUMIFS(J_Montant,J_Annee,Annee_Travail,J_Mois,11,J_Cat,$C25,J_Type,"Revenu",J_Statut,"<>Annulé",J_Statut,"<>Prévu")) | Z25: =IF($C25="",0,SUMIFS(P_M12,P_Annee,Annee_Travail,P_Cat,$C25,P_Type,"Revenu")) | AA25: =IF($C25="",0,SUMIFS(J_Montant,J_Annee,Annee_Travail,J_Mois,12,J_Cat,$C25,J_Type,"Revenu",J_Statut,"<>Annulé",J_Statut,"<>Prévu")) | AB25: =D25+F25+H25+J25+L25+N25+P25+R25+T25+V25+X25+Z25 | AC25: =E25+G25+I25+K25+M25+O25+Q25+S25+U25+W25+Y25+AA25 | AD25: =$AC25-$AB25 | AE25: =IFERROR($AC25/$AB25,0)
B26: 16 | D26: =IF($C26="",0,SUMIFS(P_M1,P_Annee,Annee_Travail,P_Cat,$C26,P_Type,"Revenu")) | E26: =IF($C26="",0,SUMIFS(J_Montant,J_Annee,Annee_Travail,J_Mois,1,J_Cat,$C26,J_Type,"Revenu",J_Statut,"<>Annulé",J_Statut,"<>Prévu")) | F26: =IF($C26="",0,SUMIFS(P_M2,P_Annee,Annee_Travail,P_Cat,$C26,P_Type,"Revenu")) | G26: =IF($C26="",0,SUMIFS(J_Montant,J_Annee,Annee_Travail,J_Mois,2,J_Cat,$C26,J_Type,"Revenu",J_Statut,"<>Annulé",J_Statut,"<>Prévu")) | H26: =IF($C26="",0,SUMIFS(P_M3,P_Annee,Annee_Travail,P_Cat,$C26,P_Type,"Revenu")) | I26: =IF($C26="",0,SUMIFS(J_Montant,J_Annee,Annee_Travail,J_Mois,3,J_Cat,$C26,J_Type,"Revenu",J_Statut,"<>Annulé",J_Statut,"<>Prévu")) | J26: =IF($C26="",0,SUMIFS(P_M4,P_Annee,Annee_Travail,P_Cat,$C26,P_Type,"Revenu")) | K26: =IF($C26="",0,SUMIFS(J_Montant,J_Annee,Annee_Travail,J_Mois,4,J_Cat,$C26,J_Type,"Revenu",J_Statut,"<>Annulé",J_Statut,"<>Prévu")) | L26: =IF($C26="",0,SUMIFS(P_M5,P_Annee,Annee_Travail,P_Cat,$C26,P_Type,"Revenu")) | M26: =IF($C26="",0,SUMIFS(J_Montant,J_Annee,Annee_Travail,J_Mois,5,J_Cat,$C26,J_Type,"Revenu",J_Statut,"<>Annulé",J_Statut,"<>Prévu")) | N26: =IF($C26="",0,SUMIFS(P_M6,P_Annee,Annee_Travail,P_Cat,$C26,P_Type,"Revenu")) | O26: =IF($C26="",0,SUMIFS(J_Montant,J_Annee,Annee_Travail,J_Mois,6,J_Cat,$C26,J_Type,"Revenu",J_Statut,"<>Annulé",J_Statut,"<>Prévu")) | P26: =IF($C26="",0,SUMIFS(P_M7,P_Annee,Annee_Travail,P_Cat,$C26,P_Type,"Revenu")) | Q26: =IF($C26="",0,SUMIFS(J_Montant,J_Annee,Annee_Travail,J_Mois,7,J_Cat,$C26,J_Type,"Revenu",J_Statut,"<>Annulé",J_Statut,"<>Prévu")) | R26: =IF($C26="",0,SUMIFS(P_M8,P_Annee,Annee_Travail,P_Cat,$C26,P_Type,"Revenu")) | S26: =IF($C26="",0,SUMIFS(J_Montant,J_Annee,Annee_Travail,J_Mois,8,J_Cat,$C26,J_Type,"Revenu",J_Statut,"<>Annulé",J_Statut,"<>Prévu")) | T26: =IF($C26="",0,SUMIFS(P_M9,P_Annee,Annee_Travail,P_Cat,$C26,P_Type,"Revenu")) | U26: =IF($C26="",0,SUMIFS(J_Montant,J_Annee,Annee_Travail,J_Mois,9,J_Cat,$C26,J_Type,"Revenu",J_Statut,"<>Annulé",J_Statut,"<>Prévu")) | V26: =IF($C26="",0,SUMIFS(P_M10,P_Annee,Annee_Travail,P_Cat,$C26,P_Type,"Revenu")) | W26: =IF($C26="",0,SUMIFS(J_Montant,J_Annee,Annee_Travail,J_Mois,10,J_Cat,$C26,J_Type,"Revenu",J_Statut,"<>Annulé",J_Statut,"<>Prévu")) | X26: =IF($C26="",0,SUMIFS(P_M11,P_Annee,Annee_Travail,P_Cat,$C26,P_Type,"Revenu")) | Y26: =IF($C26="",0,SUMIFS(J_Montant,J_Annee,Annee_Travail,J_Mois,11,J_Cat,$C26,J_Type,"Revenu",J_Statut,"<>Annulé",J_Statut,"<>Prévu")) | Z26: =IF($C26="",0,SUMIFS(P_M12,P_Annee,Annee_Travail,P_Cat,$C26,P_Type,"Revenu")) | AA26: =IF($C26="",0,SUMIFS(J_Montant,J_Annee,Annee_Travail,J_Mois,12,J_Cat,$C26,J_Type,"Revenu",J_Statut,"<>Annulé",J_Statut,"<>Prévu")) | AB26: =D26+F26+H26+J26+L26+N26+P26+R26+T26+V26+X26+Z26 | AC26: =E26+G26+I26+K26+M26+O26+Q26+S26+U26+W26+Y26+AA26 | AD26: =$AC26-$AB26 | AE26: =IFERROR($AC26/$AB26,0)
B27: 17 | D27: =IF($C27="",0,SUMIFS(P_M1,P_Annee,Annee_Travail,P_Cat,$C27,P_Type,"Revenu")) | E27: =IF($C27="",0,SUMIFS(J_Montant,J_Annee,Annee_Travail,J_Mois,1,J_Cat,$C27,J_Type,"Revenu",J_Statut,"<>Annulé",J_Statut,"<>Prévu")) | F27: =IF($C27="",0,SUMIFS(P_M2,P_Annee,Annee_Travail,P_Cat,$C27,P_Type,"Revenu")) | G27: =IF($C27="",0,SUMIFS(J_Montant,J_Annee,Annee_Travail,J_Mois,2,J_Cat,$C27,J_Type,"Revenu",J_Statut,"<>Annulé",J_Statut,"<>Prévu")) | H27: =IF($C27="",0,SUMIFS(P_M3,P_Annee,Annee_Travail,P_Cat,$C27,P_Type,"Revenu")) | I27: =IF($C27="",0,SUMIFS(J_Montant,J_Annee,Annee_Travail,J_Mois,3,J_Cat,$C27,J_Type,"Revenu",J_Statut,"<>Annulé",J_Statut,"<>Prévu")) | J27: =IF($C27="",0,SUMIFS(P_M4,P_Annee,Annee_Travail,P_Cat,$C27,P_Type,"Revenu")) | K27: =IF($C27="",0,SUMIFS(J_Montant,J_Annee,Annee_Travail,J_Mois,4,J_Cat,$C27,J_Type,"Revenu",J_Statut,"<>Annulé",J_Statut,"<>Prévu")) | L27: =IF($C27="",0,SUMIFS(P_M5,P_Annee,Annee_Travail,P_Cat,$C27,P_Type,"Revenu")) | M27: =IF($C27="",0,SUMIFS(J_Montant,J_Annee,Annee_Travail,J_Mois,5,J_Cat,$C27,J_Type,"Revenu",J_Statut,"<>Annulé",J_Statut,"<>Prévu")) | N27: =IF($C27="",0,SUMIFS(P_M6,P_Annee,Annee_Travail,P_Cat,$C27,P_Type,"Revenu")) | O27: =IF($C27="",0,SUMIFS(J_Montant,J_Annee,Annee_Travail,J_Mois,6,J_Cat,$C27,J_Type,"Revenu",J_Statut,"<>Annulé",J_Statut,"<>Prévu")) | P27: =IF($C27="",0,SUMIFS(P_M7,P_Annee,Annee_Travail,P_Cat,$C27,P_Type,"Revenu")) | Q27: =IF($C27="",0,SUMIFS(J_Montant,J_Annee,Annee_Travail,J_Mois,7,J_Cat,$C27,J_Type,"Revenu",J_Statut,"<>Annulé",J_Statut,"<>Prévu")) | R27: =IF($C27="",0,SUMIFS(P_M8,P_Annee,Annee_Travail,P_Cat,$C27,P_Type,"Revenu")) | S27: =IF($C27="",0,SUMIFS(J_Montant,J_Annee,Annee_Travail,J_Mois,8,J_Cat,$C27,J_Type,"Revenu",J_Statut,"<>Annulé",J_Statut,"<>Prévu")) | T27: =IF($C27="",0,SUMIFS(P_M9,P_Annee,Annee_Travail,P_Cat,$C27,P_Type,"Revenu")) | U27: =IF($C27="",0,SUMIFS(J_Montant,J_Annee,Annee_Travail,J_Mois,9,J_Cat,$C27,J_Type,"Revenu",J_Statut,"<>Annulé",J_Statut,"<>Prévu")) | V27: =IF($C27="",0,SUMIFS(P_M10,P_Annee,Annee_Travail,P_Cat,$C27,P_Type,"Revenu")) | W27: =IF($C27="",0,SUMIFS(J_Montant,J_Annee,Annee_Travail,J_Mois,10,J_Cat,$C27,J_Type,"Revenu",J_Statut,"<>Annulé",J_Statut,"<>Prévu")) | X27: =IF($C27="",0,SUMIFS(P_M11,P_Annee,Annee_Travail,P_Cat,$C27,P_Type,"Revenu")) | Y27: =IF($C27="",0,SUMIFS(J_Montant,J_Annee,Annee_Travail,J_Mois,11,J_Cat,$C27,J_Type,"Revenu",J_Statut,"<>Annulé",J_Statut,"<>Prévu")) | Z27: =IF($C27="",0,SUMIFS(P_M12,P_Annee,Annee_Travail,P_Cat,$C27,P_Type,"Revenu")) | AA27: =IF($C27="",0,SUMIFS(J_Montant,J_Annee,Annee_Travail,J_Mois,12,J_Cat,$C27,J_Type,"Revenu",J_Statut,"<>Annulé",J_Statut,"<>Prévu")) | AB27: =D27+F27+H27+J27+L27+N27+P27+R27+T27+V27+X27+Z27 | AC27: =E27+G27+I27+K27+M27+O27+Q27+S27+U27+W27+Y27+AA27 | AD27: =$AC27-$AB27 | AE27: =IFERROR($AC27/$AB27,0)
B28: 18 | D28: =IF($C28="",0,SUMIFS(P_M1,P_Annee,Annee_Travail,P_Cat,$C28,P_Type,"Revenu")) | E28: =IF($C28="",0,SUMIFS(J_Montant,J_Annee,Annee_Travail,J_Mois,1,J_Cat,$C28,J_Type,"Revenu",J_Statut,"<>Annulé",J_Statut,"<>Prévu")) | F28: =IF($C28="",0,SUMIFS(P_M2,P_Annee,Annee_Travail,P_Cat,$C28,P_Type,"Revenu")) | G28: =IF($C28="",0,SUMIFS(J_Montant,J_Annee,Annee_Travail,J_Mois,2,J_Cat,$C28,J_Type,"Revenu",J_Statut,"<>Annulé",J_Statut,"<>Prévu")) | H28: =IF($C28="",0,SUMIFS(P_M3,P_Annee,Annee_Travail,P_Cat,$C28,P_Type,"Revenu")) | I28: =IF($C28="",0,SUMIFS(J_Montant,J_Annee,Annee_Travail,J_Mois,3,J_Cat,$C28,J_Type,"Revenu",J_Statut,"<>Annulé",J_Statut,"<>Prévu")) | J28: =IF($C28="",0,SUMIFS(P_M4,P_Annee,Annee_Travail,P_Cat,$C28,P_Type,"Revenu")) | K28: =IF($C28="",0,SUMIFS(J_Montant,J_Annee,Annee_Travail,J_Mois,4,J_Cat,$C28,J_Type,"Revenu",J_Statut,"<>Annulé",J_Statut,"<>Prévu")) | L28: =IF($C28="",0,SUMIFS(P_M5,P_Annee,Annee_Travail,P_Cat,$C28,P_Type,"Revenu")) | M28: =IF($C28="",0,SUMIFS(J_Montant,J_Annee,Annee_Travail,J_Mois,5,J_Cat,$C28,J_Type,"Revenu",J_Statut,"<>Annulé",J_Statut,"<>Prévu")) | N28: =IF($C28="",0,SUMIFS(P_M6,P_Annee,Annee_Travail,P_Cat,$C28,P_Type,"Revenu")) | O28: =IF($C28="",0,SUMIFS(J_Montant,J_Annee,Annee_Travail,J_Mois,6,J_Cat,$C28,J_Type,"Revenu",J_Statut,"<>Annulé",J_Statut,"<>Prévu")) | P28: =IF($C28="",0,SUMIFS(P_M7,P_Annee,Annee_Travail,P_Cat,$C28,P_Type,"Revenu")) | Q28: =IF($C28="",0,SUMIFS(J_Montant,J_Annee,Annee_Travail,J_Mois,7,J_Cat,$C28,J_Type,"Revenu",J_Statut,"<>Annulé",J_Statut,"<>Prévu")) | R28: =IF($C28="",0,SUMIFS(P_M8,P_Annee,Annee_Travail,P_Cat,$C28,P_Type,"Revenu")) | S28: =IF($C28="",0,SUMIFS(J_Montant,J_Annee,Annee_Travail,J_Mois,8,J_Cat,$C28,J_Type,"Revenu",J_Statut,"<>Annulé",J_Statut,"<>Prévu")) | T28: =IF($C28="",0,SUMIFS(P_M9,P_Annee,Annee_Travail,P_Cat,$C28,P_Type,"Revenu")) | U28: =IF($C28="",0,SUMIFS(J_Montant,J_Annee,Annee_Travail,J_Mois,9,J_Cat,$C28,J_Type,"Revenu",J_Statut,"<>Annulé",J_Statut,"<>Prévu")) | V28: =IF($C28="",0,SUMIFS(P_M10,P_Annee,Annee_Travail,P_Cat,$C28,P_Type,"Revenu")) | W28: =IF($C28="",0,SUMIFS(J_Montant,J_Annee,Annee_Travail,J_Mois,10,J_Cat,$C28,J_Type,"Revenu",J_Statut,"<>Annulé",J_Statut,"<>Prévu")) | X28: =IF($C28="",0,SUMIFS(P_M11,P_Annee,Annee_Travail,P_Cat,$C28,P_Type,"Revenu")) | Y28: =IF($C28="",0,SUMIFS(J_Montant,J_Annee,Annee_Travail,J_Mois,11,J_Cat,$C28,J_Type,"Revenu",J_Statut,"<>Annulé",J_Statut,"<>Prévu")) | Z28: =IF($C28="",0,SUMIFS(P_M12,P_Annee,Annee_Travail,P_Cat,$C28,P_Type,"Revenu")) | AA28: =IF($C28="",0,SUMIFS(J_Montant,J_Annee,Annee_Travail,J_Mois,12,J_Cat,$C28,J_Type,"Revenu",J_Statut,"<>Annulé",J_Statut,"<>Prévu")) | AB28: =D28+F28+H28+J28+L28+N28+P28+R28+T28+V28+X28+Z28 | AC28: =E28+G28+I28+K28+M28+O28+Q28+S28+U28+W28+Y28+AA28 | AD28: =$AC28-$AB28 | AE28: =IFERROR($AC28/$AB28,0)
C29: TOTAL DES ENTRÉES | D29: =SUM(D11:D28) | E29: =SUM(E11:E28) | F29: =SUM(F11:F28) | G29: =SUM(G11:G28) | H29: =SUM(H11:H28) | I29: =SUM(I11:I28) | J29: =SUM(J11:J28) | K29: =SUM(K11:K28) | ... AA29: =SUM(AA11:AA28) | AB29: =D29+F29+H29+J29+L29+N29+P29+R29+T29+V29+X29+Z29 | AC29: =E29+G29+I29+K29+M29+O29+Q29+S29+U29+W29+Y29+AA29 | AD29: =$AC29-$AB29 | AE29: =IFERROR($AC29/$AB29,0)
B31: B ▸ ÉPARGNE, PLACEMENTS & PROVISIONS (vos objectifs)
B32: 1 | C32: =IF(Objectifs!$C$10="","",Objectifs!$C$10) | D32: =IF($C32="",0,N(Objectifs!$J$10)) | E32: =IF($C32="",0,SUMIFS(J_Montant,J_Annee,Annee_Travail,J_Mois,1,J_Projet,$C32,J_Type,"Épargne",J_Statut,"<>Annulé",J_Statut,"<>Prévu")+SUMIFS(J_Montant,J_Annee,Annee_Travail,J_Mois,1,J_Projet,$C32,J_Type,"Investissement",J_Statut,"<>Annulé",J_Statut,"<>Prévu")) | F32: =IF($C32="",0,N(Objectifs!$J$10)) | G32: =IF($C32="",0,SUMIFS(J_Montant,J_Annee,Annee_Travail,J_Mois,2,J_Projet,$C32,J_Type,"Épargne",J_Statut,"<>Annulé",J_Statut,"<>Prévu")+SUMIFS(J_Montant,J_Annee,Annee_Travail,J_Mois,2,J_Projet,$C32,J_Type,"Investissement",J_Statut,"<>Annulé",J_Statut,"<>Prévu")) | H32: =IF($C32="",0,N(Objectifs!$J$10)) | I32: =IF($C32="",0,SUMIFS(J_Montant,J_Annee,Annee_Travail,J_Mois,3,J_Projet,$C32,J_Type,"Épargne",J_Statut,"<>Annulé",J_Statut,"<>Prévu")+SUMIFS(J_Montant,J_Annee,Annee_Travail,J_Mois,3,J_Projet,$C32,J_Type,"Investissement",J_Statut,"<>Annulé",J_Statut,"<>Prévu")) | J32: =IF($C32="",0,N(Objectifs!$J$10)) | K32: =IF($C32="",0,SUMIFS(J_Montant,J_Annee,Annee_Travail,J_Mois,4,J_Projet,$C32,J_Type,"Épargne",J_Statut,"<>Annulé",J_Statut,"<>Prévu")+SUMIFS(J_Montant,J_Annee,Annee_Travail,J_Mois,4,J_Projet,$C32,J_Type,"Investissement",J_Statut,"<>Annulé",J_Statut,"<>Prévu")) | L32: =IF($C32="",0,N(Objectifs!$J$10)) | M32: =IF($C32="",0,SUMIFS(J_Montant,J_Annee,Annee_Travail,J_Mois,5,J_Projet,$C32,J_Type,"Épargne",J_Statut,"<>Annulé",J_Statut,"<>Prévu")+SUMIFS(J_Montant,J_Annee,Annee_Travail,J_Mois,5,J_Projet,$C32,J_Type,"Investissement",J_Statut,"<>Annulé",J_Statut,"<>Prévu")) | N32: =IF($C32="",0,N(Objectifs!$J$10)) | O32: =IF($C32="",0,SUMIFS(J_Montant,J_Annee,Annee_Travail,J_Mois,6,J_Projet,$C32,J_Type,"Épargne",J_Statut,"<>Annulé",J_Statut,"<>Prévu")+SUMIFS(J_Montant,J_Annee,Annee_Travail,J_Mois,6,J_Projet,$C32,J_Type,"Investissement",J_Statut,"<>Annulé",J_Statut,"<>Prévu")) | P32: =IF($C32="",0,N(Objectifs!$J$10)) | Q32: =IF($C32="",0,SUMIFS(J_Montant,J_Annee,Annee_Travail,J_Mois,7,J_Projet,$C32,J_Type,"Épargne",J_Statut,"<>Annulé",J_Statut,"<>Prévu")+SUMIFS(J_Montant,J_Annee,Annee_Travail,J_Mois,7,J_Projet,$C32,J_Type,"Investissement",J_Statut,"<>Annulé",J_Statut,"<>Prévu")) | R32: =IF($C32="",0,N(Objectifs!$J$10)) | S32: =IF($C32="",0,SUMIFS(J_Montant,J_Annee,Annee_Travail,J_Mois,8,J_Projet,$C32,J_Type,"Épargne",J_Statut,"<>Annulé",J_Statut,"<>Prévu")+SUMIFS(J_Montant,J_Annee,Annee_Travail,J_Mois,8,J_Projet,$C32,J_Type,"Investissement",J_Statut,"<>Annulé",J_Statut,"<>Prévu")) | T32: =IF($C32="",0,N(Objectifs!$J$10)) | U32: =IF($C32="",0,SUMIFS(J_Montant,J_Annee,Annee_Travail,J_Mois,9,J_Projet,$C32,J_Type,"Épargne",J_Statut,"<>Annulé",J_Statut,"<>Prévu")+SUMIFS(J_Montant,J_Annee,Annee_Travail,J_Mois,9,J_Projet,$C32,J_Type,"Investissement",J_Statut,"<>Annulé",J_Statut,"<>Prévu")) | V32: =IF($C32="",0,N(Objectifs!$J$10)) | W32: =IF($C32="",0,SUMIFS(J_Montant,J_Annee,Annee_Travail,J_Mois,10,J_Projet,$C32,J_Type,"Épargne",J_Statut,"<>Annulé",J_Statut,"<>Prévu")+SUMIFS(J_Montant,J_Annee,Annee_Travail,J_Mois,10,J_Projet,$C32,J_Type,"Investissement",J_Statut,"<>Annulé",J_Statut,"<>Prévu")) | X32: =IF($C32="",0,N(Objectifs!$J$10)) | Y32: =IF($C32="",0,SUMIFS(J_Montant,J_Annee,Annee_Travail,J_Mois,11,J_Projet,$C32,J_Type,"Épargne",J_Statut,"<>Annulé",J_Statut,"<>Prévu")+SUMIFS(J_Montant,J_Annee,Annee_Travail,J_Mois,11,J_Projet,$C32,J_Type,"Investissement",J_Statut,"<>Annulé",J_Statut,"<>Prévu")) | Z32: =IF($C32="",0,N(Objectifs!$J$10)) | AA32: =IF($C32="",0,SUMIFS(J_Montant,J_Annee,Annee_Travail,J_Mois,12,J_Projet,$C32,J_Type,"Épargne",J_Statut,"<>Annulé",J_Statut,"<>Prévu")+SUMIFS(J_Montant,J_Annee,Annee_Travail,J_Mois,12,J_Projet,$C32,J_Type,"Investissement",J_Statut,"<>Annulé",J_Statut,"<>Prévu")) | AB32: =D32+F32+H32+J32+L32+N32+P32+R32+T32+V32+X32+Z32 | AC32: =E32+G32+I32+K32+M32+O32+Q32+S32+U32+W32+Y32+AA32 | AD32: =$AB32-$AC32 | AE32: =IFERROR($AC32/$AB32,0)
B33: 2 | C33: =IF(Objectifs!$C$11="","",Objectifs!$C$11) | D33: =IF($C33="",0,N(Objectifs!$J$11)) | E33: =IF($C33="",0,SUMIFS(J_Montant,J_Annee,Annee_Travail,J_Mois,1,J_Projet,$C33,J_Type,"Épargne",J_Statut,"<>Annulé",J_Statut,"<>Prévu")+SUMIFS(J_Montant,J_Annee,Annee_Travail,J_Mois,1,J_Projet,$C33,J_Type,"Investissement",J_Statut,"<>Annulé",J_Statut,"<>Prévu")) | F33: =IF($C33="",0,N(Objectifs!$J$11)) | G33: =IF($C33="",0,SUMIFS(J_Montant,J_Annee,Annee_Travail,J_Mois,2,J_Projet,$C33,J_Type,"Épargne",J_Statut,"<>Annulé",J_Statut,"<>Prévu")+SUMIFS(J_Montant,J_Annee,Annee_Travail,J_Mois,2,J_Projet,$C33,J_Type,"Investissement",J_Statut,"<>Annulé",J_Statut,"<>Prévu")) | H33: =IF($C33="",0,N(Objectifs!$J$11)) | I33: =IF($C33="",0,SUMIFS(J_Montant,J_Annee,Annee_Travail,J_Mois,3,J_Projet,$C33,J_Type,"Épargne",J_Statut,"<>Annulé",J_Statut,"<>Prévu")+SUMIFS(J_Montant,J_Annee,Annee_Travail,J_Mois,3,J_Projet,$C33,J_Type,"Investissement",J_Statut,"<>Annulé",J_Statut,"<>Prévu")) | J33: =IF($C33="",0,N(Objectifs!$J$11)) | K33: =IF($C33="",0,SUMIFS(J_Montant,J_Annee,Annee_Travail,J_Mois,4,J_Projet,$C33,J_Type,"Épargne",J_Statut,"<>Annulé",J_Statut,"<>Prévu")+SUMIFS(J_Montant,J_Annee,Annee_Travail,J_Mois,4,J_Projet,$C33,J_Type,"Investissement",J_Statut,"<>Annulé",J_Statut,"<>Prévu")) | L33: =IF($C33="",0,N(Objectifs!$J$11)) | M33: =IF($C33="",0,SUMIFS(J_Montant,J_Annee,Annee_Travail,J_Mois,5,J_Projet,$C33,J_Type,"Épargne",J_Statut,"<>Annulé",J_Statut,"<>Prévu")+SUMIFS(J_Montant,J_Annee,Annee_Travail,J_Mois,5,J_Projet,$C33,J_Type,"Investissement",J_Statut,"<>Annulé",J_Statut,"<>Prévu")) | N33: =IF($C33="",0,N(Objectifs!$J$11)) | O33: =IF($C33="",0,SUMIFS(J_Montant,J_Annee,Annee_Travail,J_Mois,6,J_Projet,$C33,J_Type,"Épargne",J_Statut,"<>Annulé",J_Statut,"<>Prévu")+SUMIFS(J_Montant,J_Annee,Annee_Travail,J_Mois,6,J_Projet,$C33,J_Type,"Investissement",J_Statut,"<>Annulé",J_Statut,"<>Prévu")) | P33: =IF($C33="",0,N(Objectifs!$J$11)) | Q33: =IF($C33="",0,SUMIFS(J_Montant,J_Annee,Annee_Travail,J_Mois,7,J_Projet,$C33,J_Type,"Épargne",J_Statut,"<>Annulé",J_Statut,"<>Prévu")+SUMIFS(J_Montant,J_Annee,Annee_Travail,J_Mois,7,J_Projet,$C33,J_Type,"Investissement",J_Statut,"<>Annulé",J_Statut,"<>Prévu")) | R33: =IF($C33="",0,N(Objectifs!$J$11)) | S33: =IF($C33="",0,SUMIFS(J_Montant,J_Annee,Annee_Travail,J_Mois,8,J_Projet,$C33,J_Type,"Épargne",J_Statut,"<>Annulé",J_Statut,"<>Prévu")+SUMIFS(J_Montant,J_Annee,Annee_Travail,J_Mois,8,J_Projet,$C33,J_Type,"Investissement",J_Statut,"<>Annulé",J_Statut,"<>Prévu")) | T33: =IF($C33="",0,N(Objectifs!$J$11)) | U33: =IF($C33="",0,SUMIFS(J_Montant,J_Annee,Annee_Travail,J_Mois,9,J_Projet,$C33,J_Type,"Épargne",J_Statut,"<>Annulé",J_Statut,"<>Prévu")+SUMIFS(J_Montant,J_Annee,Annee_Travail,J_Mois,9,J_Projet,$C33,J_Type,"Investissement",J_Statut,"<>Annulé",J_Statut,"<>Prévu")) | V33: =IF($C33="",0,N(Objectifs!$J$11)) | W33: =IF($C33="",0,SUMIFS(J_Montant,J_Annee,Annee_Travail,J_Mois,10,J_Projet,$C33,J_Type,"Épargne",J_Statut,"<>Annulé",J_Statut,"<>Prévu")+SUMIFS(J_Montant,J_Annee,Annee_Travail,J_Mois,10,J_Projet,$C33,J_Type,"Investissement",J_Statut,"<>Annulé",J_Statut,"<>Prévu")) | X33: =IF($C33="",0,N(Objectifs!$J$11)) | Y33: =IF($C33="",0,SUMIFS(J_Montant,J_Annee,Annee_Travail,J_Mois,11,J_Projet,$C33,J_Type,"Épargne",J_Statut,"<>Annulé",J_Statut,"<>Prévu")+SUMIFS(J_Montant,J_Annee,Annee_Travail,J_Mois,11,J_Projet,$C33,J_Type,"Investissement",J_Statut,"<>Annulé",J_Statut,"<>Prévu")) | Z33: =IF($C33="",0,N(Objectifs!$J$11)) | AA33: =IF($C33="",0,SUMIFS(J_Montant,J_Annee,Annee_Travail,J_Mois,12,J_Projet,$C33,J_Type,"Épargne",J_Statut,"<>Annulé",J_Statut,"<>Prévu")+SUMIFS(J_Montant,J_Annee,Annee_Travail,J_Mois,12,J_Projet,$C33,J_Type,"Investissement",J_Statut,"<>Annulé",J_Statut,"<>Prévu")) | AB33: =D33+F33+H33+J33+L33+N33+P33+R33+T33+V33+X33+Z33 | AC33: =E33+G33+I33+K33+M33+O33+Q33+S33+U33+W33+Y33+AA33 | AD33: =$AB33-$AC33 | AE33: =IFERROR($AC33/$AB33,0)
B34: 3 | C34: =IF(Objectifs!$C$12="","",Objectifs!$C$12) | D34: =IF($C34="",0,N(Objectifs!$J$12)) | E34: =IF($C34="",0,SUMIFS(J_Montant,J_Annee,Annee_Travail,J_Mois,1,J_Projet,$C34,J_Type,"Épargne",J_Statut,"<>Annulé",J_Statut,"<>Prévu")+SUMIFS(J_Montant,J_Annee,Annee_Travail,J_Mois,1,J_Projet,$C34,J_Type,"Investissement",J_Statut,"<>Annulé",J_Statut,"<>Prévu")) | F34: =IF($C34="",0,N(Objectifs!$J$12)) | G34: =IF($C34="",0,SUMIFS(J_Montant,J_Annee,Annee_Travail,J_Mois,2,J_Projet,$C34,J_Type,"Épargne",J_Statut,"<>Annulé",J_Statut,"<>Prévu")+SUMIFS(J_Montant,J_Annee,Annee_Travail,J_Mois,2,J_Projet,$C34,J_Type,"Investissement",J_Statut,"<>Annulé",J_Statut,"<>Prévu")) | H34: =IF($C34="",0,N(Objectifs!$J$12)) | I34: =IF($C34="",0,SUMIFS(J_Montant,J_Annee,Annee_Travail,J_Mois,3,J_Projet,$C34,J_Type,"Épargne",J_Statut,"<>Annulé",J_Statut,"<>Prévu")+SUMIFS(J_Montant,J_Annee,Annee_Travail,J_Mois,3,J_Projet,$C34,J_Type,"Investissement",J_Statut,"<>Annulé",J_Statut,"<>Prévu")) | J34: =IF($C34="",0,N(Objectifs!$J$12)) | K34: =IF($C34="",0,SUMIFS(J_Montant,J_Annee,Annee_Travail,J_Mois,4,J_Projet,$C34,J_Type,"Épargne",J_Statut,"<>Annulé",J_Statut,"<>Prévu")+SUMIFS(J_Montant,J_Annee,Annee_Travail,J_Mois,4,J_Projet,$C34,J_Type,"Investissement",J_Statut,"<>Annulé",J_Statut,"<>Prévu")) | L34: =IF($C34="",0,N(Objectifs!$J$12)) | M34: =IF($C34="",0,SUMIFS(J_Montant,J_Annee,Annee_Travail,J_Mois,5,J_Projet,$C34,J_Type,"Épargne",J_Statut,"<>Annulé",J_Statut,"<>Prévu")+SUMIFS(J_Montant,J_Annee,Annee_Travail,J_Mois,5,J_Projet,$C34,J_Type,"Investissement",J_Statut,"<>Annulé",J_Statut,"<>Prévu")) | N34: =IF($C34="",0,N(Objectifs!$J$12)) | O34: =IF($C34="",0,SUMIFS(J_Montant,J_Annee,Annee_Travail,J_Mois,6,J_Projet,$C34,J_Type,"Épargne",J_Statut,"<>Annulé",J_Statut,"<>Prévu")+SUMIFS(J_Montant,J_Annee,Annee_Travail,J_Mois,6,J_Projet,$C34,J_Type,"Investissement",J_Statut,"<>Annulé",J_Statut,"<>Prévu")) | P34: =IF($C34="",0,N(Objectifs!$J$12)) | Q34: =IF($C34="",0,SUMIFS(J_Montant,J_Annee,Annee_Travail,J_Mois,7,J_Projet,$C34,J_Type,"Épargne",J_Statut,"<>Annulé",J_Statut,"<>Prévu")+SUMIFS(J_Montant,J_Annee,Annee_Travail,J_Mois,7,J_Projet,$C34,J_Type,"Investissement",J_Statut,"<>Annulé",J_Statut,"<>Prévu")) | R34: =IF($C34="",0,N(Objectifs!$J$12)) | S34: =IF($C34="",0,SUMIFS(J_Montant,J_Annee,Annee_Travail,J_Mois,8,J_Projet,$C34,J_Type,"Épargne",J_Statut,"<>Annulé",J_Statut,"<>Prévu")+SUMIFS(J_Montant,J_Annee,Annee_Travail,J_Mois,8,J_Projet,$C34,J_Type,"Investissement",J_Statut,"<>Annulé",J_Statut,"<>Prévu")) | T34: =IF($C34="",0,N(Objectifs!$J$12)) | U34: =IF($C34="",0,SUMIFS(J_Montant,J_Annee,Annee_Travail,J_Mois,9,J_Projet,$C34,J_Type,"Épargne",J_Statut,"<>Annulé",J_Statut,"<>Prévu")+SUMIFS(J_Montant,J_Annee,Annee_Travail,J_Mois,9,J_Projet,$C34,J_Type,"Investissement",J_Statut,"<>Annulé",J_Statut,"<>Prévu")) | V34: =IF($C34="",0,N(Objectifs!$J$12)) | W34: =IF($C34="",0,SUMIFS(J_Montant,J_Annee,Annee_Travail,J_Mois,10,J_Projet,$C34,J_Type,"Épargne",J_Statut,"<>Annulé",J_Statut,"<>Prévu")+SUMIFS(J_Montant,J_Annee,Annee_Travail,J_Mois,10,J_Projet,$C34,J_Type,"Investissement",J_Statut,"<>Annulé",J_Statut,"<>Prévu")) | X34: =IF($C34="",0,N(Objectifs!$J$12)) | Y34: =IF($C34="",0,SUMIFS(J_Montant,J_Annee,Annee_Travail,J_Mois,11,J_Projet,$C34,J_Type,"Épargne",J_Statut,"<>Annulé",J_Statut,"<>Prévu")+SUMIFS(J_Montant,J_Annee,Annee_Travail,J_Mois,11,J_Projet,$C34,J_Type,"Investissement",J_Statut,"<>Annulé",J_Statut,"<>Prévu")) | Z34: =IF($C34="",0,N(Objectifs!$J$12)) | AA34: =IF($C34="",0,SUMIFS(J_Montant,J_Annee,Annee_Travail,J_Mois,12,J_Projet,$C34,J_Type,"Épargne",J_Statut,"<>Annulé",J_Statut,"<>Prévu")+SUMIFS(J_Montant,J_Annee,Annee_Travail,J_Mois,12,J_Projet,$C34,J_Type,"Investissement",J_Statut,"<>Annulé",J_Statut,"<>Prévu")) | AB34: =D34+F34+H34+J34+L34+N34+P34+R34+T34+V34+X34+Z34 | AC34: =E34+G34+I34+K34+M34+O34+Q34+S34+U34+W34+Y34+AA34 | AD34: =$AB34-$AC34 | AE34: =IFERROR($AC34/$AB34,0)
B35: 4 | C35: =IF(Objectifs!$C$13="","",Objectifs!$C$13) | D35: =IF($C35="",0,N(Objectifs!$J$13)) | E35: =IF($C35="",0,SUMIFS(J_Montant,J_Annee,Annee_Travail,J_Mois,1,J_Projet,$C35,J_Type,"Épargne",J_Statut,"<>Annulé",J_Statut,"<>Prévu")+SUMIFS(J_Montant,J_Annee,Annee_Travail,J_Mois,1,J_Projet,$C35,J_Type,"Investissement",J_Statut,"<>Annulé",J_Statut,"<>Prévu")) | F35: =IF($C35="",0,N(Objectifs!$J$13)) | G35: =IF($C35="",0,SUMIFS(J_Montant,J_Annee,Annee_Travail,J_Mois,2,J_Projet,$C35,J_Type,"Épargne",J_Statut,"<>Annulé",J_Statut,"<>Prévu")+SUMIFS(J_Montant,J_Annee,Annee_Travail,J_Mois,2,J_Projet,$C35,J_Type,"Investissement",J_Statut,"<>Annulé",J_Statut,"<>Prévu")) | H35: =IF($C35="",0,N(Objectifs!$J$13)) | I35: =IF($C35="",0,SUMIFS(J_Montant,J_Annee,Annee_Travail,J_Mois,3,J_Projet,$C35,J_Type,"Épargne",J_Statut,"<>Annulé",J_Statut,"<>Prévu")+SUMIFS(J_Montant,J_Annee,Annee_Travail,J_Mois,3,J_Projet,$C35,J_Type,"Investissement",J_Statut,"<>Annulé",J_Statut,"<>Prévu")) | J35: =IF($C35="",0,N(Objectifs!$J$13)) | K35: =IF($C35="",0,SUMIFS(J_Montant,J_Annee,Annee_Travail,J_Mois,4,J_Projet,$C35,J_Type,"Épargne",J_Statut,"<>Annulé",J_Statut,"<>Prévu")+SUMIFS(J_Montant,J_Annee,Annee_Travail,J_Mois,4,J_Projet,$C35,J_Type,"Investissement",J_Statut,"<>Annulé",J_Statut,"<>Prévu")) | L35: =IF($C35="",0,N(Objectifs!$J$13)) | M35: =IF($C35="",0,SUMIFS(J_Montant,J_Annee,Annee_Travail,J_Mois,5,J_Projet,$C35,J_Type,"Épargne",J_Statut,"<>Annulé",J_Statut,"<>Prévu")+SUMIFS(J_Montant,J_Annee,Annee_Travail,J_Mois,5,J_Projet,$C35,J_Type,"Investissement",J_Statut,"<>Annulé",J_Statut,"<>Prévu")) | N35: =IF($C35="",0,N(Objectifs!$J$13)) | O35: =IF($C35="",0,SUMIFS(J_Montant,J_Annee,Annee_Travail,J_Mois,6,J_Projet,$C35,J_Type,"Épargne",J_Statut,"<>Annulé",J_Statut,"<>Prévu")+SUMIFS(J_Montant,J_Annee,Annee_Travail,J_Mois,6,J_Projet,$C35,J_Type,"Investissement",J_Statut,"<>Annulé",J_Statut,"<>Prévu")) | P35: =IF($C35="",0,N(Objectifs!$J$13)) | Q35: =IF($C35="",0,SUMIFS(J_Montant,J_Annee,Annee_Travail,J_Mois,7,J_Projet,$C35,J_Type,"Épargne",J_Statut,"<>Annulé",J_Statut,"<>Prévu")+SUMIFS(J_Montant,J_Annee,Annee_Travail,J_Mois,7,J_Projet,$C35,J_Type,"Investissement",J_Statut,"<>Annulé",J_Statut,"<>Prévu")) | R35: =IF($C35="",0,N(Objectifs!$J$13)) | S35: =IF($C35="",0,SUMIFS(J_Montant,J_Annee,Annee_Travail,J_Mois,8,J_Projet,$C35,J_Type,"Épargne",J_Statut,"<>Annulé",J_Statut,"<>Prévu")+SUMIFS(J_Montant,J_Annee,Annee_Travail,J_Mois,8,J_Projet,$C35,J_Type,"Investissement",J_Statut,"<>Annulé",J_Statut,"<>Prévu")) | T35: =IF($C35="",0,N(Objectifs!$J$13)) | U35: =IF($C35="",0,SUMIFS(J_Montant,J_Annee,Annee_Travail,J_Mois,9,J_Projet,$C35,J_Type,"Épargne",J_Statut,"<>Annulé",J_Statut,"<>Prévu")+SUMIFS(J_Montant,J_Annee,Annee_Travail,J_Mois,9,J_Projet,$C35,J_Type,"Investissement",J_Statut,"<>Annulé",J_Statut,"<>Prévu")) | V35: =IF($C35="",0,N(Objectifs!$J$13)) | W35: =IF($C35="",0,SUMIFS(J_Montant,J_Annee,Annee_Travail,J_Mois,10,J_Projet,$C35,J_Type,"Épargne",J_Statut,"<>Annulé",J_Statut,"<>Prévu")+SUMIFS(J_Montant,J_Annee,Annee_Travail,J_Mois,10,J_Projet,$C35,J_Type,"Investissement",J_Statut,"<>Annulé",J_Statut,"<>Prévu")) | X35: =IF($C35="",0,N(Objectifs!$J$13)) | Y35: =IF($C35="",0,SUMIFS(J_Montant,J_Annee,Annee_Travail,J_Mois,11,J_Projet,$C35,J_Type,"Épargne",J_Statut,"<>Annulé",J_Statut,"<>Prévu")+SUMIFS(J_Montant,J_Annee,Annee_Travail,J_Mois,11,J_Projet,$C35,J_Type,"Investissement",J_Statut,"<>Annulé",J_Statut,"<>Prévu")) | Z35: =IF($C35="",0,N(Objectifs!$J$13)) | AA35: =IF($C35="",0,SUMIFS(J_Montant,J_Annee,Annee_Travail,J_Mois,12,J_Projet,$C35,J_Type,"Épargne",J_Statut,"<>Annulé",J_Statut,"<>Prévu")+SUMIFS(J_Montant,J_Annee,Annee_Travail,J_Mois,12,J_Projet,$C35,J_Type,"Investissement",J_Statut,"<>Annulé",J_Statut,"<>Prévu")) | AB35: =D35+F35+H35+J35+L35+N35+P35+R35+T35+V35+X35+Z35 | AC35: =E35+G35+I35+K35+M35+O35+Q35+S35+U35+W35+Y35+AA35 | AD35: =$AB35-$AC35 | AE35: =IFERROR($AC35/$AB35,0)
B36: 5 | C36: =IF(Objectifs!$C$14="","",Objectifs!$C$14) | D36: =IF($C36="",0,N(Objectifs!$J$14)) | E36: =IF($C36="",0,SUMIFS(J_Montant,J_Annee,Annee_Travail,J_Mois,1,J_Projet,$C36,J_Type,"Épargne",J_Statut,"<>Annulé",J_Statut,"<>Prévu")+SUMIFS(J_Montant,J_Annee,Annee_Travail,J_Mois,1,J_Projet,$C36,J_Type,"Investissement",J_Statut,"<>Annulé",J_Statut,"<>Prévu")) | F36: =IF($C36="",0,N(Objectifs!$J$14)) | G36: =IF($C36="",0,SUMIFS(J_Montant,J_Annee,Annee_Travail,J_Mois,2,J_Projet,$C36,J_Type,"Épargne",J_Statut,"<>Annulé",J_Statut,"<>Prévu")+SUMIFS(J_Montant,J_Annee,Annee_Travail,J_Mois,2,J_Projet,$C36,J_Type,"Investissement",J_Statut,"<>Annulé",J_Statut,"<>Prévu")) | H36: =IF($C36="",0,N(Objectifs!$J$14)) | I36: =IF($C36="",0,SUMIFS(J_Montant,J_Annee,Annee_Travail,J_Mois,3,J_Projet,$C36,J_Type,"Épargne",J_Statut,"<>Annulé",J_Statut,"<>Prévu")+SUMIFS(J_Montant,J_Annee,Annee_Travail,J_Mois,3,J_Projet,$C36,J_Type,"Investissement",J_Statut,"<>Annulé",J_Statut,"<>Prévu")) | J36: =IF($C36="",0,N(Objectifs!$J$14)) | K36: =IF($C36="",0,SUMIFS(J_Montant,J_Annee,Annee_Travail,J_Mois,4,J_Projet,$C36,J_Type,"Épargne",J_Statut,"<>Annulé",J_Statut,"<>Prévu")+SUMIFS(J_Montant,J_Annee,Annee_Travail,J_Mois,4,J_Projet,$C36,J_Type,"Investissement",J_Statut,"<>Annulé",J_Statut,"<>Prévu")) | L36: =IF($C36="",0,N(Objectifs!$J$14)) | M36: =IF($C36="",0,SUMIFS(J_Montant,J_Annee,Annee_Travail,J_Mois,5,J_Projet,$C36,J_Type,"Épargne",J_Statut,"<>Annulé",J_Statut,"<>Prévu")+SUMIFS(J_Montant,J_Annee,Annee_Travail,J_Mois,5,J_Projet,$C36,J_Type,"Investissement",J_Statut,"<>Annulé",J_Statut,"<>Prévu")) | N36: =IF($C36="",0,N(Objectifs!$J$14)) | O36: =IF($C36="",0,SUMIFS(J_Montant,J_Annee,Annee_Travail,J_Mois,6,J_Projet,$C36,J_Type,"Épargne",J_Statut,"<>Annulé",J_Statut,"<>Prévu")+SUMIFS(J_Montant,J_Annee,Annee_Travail,J_Mois,6,J_Projet,$C36,J_Type,"Investissement",J_Statut,"<>Annulé",J_Statut,"<>Prévu")) | P36: =IF($C36="",0,N(Objectifs!$J$14)) | Q36: =IF($C36="",0,SUMIFS(J_Montant,J_Annee,Annee_Travail,J_Mois,7,J_Projet,$C36,J_Type,"Épargne",J_Statut,"<>Annulé",J_Statut,"<>Prévu")+SUMIFS(J_Montant,J_Annee,Annee_Travail,J_Mois,7,J_Projet,$C36,J_Type,"Investissement",J_Statut,"<>Annulé",J_Statut,"<>Prévu")) | R36: =IF($C36="",0,N(Objectifs!$J$14)) | S36: =IF($C36="",0,SUMIFS(J_Montant,J_Annee,Annee_Travail,J_Mois,8,J_Projet,$C36,J_Type,"Épargne",J_Statut,"<>Annulé",J_Statut,"<>Prévu")+SUMIFS(J_Montant,J_Annee,Annee_Travail,J_Mois,8,J_Projet,$C36,J_Type,"Investissement",J_Statut,"<>Annulé",J_Statut,"<>Prévu")) | T36: =IF($C36="",0,N(Objectifs!$J$14)) | U36: =IF($C36="",0,SUMIFS(J_Montant,J_Annee,Annee_Travail,J_Mois,9,J_Projet,$C36,J_Type,"Épargne",J_Statut,"<>Annulé",J_Statut,"<>Prévu")+SUMIFS(J_Montant,J_Annee,Annee_Travail,J_Mois,9,J_Projet,$C36,J_Type,"Investissement",J_Statut,"<>Annulé",J_Statut,"<>Prévu")) | V36: =IF($C36="",0,N(Objectifs!$J$14)) | W36: =IF($C36="",0,SUMIFS(J_Montant,J_Annee,Annee_Travail,J_Mois,10,J_Projet,$C36,J_Type,"Épargne",J_Statut,"<>Annulé",J_Statut,"<>Prévu")+SUMIFS(J_Montant,J_Annee,Annee_Travail,J_Mois,10,J_Projet,$C36,J_Type,"Investissement",J_Statut,"<>Annulé",J_Statut,"<>Prévu")) | X36: =IF($C36="",0,N(Objectifs!$J$14)) | Y36: =IF($C36="",0,SUMIFS(J_Montant,J_Annee,Annee_Travail,J_Mois,11,J_Projet,$C36,J_Type,"Épargne",J_Statut,"<>Annulé",J_Statut,"<>Prévu")+SUMIFS(J_Montant,J_Annee,Annee_Travail,J_Mois,11,J_Projet,$C36,J_Type,"Investissement",J_Statut,"<>Annulé",J_Statut,"<>Prévu")) | Z36: =IF($C36="",0,N(Objectifs!$J$14)) | AA36: =IF($C36="",0,SUMIFS(J_Montant,J_Annee,Annee_Travail,J_Mois,12,J_Projet,$C36,J_Type,"Épargne",J_Statut,"<>Annulé",J_Statut,"<>Prévu")+SUMIFS(J_Montant,J_Annee,Annee_Travail,J_Mois,12,J_Projet,$C36,J_Type,"Investissement",J_Statut,"<>Annulé",J_Statut,"<>Prévu")) | AB36: =D36+F36+H36+J36+L36+N36+P36+R36+T36+V36+X36+Z36 | AC36: =E36+G36+I36+K36+M36+O36+Q36+S36+U36+W36+Y36+AA36 | AD36: =$AB36-$AC36 | AE36: =IFERROR($AC36/$AB36,0)
B37: 6 | C37: =IF(Objectifs!$C$15="","",Objectifs!$C$15) | D37: =IF($C37="",0,N(Objectifs!$J$15)) | E37: =IF($C37="",0,SUMIFS(J_Montant,J_Annee,Annee_Travail,J_Mois,1,J_Projet,$C37,J_Type,"Épargne",J_Statut,"<>Annulé",J_Statut,"<>Prévu")+SUMIFS(J_Montant,J_Annee,Annee_Travail,J_Mois,1,J_Projet,$C37,J_Type,"Investissement",J_Statut,"<>Annulé",J_Statut,"<>Prévu")) | F37: =IF($C37="",0,N(Objectifs!$J$15)) | G37: =IF($C37="",0,SUMIFS(J_Montant,J_Annee,Annee_Travail,J_Mois,2,J_Projet,$C37,J_Type,"Épargne",J_Statut,"<>Annulé",J_Statut,"<>Prévu")+SUMIFS(J_Montant,J_Annee,Annee_Travail,J_Mois,2,J_Projet,$C37,J_Type,"Investissement",J_Statut,"<>Annulé",J_Statut,"<>Prévu")) | H37: =IF($C37="",0,N(Objectifs!$J$15)) | I37: =IF($C37="",0,SUMIFS(J_Montant,J_Annee,Annee_Travail,J_Mois,3,J_Projet,$C37,J_Type,"Épargne",J_Statut,"<>Annulé",J_Statut,"<>Prévu")+SUMIFS(J_Montant,J_Annee,Annee_Travail,J_Mois,3,J_Projet,$C37,J_Type,"Investissement",J_Statut,"<>Annulé",J_Statut,"<>Prévu")) | J37: =IF($C37="",0,N(Objectifs!$J$15)) | K37: =IF($C37="",0,SUMIFS(J_Montant,J_Annee,Annee_Travail,J_Mois,4,J_Projet,$C37,J_Type,"Épargne",J_Statut,"<>Annulé",J_Statut,"<>Prévu")+SUMIFS(J_Montant,J_Annee,Annee_Travail,J_Mois,4,J_Projet,$C37,J_Type,"Investissement",J_Statut,"<>Annulé",J_Statut,"<>Prévu")) | L37: =IF($C37="",0,N(Objectifs!$J$15)) | M37: =IF($C37="",0,SUMIFS(J_Montant,J_Annee,Annee_Travail,J_Mois,5,J_Projet,$C37,J_Type,"Épargne",J_Statut,"<>Annulé",J_Statut,"<>Prévu")+SUMIFS(J_Montant,J_Annee,Annee_Travail,J_Mois,5,J_Projet,$C37,J_Type,"Investissement",J_Statut,"<>Annulé",J_Statut,"<>Prévu")) | N37: =IF($C37="",0,N(Objectifs!$J$15)) | O37: =IF($C37="",0,SUMIFS(J_Montant,J_Annee,Annee_Travail,J_Mois,6,J_Projet,$C37,J_Type,"Épargne",J_Statut,"<>Annulé",J_Statut,"<>Prévu")+SUMIFS(J_Montant,J_Annee,Annee_Travail,J_Mois,6,J_Projet,$C37,J_Type,"Investissement",J_Statut,"<>Annulé",J_Statut,"<>Prévu")) | P37: =IF($C37="",0,N(Objectifs!$J$15)) | Q37: =IF($C37="",0,SUMIFS(J_Montant,J_Annee,Annee_Travail,J_Mois,7,J_Projet,$C37,J_Type,"Épargne",J_Statut,"<>Annulé",J_Statut,"<>Prévu")+SUMIFS(J_Montant,J_Annee,Annee_Travail,J_Mois,7,J_Projet,$C37,J_Type,"Investissement",J_Statut,"<>Annulé",J_Statut,"<>Prévu")) | R37: =IF($C37="",0,N(Objectifs!$J$15)) | S37: =IF($C37="",0,SUMIFS(J_Montant,J_Annee,Annee_Travail,J_Mois,8,J_Projet,$C37,J_Type,"Épargne",J_Statut,"<>Annulé",J_Statut,"<>Prévu")+SUMIFS(J_Montant,J_Annee,Annee_Travail,J_Mois,8,J_Projet,$C37,J_Type,"Investissement",J_Statut,"<>Annulé",J_Statut,"<>Prévu")) | T37: =IF($C37="",0,N(Objectifs!$J$15)) | U37: =IF($C37="",0,SUMIFS(J_Montant,J_Annee,Annee_Travail,J_Mois,9,J_Projet,$C37,J_Type,"Épargne",J_Statut,"<>Annulé",J_Statut,"<>Prévu")+SUMIFS(J_Montant,J_Annee,Annee_Travail,J_Mois,9,J_Projet,$C37,J_Type,"Investissement",J_Statut,"<>Annulé",J_Statut,"<>Prévu")) | V37: =IF($C37="",0,N(Objectifs!$J$15)) | W37: =IF($C37="",0,SUMIFS(J_Montant,J_Annee,Annee_Travail,J_Mois,10,J_Projet,$C37,J_Type,"Épargne",J_Statut,"<>Annulé",J_Statut,"<>Prévu")+SUMIFS(J_Montant,J_Annee,Annee_Travail,J_Mois,10,J_Projet,$C37,J_Type,"Investissement",J_Statut,"<>Annulé",J_Statut,"<>Prévu")) | X37: =IF($C37="",0,N(Objectifs!$J$15)) | Y37: =IF($C37="",0,SUMIFS(J_Montant,J_Annee,Annee_Travail,J_Mois,11,J_Projet,$C37,J_Type,"Épargne",J_Statut,"<>Annulé",J_Statut,"<>Prévu")+SUMIFS(J_Montant,J_Annee,Annee_Travail,J_Mois,11,J_Projet,$C37,J_Type,"Investissement",J_Statut,"<>Annulé",J_Statut,"<>Prévu")) | Z37: =IF($C37="",0,N(Objectifs!$J$15)) | AA37: =IF($C37="",0,SUMIFS(J_Montant,J_Annee,Annee_Travail,J_Mois,12,J_Projet,$C37,J_Type,"Épargne",J_Statut,"<>Annulé",J_Statut,"<>Prévu")+SUMIFS(J_Montant,J_Annee,Annee_Travail,J_Mois,12,J_Projet,$C37,J_Type,"Investissement",J_Statut,"<>Annulé",J_Statut,"<>Prévu")) | AB37: =D37+F37+H37+J37+L37+N37+P37+R37+T37+V37+X37+Z37 | AC37: =E37+G37+I37+K37+M37+O37+Q37+S37+U37+W37+Y37+AA37 | AD37: =$AB37-$AC37 | AE37: =IFERROR($AC37/$AB37,0)
B38: 7 | C38: =IF(Objectifs!$C$16="","",Objectifs!$C$16) | D38: =IF($C38="",0,N(Objectifs!$J$16)) | E38: =IF($C38="",0,SUMIFS(J_Montant,J_Annee,Annee_Travail,J_Mois,1,J_Projet,$C38,J_Type,"Épargne",J_Statut,"<>Annulé",J_Statut,"<>Prévu")+SUMIFS(J_Montant,J_Annee,Annee_Travail,J_Mois,1,J_Projet,$C38,J_Type,"Investissement",J_Statut,"<>Annulé",J_Statut,"<>Prévu")) | F38: =IF($C38="",0,N(Objectifs!$J$16)) | G38: =IF($C38="",0,SUMIFS(J_Montant,J_Annee,Annee_Travail,J_Mois,2,J_Projet,$C38,J_Type,"Épargne",J_Statut,"<>Annulé",J_Statut,"<>Prévu")+SUMIFS(J_Montant,J_Annee,Annee_Travail,J_Mois,2,J_Projet,$C38,J_Type,"Investissement",J_Statut,"<>Annulé",J_Statut,"<>Prévu")) | H38: =IF($C38="",0,N(Objectifs!$J$16)) | I38: =IF($C38="",0,SUMIFS(J_Montant,J_Annee,Annee_Travail,J_Mois,3,J_Projet,$C38,J_Type,"Épargne",J_Statut,"<>Annulé",J_Statut,"<>Prévu")+SUMIFS(J_Montant,J_Annee,Annee_Travail,J_Mois,3,J_Projet,$C38,J_Type,"Investissement",J_Statut,"<>Annulé",J_Statut,"<>Prévu")) | J38: =IF($C38="",0,N(Objectifs!$J$16)) | K38: =IF($C38="",0,SUMIFS(J_Montant,J_Annee,Annee_Travail,J_Mois,4,J_Projet,$C38,J_Type,"Épargne",J_Statut,"<>Annulé",J_Statut,"<>Prévu")+SUMIFS(J_Montant,J_Annee,Annee_Travail,J_Mois,4,J_Projet,$C38,J_Type,"Investissement",J_Statut,"<>Annulé",J_Statut,"<>Prévu")) | L38: =IF($C38="",0,N(Objectifs!$J$16)) | M38: =IF($C38="",0,SUMIFS(J_Montant,J_Annee,Annee_Travail,J_Mois,5,J_Projet,$C38,J_Type,"Épargne",J_Statut,"<>Annulé",J_Statut,"<>Prévu")+SUMIFS(J_Montant,J_Annee,Annee_Travail,J_Mois,5,J_Projet,$C38,J_Type,"Investissement",J_Statut,"<>Annulé",J_Statut,"<>Prévu")) | N38: =IF($C38="",0,N(Objectifs!$J$16)) | O38: =IF($C38="",0,SUMIFS(J_Montant,J_Annee,Annee_Travail,J_Mois,6,J_Projet,$C38,J_Type,"Épargne",J_Statut,"<>Annulé",J_Statut,"<>Prévu")+SUMIFS(J_Montant,J_Annee,Annee_Travail,J_Mois,6,J_Projet,$C38,J_Type,"Investissement",J_Statut,"<>Annulé",J_Statut,"<>Prévu")) | P38: =IF($C38="",0,N(Objectifs!$J$16)) | Q38: =IF($C38="",0,SUMIFS(J_Montant,J_Annee,Annee_Travail,J_Mois,7,J_Projet,$C38,J_Type,"Épargne",J_Statut,"<>Annulé",J_Statut,"<>Prévu")+SUMIFS(J_Montant,J_Annee,Annee_Travail,J_Mois,7,J_Projet,$C38,J_Type,"Investissement",J_Statut,"<>Annulé",J_Statut,"<>Prévu")) | R38: =IF($C38="",0,N(Objectifs!$J$16)) | S38: =IF($C38="",0,SUMIFS(J_Montant,J_Annee,Annee_Travail,J_Mois,8,J_Projet,$C38,J_Type,"Épargne",J_Statut,"<>Annulé",J_Statut,"<>Prévu")+SUMIFS(J_Montant,J_Annee,Annee_Travail,J_Mois,8,J_Projet,$C38,J_Type,"Investissement",J_Statut,"<>Annulé",J_Statut,"<>Prévu")) | T38: =IF($C38="",0,N(Objectifs!$J$16)) | U38: =IF($C38="",0,SUMIFS(J_Montant,J_Annee,Annee_Travail,J_Mois,9,J_Projet,$C38,J_Type,"Épargne",J_Statut,"<>Annulé",J_Statut,"<>Prévu")+SUMIFS(J_Montant,J_Annee,Annee_Travail,J_Mois,9,J_Projet,$C38,J_Type,"Investissement",J_Statut,"<>Annulé",J_Statut,"<>Prévu")) | V38: =IF($C38="",0,N(Objectifs!$J$16)) | W38: =IF($C38="",0,SUMIFS(J_Montant,J_Annee,Annee_Travail,J_Mois,10,J_Projet,$C38,J_Type,"Épargne",J_Statut,"<>Annulé",J_Statut,"<>Prévu")+SUMIFS(J_Montant,J_Annee,Annee_Travail,J_Mois,10,J_Projet,$C38,J_Type,"Investissement",J_Statut,"<>Annulé",J_Statut,"<>Prévu")) | X38: =IF($C38="",0,N(Objectifs!$J$16)) | Y38: =IF($C38="",0,SUMIFS(J_Montant,J_Annee,Annee_Travail,J_Mois,11,J_Projet,$C38,J_Type,"Épargne",J_Statut,"<>Annulé",J_Statut,"<>Prévu")+SUMIFS(J_Montant,J_Annee,Annee_Travail,J_Mois,11,J_Projet,$C38,J_Type,"Investissement",J_Statut,"<>Annulé",J_Statut,"<>Prévu")) | Z38: =IF($C38="",0,N(Objectifs!$J$16)) | AA38: =IF($C38="",0,SUMIFS(J_Montant,J_Annee,Annee_Travail,J_Mois,12,J_Projet,$C38,J_Type,"Épargne",J_Statut,"<>Annulé",J_Statut,"<>Prévu")+SUMIFS(J_Montant,J_Annee,Annee_Travail,J_Mois,12,J_Projet,$C38,J_Type,"Investissement",J_Statut,"<>Annulé",J_Statut,"<>Prévu")) | AB38: =D38+F38+H38+J38+L38+N38+P38+R38+T38+V38+X38+Z38 | AC38: =E38+G38+I38+K38+M38+O38+Q38+S38+U38+W38+Y38+AA38 | AD38: =$AB38-$AC38 | AE38: =IFERROR($AC38/$AB38,0)
B39: 8 | C39: =IF(Objectifs!$C$17="","",Objectifs!$C$17) | D39: =IF($C39="",0,N(Objectifs!$J$17)) | E39: =IF($C39="",0,SUMIFS(J_Montant,J_Annee,Annee_Travail,J_Mois,1,J_Projet,$C39,J_Type,"Épargne",J_Statut,"<>Annulé",J_Statut,"<>Prévu")+SUMIFS(J_Montant,J_Annee,Annee_Travail,J_Mois,1,J_Projet,$C39,J_Type,"Investissement",J_Statut,"<>Annulé",J_Statut,"<>Prévu")) | F39: =IF($C39="",0,N(Objectifs!$J$17)) | G39: =IF($C39="",0,SUMIFS(J_Montant,J_Annee,Annee_Travail,J_Mois,2,J_Projet,$C39,J_Type,"Épargne",J_Statut,"<>Annulé",J_Statut,"<>Prévu")+SUMIFS(J_Montant,J_Annee,Annee_Travail,J_Mois,2,J_Projet,$C39,J_Type,"Investissement",J_Statut,"<>Annulé",J_Statut,"<>Prévu")) | H39: =IF($C39="",0,N(Objectifs!$J$17)) | I39: =IF($C39="",0,SUMIFS(J_Montant,J_Annee,Annee_Travail,J_Mois,3,J_Projet,$C39,J_Type,"Épargne",J_Statut,"<>Annulé",J_Statut,"<>Prévu")+SUMIFS(J_Montant,J_Annee,Annee_Travail,J_Mois,3,J_Projet,$C39,J_Type,"Investissement",J_Statut,"<>Annulé",J_Statut,"<>Prévu")) | J39: =IF($C39="",0,N(Objectifs!$J$17)) | K39: =IF($C39="",0,SUMIFS(J_Montant,J_Annee,Annee_Travail,J_Mois,4,J_Projet,$C39,J_Type,"Épargne",J_Statut,"<>Annulé",J_Statut,"<>Prévu")+SUMIFS(J_Montant,J_Annee,Annee_Travail,J_Mois,4,J_Projet,$C39,J_Type,"Investissement",J_Statut,"<>Annulé",J_Statut,"<>Prévu")) | L39: =IF($C39="",0,N(Objectifs!$J$17)) | M39: =IF($C39="",0,SUMIFS(J_Montant,J_Annee,Annee_Travail,J_Mois,5,J_Projet,$C39,J_Type,"Épargne",J_Statut,"<>Annulé",J_Statut,"<>Prévu")+SUMIFS(J_Montant,J_Annee,Annee_Travail,J_Mois,5,J_Projet,$C39,J_Type,"Investissement",J_Statut,"<>Annulé",J_Statut,"<>Prévu")) | N39: =IF($C39="",0,N(Objectifs!$J$17)) | O39: =IF($C39="",0,SUMIFS(J_Montant,J_Annee,Annee_Travail,J_Mois,6,J_Projet,$C39,J_Type,"Épargne",J_Statut,"<>Annulé",J_Statut,"<>Prévu")+SUMIFS(J_Montant,J_Annee,Annee_Travail,J_Mois,6,J_Projet,$C39,J_Type,"Investissement",J_Statut,"<>Annulé",J_Statut,"<>Prévu")) | P39: =IF($C39="",0,N(Objectifs!$J$17)) | Q39: =IF($C39="",0,SUMIFS(J_Montant,J_Annee,Annee_Travail,J_Mois,7,J_Projet,$C39,J_Type,"Épargne",J_Statut,"<>Annulé",J_Statut,"<>Prévu")+SUMIFS(J_Montant,J_Annee,Annee_Travail,J_Mois,7,J_Projet,$C39,J_Type,"Investissement",J_Statut,"<>Annulé",J_Statut,"<>Prévu")) | R39: =IF($C39="",0,N(Objectifs!$J$17)) | S39: =IF($C39="",0,SUMIFS(J_Montant,J_Annee,Annee_Travail,J_Mois,8,J_Projet,$C39,J_Type,"Épargne",J_Statut,"<>Annulé",J_Statut,"<>Prévu")+SUMIFS(J_Montant,J_Annee,Annee_Travail,J_Mois,8,J_Projet,$C39,J_Type,"Investissement",J_Statut,"<>Annulé",J_Statut,"<>Prévu")) | T39: =IF($C39="",0,N(Objectifs!$J$17)) | U39: =IF($C39="",0,SUMIFS(J_Montant,J_Annee,Annee_Travail,J_Mois,9,J_Projet,$C39,J_Type,"Épargne",J_Statut,"<>Annulé",J_Statut,"<>Prévu")+SUMIFS(J_Montant,J_Annee,Annee_Travail,J_Mois,9,J_Projet,$C39,J_Type,"Investissement",J_Statut,"<>Annulé",J_Statut,"<>Prévu")) | V39: =IF($C39="",0,N(Objectifs!$J$17)) | W39: =IF($C39="",0,SUMIFS(J_Montant,J_Annee,Annee_Travail,J_Mois,10,J_Projet,$C39,J_Type,"Épargne",J_Statut,"<>Annulé",J_Statut,"<>Prévu")+SUMIFS(J_Montant,J_Annee,Annee_Travail,J_Mois,10,J_Projet,$C39,J_Type,"Investissement",J_Statut,"<>Annulé",J_Statut,"<>Prévu")) | X39: =IF($C39="",0,N(Objectifs!$J$17)) | Y39: =IF($C39="",0,SUMIFS(J_Montant,J_Annee,Annee_Travail,J_Mois,11,J_Projet,$C39,J_Type,"Épargne",J_Statut,"<>Annulé",J_Statut,"<>Prévu")+SUMIFS(J_Montant,J_Annee,Annee_Travail,J_Mois,11,J_Projet,$C39,J_Type,"Investissement",J_Statut,"<>Annulé",J_Statut,"<>Prévu")) | Z39: =IF($C39="",0,N(Objectifs!$J$17)) | AA39: =IF($C39="",0,SUMIFS(J_Montant,J_Annee,Annee_Travail,J_Mois,12,J_Projet,$C39,J_Type,"Épargne",J_Statut,"<>Annulé",J_Statut,"<>Prévu")+SUMIFS(J_Montant,J_Annee,Annee_Travail,J_Mois,12,J_Projet,$C39,J_Type,"Investissement",J_Statut,"<>Annulé",J_Statut,"<>Prévu")) | AB39: =D39+F39+H39+J39+L39+N39+P39+R39+T39+V39+X39+Z39 | AC39: =E39+G39+I39+K39+M39+O39+Q39+S39+U39+W39+Y39+AA39 | AD39: =$AB39-$AC39 | AE39: =IFERROR($AC39/$AB39,0)
B40: 9 | C40: =IF(Objectifs!$C$18="","",Objectifs!$C$18) | D40: =IF($C40="",0,N(Objectifs!$J$18)) | E40: =IF($C40="",0,SUMIFS(J_Montant,J_Annee,Annee_Travail,J_Mois,1,J_Projet,$C40,J_Type,"Épargne",J_Statut,"<>Annulé",J_Statut,"<>Prévu")+SUMIFS(J_Montant,J_Annee,Annee_Travail,J_Mois,1,J_Projet,$C40,J_Type,"Investissement",J_Statut,"<>Annulé",J_Statut,"<>Prévu")) | F40: =IF($C40="",0,N(Objectifs!$J$18)) | G40: =IF($C40="",0,SUMIFS(J_Montant,J_Annee,Annee_Travail,J_Mois,2,J_Projet,$C40,J_Type,"Épargne",J_Statut,"<>Annulé",J_Statut,"<>Prévu")+SUMIFS(J_Montant,J_Annee,Annee_Travail,J_Mois,2,J_Projet,$C40,J_Type,"Investissement",J_Statut,"<>Annulé",J_Statut,"<>Prévu")) | H40: =IF($C40="",0,N(Objectifs!$J$18)) | I40: =IF($C40="",0,SUMIFS(J_Montant,J_Annee,Annee_Travail,J_Mois,3,J_Projet,$C40,J_Type,"Épargne",J_Statut,"<>Annulé",J_Statut,"<>Prévu")+SUMIFS(J_Montant,J_Annee,Annee_Travail,J_Mois,3,J_Projet,$C40,J_Type,"Investissement",J_Statut,"<>Annulé",J_Statut,"<>Prévu")) | J40: =IF($C40="",0,N(Objectifs!$J$18)) | K40: =IF($C40="",0,SUMIFS(J_Montant,J_Annee,Annee_Travail,J_Mois,4,J_Projet,$C40,J_Type,"Épargne",J_Statut,"<>Annulé",J_Statut,"<>Prévu")+SUMIFS(J_Montant,J_Annee,Annee_Travail,J_Mois,4,J_Projet,$C40,J_Type,"Investissement",J_Statut,"<>Annulé",J_Statut,"<>Prévu")) | L40: =IF($C40="",0,N(Objectifs!$J$18)) | M40: =IF($C40="",0,SUMIFS(J_Montant,J_Annee,Annee_Travail,J_Mois,5,J_Projet,$C40,J_Type,"Épargne",J_Statut,"<>Annulé",J_Statut,"<>Prévu")+SUMIFS(J_Montant,J_Annee,Annee_Travail,J_Mois,5,J_Projet,$C40,J_Type,"Investissement",J_Statut,"<>Annulé",J_Statut,"<>Prévu")) | N40: =IF($C40="",0,N(Objectifs!$J$18)) | O40: =IF($C40="",0,SUMIFS(J_Montant,J_Annee,Annee_Travail,J_Mois,6,J_Projet,$C40,J_Type,"Épargne",J_Statut,"<>Annulé",J_Statut,"<>Prévu")+SUMIFS(J_Montant,J_Annee,Annee_Travail,J_Mois,6,J_Projet,$C40,J_Type,"Investissement",J_Statut,"<>Annulé",J_Statut,"<>Prévu")) | P40: =IF($C40="",0,N(Objectifs!$J$18)) | Q40: =IF($C40="",0,SUMIFS(J_Montant,J_Annee,Annee_Travail,J_Mois,7,J_Projet,$C40,J_Type,"Épargne",J_Statut,"<>Annulé",J_Statut,"<>Prévu")+SUMIFS(J_Montant,J_Annee,Annee_Travail,J_Mois,7,J_Projet,$C40,J_Type,"Investissement",J_Statut,"<>Annulé",J_Statut,"<>Prévu")) | R40: =IF($C40="",0,N(Objectifs!$J$18)) | S40: =IF($C40="",0,SUMIFS(J_Montant,J_Annee,Annee_Travail,J_Mois,8,J_Projet,$C40,J_Type,"Épargne",J_Statut,"<>Annulé",J_Statut,"<>Prévu")+SUMIFS(J_Montant,J_Annee,Annee_Travail,J_Mois,8,J_Projet,$C40,J_Type,"Investissement",J_Statut,"<>Annulé",J_Statut,"<>Prévu")) | T40: =IF($C40="",0,N(Objectifs!$J$18)) | U40: =IF($C40="",0,SUMIFS(J_Montant,J_Annee,Annee_Travail,J_Mois,9,J_Projet,$C40,J_Type,"Épargne",J_Statut,"<>Annulé",J_Statut,"<>Prévu")+SUMIFS(J_Montant,J_Annee,Annee_Travail,J_Mois,9,J_Projet,$C40,J_Type,"Investissement",J_Statut,"<>Annulé",J_Statut,"<>Prévu")) | V40: =IF($C40="",0,N(Objectifs!$J$18)) | W40: =IF($C40="",0,SUMIFS(J_Montant,J_Annee,Annee_Travail,J_Mois,10,J_Projet,$C40,J_Type,"Épargne",J_Statut,"<>Annulé",J_Statut,"<>Prévu")+SUMIFS(J_Montant,J_Annee,Annee_Travail,J_Mois,10,J_Projet,$C40,J_Type,"Investissement",J_Statut,"<>Annulé",J_Statut,"<>Prévu")) | X40: =IF($C40="",0,N(Objectifs!$J$18)) | Y40: =IF($C40="",0,SUMIFS(J_Montant,J_Annee,Annee_Travail,J_Mois,11,J_Projet,$C40,J_Type,"Épargne",J_Statut,"<>Annulé",J_Statut,"<>Prévu")+SUMIFS(J_Montant,J_Annee,Annee_Travail,J_Mois,11,J_Projet,$C40,J_Type,"Investissement",J_Statut,"<>Annulé",J_Statut,"<>Prévu")) | Z40: =IF($C40="",0,N(Objectifs!$J$18)) | AA40: =IF($C40="",0,SUMIFS(J_Montant,J_Annee,Annee_Travail,J_Mois,12,J_Projet,$C40,J_Type,"Épargne",J_Statut,"<>Annulé",J_Statut,"<>Prévu")+SUMIFS(J_Montant,J_Annee,Annee_Travail,J_Mois,12,J_Projet,$C40,J_Type,"Investissement",J_Statut,"<>Annulé",J_Statut,"<>Prévu")) | AB40: =D40+F40+H40+J40+L40+N40+P40+R40+T40+V40+X40+Z40 | AC40: =E40+G40+I40+K40+M40+O40+Q40+S40+U40+W40+Y40+AA40 | AD40: =$AB40-$AC40 | AE40: =IFERROR($AC40/$AB40,0)
B41: 10 | C41: =IF(Objectifs!$C$19="","",Objectifs!$C$19) | D41: =IF($C41="",0,N(Objectifs!$J$19)) | E41: =IF($C41="",0,SUMIFS(J_Montant,J_Annee,Annee_Travail,J_Mois,1,J_Projet,$C41,J_Type,"Épargne",J_Statut,"<>Annulé",J_Statut,"<>Prévu")+SUMIFS(J_Montant,J_Annee,Annee_Travail,J_Mois,1,J_Projet,$C41,J_Type,"Investissement",J_Statut,"<>Annulé",J_Statut,"<>Prévu")) | F41: =IF($C41="",0,N(Objectifs!$J$19)) | G41: =IF($C41="",0,SUMIFS(J_Montant,J_Annee,Annee_Travail,J_Mois,2,J_Projet,$C41,J_Type,"Épargne",J_Statut,"<>Annulé",J_Statut,"<>Prévu")+SUMIFS(J_Montant,J_Annee,Annee_Travail,J_Mois,2,J_Projet,$C41,J_Type,"Investissement",J_Statut,"<>Annulé",J_Statut,"<>Prévu")) | H41: =IF($C41="",0,N(Objectifs!$J$19)) | I41: =IF($C41="",0,SUMIFS(J_Montant,J_Annee,Annee_Travail,J_Mois,3,J_Projet,$C41,J_Type,"Épargne",J_Statut,"<>Annulé",J_Statut,"<>Prévu")+SUMIFS(J_Montant,J_Annee,Annee_Travail,J_Mois,3,J_Projet,$C41,J_Type,"Investissement",J_Statut,"<>Annulé",J_Statut,"<>Prévu")) | J41: =IF($C41="",0,N(Objectifs!$J$19)) | K41: =IF($C41="",0,SUMIFS(J_Montant,J_Annee,Annee_Travail,J_Mois,4,J_Projet,$C41,J_Type,"Épargne",J_Statut,"<>Annulé",J_Statut,"<>Prévu")+SUMIFS(J_Montant,J_Annee,Annee_Travail,J_Mois,4,J_Projet,$C41,J_Type,"Investissement",J_Statut,"<>Annulé",J_Statut,"<>Prévu")) | L41: =IF($C41="",0,N(Objectifs!$J$19)) | M41: =IF($C41="",0,SUMIFS(J_Montant,J_Annee,Annee_Travail,J_Mois,5,J_Projet,$C41,J_Type,"Épargne",J_Statut,"<>Annulé",J_Statut,"<>Prévu")+SUMIFS(J_Montant,J_Annee,Annee_Travail,J_Mois,5,J_Projet,$C41,J_Type,"Investissement",J_Statut,"<>Annulé",J_Statut,"<>Prévu")) | N41: =IF($C41="",0,N(Objectifs!$J$19)) | O41: =IF($C41="",0,SUMIFS(J_Montant,J_Annee,Annee_Travail,J_Mois,6,J_Projet,$C41,J_Type,"Épargne",J_Statut,"<>Annulé",J_Statut,"<>Prévu")+SUMIFS(J_Montant,J_Annee,Annee_Travail,J_Mois,6,J_Projet,$C41,J_Type,"Investissement",J_Statut,"<>Annulé",J_Statut,"<>Prévu")) | P41: =IF($C41="",0,N(Objectifs!$J$19)) | Q41: =IF($C41="",0,SUMIFS(J_Montant,J_Annee,Annee_Travail,J_Mois,7,J_Projet,$C41,J_Type,"Épargne",J_Statut,"<>Annulé",J_Statut,"<>Prévu")+SUMIFS(J_Montant,J_Annee,Annee_Travail,J_Mois,7,J_Projet,$C41,J_Type,"Investissement",J_Statut,"<>Annulé",J_Statut,"<>Prévu")) | R41: =IF($C41="",0,N(Objectifs!$J$19)) | S41: =IF($C41="",0,SUMIFS(J_Montant,J_Annee,Annee_Travail,J_Mois,8,J_Projet,$C41,J_Type,"Épargne",J_Statut,"<>Annulé",J_Statut,"<>Prévu")+SUMIFS(J_Montant,J_Annee,Annee_Travail,J_Mois,8,J_Projet,$C41,J_Type,"Investissement",J_Statut,"<>Annulé",J_Statut,"<>Prévu")) | T41: =IF($C41="",0,N(Objectifs!$J$19)) | U41: =IF($C41="",0,SUMIFS(J_Montant,J_Annee,Annee_Travail,J_Mois,9,J_Projet,$C41,J_Type,"Épargne",J_Statut,"<>Annulé",J_Statut,"<>Prévu")+SUMIFS(J_Montant,J_Annee,Annee_Travail,J_Mois,9,J_Projet,$C41,J_Type,"Investissement",J_Statut,"<>Annulé",J_Statut,"<>Prévu")) | V41: =IF($C41="",0,N(Objectifs!$J$19)) | W41: =IF($C41="",0,SUMIFS(J_Montant,J_Annee,Annee_Travail,J_Mois,10,J_Projet,$C41,J_Type,"Épargne",J_Statut,"<>Annulé",J_Statut,"<>Prévu")+SUMIFS(J_Montant,J_Annee,Annee_Travail,J_Mois,10,J_Projet,$C41,J_Type,"Investissement",J_Statut,"<>Annulé",J_Statut,"<>Prévu")) | X41: =IF($C41="",0,N(Objectifs!$J$19)) | Y41: =IF($C41="",0,SUMIFS(J_Montant,J_Annee,Annee_Travail,J_Mois,11,J_Projet,$C41,J_Type,"Épargne",J_Statut,"<>Annulé",J_Statut,"<>Prévu")+SUMIFS(J_Montant,J_Annee,Annee_Travail,J_Mois,11,J_Projet,$C41,J_Type,"Investissement",J_Statut,"<>Annulé",J_Statut,"<>Prévu")) | Z41: =IF($C41="",0,N(Objectifs!$J$19)) | AA41: =IF($C41="",0,SUMIFS(J_Montant,J_Annee,Annee_Travail,J_Mois,12,J_Projet,$C41,J_Type,"Épargne",J_Statut,"<>Annulé",J_Statut,"<>Prévu")+SUMIFS(J_Montant,J_Annee,Annee_Travail,J_Mois,12,J_Projet,$C41,J_Type,"Investissement",J_Statut,"<>Annulé",J_Statut,"<>Prévu")) | AB41: =D41+F41+H41+J41+L41+N41+P41+R41+T41+V41+X41+Z41 | AC41: =E41+G41+I41+K41+M41+O41+Q41+S41+U41+W41+Y41+AA41 | AD41: =$AB41-$AC41 | AE41: =IFERROR($AC41/$AB41,0)
B42: 11 | C42: =IF(Objectifs!$C$20="","",Objectifs!$C$20) | D42: =IF($C42="",0,N(Objectifs!$J$20)) | E42: =IF($C42="",0,SUMIFS(J_Montant,J_Annee,Annee_Travail,J_Mois,1,J_Projet,$C42,J_Type,"Épargne",J_Statut,"<>Annulé",J_Statut,"<>Prévu")+SUMIFS(J_Montant,J_Annee,Annee_Travail,J_Mois,1,J_Projet,$C42,J_Type,"Investissement",J_Statut,"<>Annulé",J_Statut,"<>Prévu")) | F42: =IF($C42="",0,N(Objectifs!$J$20)) | G42: =IF($C42="",0,SUMIFS(J_Montant,J_Annee,Annee_Travail,J_Mois,2,J_Projet,$C42,J_Type,"Épargne",J_Statut,"<>Annulé",J_Statut,"<>Prévu")+SUMIFS(J_Montant,J_Annee,Annee_Travail,J_Mois,2,J_Projet,$C42,J_Type,"Investissement",J_Statut,"<>Annulé",J_Statut,"<>Prévu")) | H42: =IF($C42="",0,N(Objectifs!$J$20)) | I42: =IF($C42="",0,SUMIFS(J_Montant,J_Annee,Annee_Travail,J_Mois,3,J_Projet,$C42,J_Type,"Épargne",J_Statut,"<>Annulé",J_Statut,"<>Prévu")+SUMIFS(J_Montant,J_Annee,Annee_Travail,J_Mois,3,J_Projet,$C42,J_Type,"Investissement",J_Statut,"<>Annulé",J_Statut,"<>Prévu")) | J42: =IF($C42="",0,N(Objectifs!$J$20)) | K42: =IF($C42="",0,SUMIFS(J_Montant,J_Annee,Annee_Travail,J_Mois,4,J_Projet,$C42,J_Type,"Épargne",J_Statut,"<>Annulé",J_Statut,"<>Prévu")+SUMIFS(J_Montant,J_Annee,Annee_Travail,J_Mois,4,J_Projet,$C42,J_Type,"Investissement",J_Statut,"<>Annulé",J_Statut,"<>Prévu")) | L42: =IF($C42="",0,N(Objectifs!$J$20)) | M42: =IF($C42="",0,SUMIFS(J_Montant,J_Annee,Annee_Travail,J_Mois,5,J_Projet,$C42,J_Type,"Épargne",J_Statut,"<>Annulé",J_Statut,"<>Prévu")+SUMIFS(J_Montant,J_Annee,Annee_Travail,J_Mois,5,J_Projet,$C42,J_Type,"Investissement",J_Statut,"<>Annulé",J_Statut,"<>Prévu")) | N42: =IF($C42="",0,N(Objectifs!$J$20)) | O42: =IF($C42="",0,SUMIFS(J_Montant,J_Annee,Annee_Travail,J_Mois,6,J_Projet,$C42,J_Type,"Épargne",J_Statut,"<>Annulé",J_Statut,"<>Prévu")+SUMIFS(J_Montant,J_Annee,Annee_Travail,J_Mois,6,J_Projet,$C42,J_Type,"Investissement",J_Statut,"<>Annulé",J_Statut,"<>Prévu")) | P42: =IF($C42="",0,N(Objectifs!$J$20)) | Q42: =IF($C42="",0,SUMIFS(J_Montant,J_Annee,Annee_Travail,J_Mois,7,J_Projet,$C42,J_Type,"Épargne",J_Statut,"<>Annulé",J_Statut,"<>Prévu")+SUMIFS(J_Montant,J_Annee,Annee_Travail,J_Mois,7,J_Projet,$C42,J_Type,"Investissement",J_Statut,"<>Annulé",J_Statut,"<>Prévu")) | R42: =IF($C42="",0,N(Objectifs!$J$20)) | S42: =IF($C42="",0,SUMIFS(J_Montant,J_Annee,Annee_Travail,J_Mois,8,J_Projet,$C42,J_Type,"Épargne",J_Statut,"<>Annulé",J_Statut,"<>Prévu")+SUMIFS(J_Montant,J_Annee,Annee_Travail,J_Mois,8,J_Projet,$C42,J_Type,"Investissement",J_Statut,"<>Annulé",J_Statut,"<>Prévu")) | T42: =IF($C42="",0,N(Objectifs!$J$20)) | U42: =IF($C42="",0,SUMIFS(J_Montant,J_Annee,Annee_Travail,J_Mois,9,J_Projet,$C42,J_Type,"Épargne",J_Statut,"<>Annulé",J_Statut,"<>Prévu")+SUMIFS(J_Montant,J_Annee,Annee_Travail,J_Mois,9,J_Projet,$C42,J_Type,"Investissement",J_Statut,"<>Annulé",J_Statut,"<>Prévu")) | V42: =IF($C42="",0,N(Objectifs!$J$20)) | W42: =IF($C42="",0,SUMIFS(J_Montant,J_Annee,Annee_Travail,J_Mois,10,J_Projet,$C42,J_Type,"Épargne",J_Statut,"<>Annulé",J_Statut,"<>Prévu")+SUMIFS(J_Montant,J_Annee,Annee_Travail,J_Mois,10,J_Projet,$C42,J_Type,"Investissement",J_Statut,"<>Annulé",J_Statut,"<>Prévu")) | X42: =IF($C42="",0,N(Objectifs!$J$20)) | Y42: =IF($C42="",0,SUMIFS(J_Montant,J_Annee,Annee_Travail,J_Mois,11,J_Projet,$C42,J_Type,"Épargne",J_Statut,"<>Annulé",J_Statut,"<>Prévu")+SUMIFS(J_Montant,J_Annee,Annee_Travail,J_Mois,11,J_Projet,$C42,J_Type,"Investissement",J_Statut,"<>Annulé",J_Statut,"<>Prévu")) | Z42: =IF($C42="",0,N(Objectifs!$J$20)) | AA42: =IF($C42="",0,SUMIFS(J_Montant,J_Annee,Annee_Travail,J_Mois,12,J_Projet,$C42,J_Type,"Épargne",J_Statut,"<>Annulé",J_Statut,"<>Prévu")+SUMIFS(J_Montant,J_Annee,Annee_Travail,J_Mois,12,J_Projet,$C42,J_Type,"Investissement",J_Statut,"<>Annulé",J_Statut,"<>Prévu")) | AB42: =D42+F42+H42+J42+L42+N42+P42+R42+T42+V42+X42+Z42 | AC42: =E42+G42+I42+K42+M42+O42+Q42+S42+U42+W42+Y42+AA42 | AD42: =$AB42-$AC42 | AE42: =IFERROR($AC42/$AB42,0)
B43: 12 | C43: =IF(Objectifs!$C$21="","",Objectifs!$C$21) | D43: =IF($C43="",0,N(Objectifs!$J$21)) | E43: =IF($C43="",0,SUMIFS(J_Montant,J_Annee,Annee_Travail,J_Mois,1,J_Projet,$C43,J_Type,"Épargne",J_Statut,"<>Annulé",J_Statut,"<>Prévu")+SUMIFS(J_Montant,J_Annee,Annee_Travail,J_Mois,1,J_Projet,$C43,J_Type,"Investissement",J_Statut,"<>Annulé",J_Statut,"<>Prévu")) | F43: =IF($C43="",0,N(Objectifs!$J$21)) | G43: =IF($C43="",0,SUMIFS(J_Montant,J_Annee,Annee_Travail,J_Mois,2,J_Projet,$C43,J_Type,"Épargne",J_Statut,"<>Annulé",J_Statut,"<>Prévu")+SUMIFS(J_Montant,J_Annee,Annee_Travail,J_Mois,2,J_Projet,$C43,J_Type,"Investissement",J_Statut,"<>Annulé",J_Statut,"<>Prévu")) | H43: =IF($C43="",0,N(Objectifs!$J$21)) | I43: =IF($C43="",0,SUMIFS(J_Montant,J_Annee,Annee_Travail,J_Mois,3,J_Projet,$C43,J_Type,"Épargne",J_Statut,"<>Annulé",J_Statut,"<>Prévu")+SUMIFS(J_Montant,J_Annee,Annee_Travail,J_Mois,3,J_Projet,$C43,J_Type,"Investissement",J_Statut,"<>Annulé",J_Statut,"<>Prévu")) | J43: =IF($C43="",0,N(Objectifs!$J$21)) | K43: =IF($C43="",0,SUMIFS(J_Montant,J_Annee,Annee_Travail,J_Mois,4,J_Projet,$C43,J_Type,"Épargne",J_Statut,"<>Annulé",J_Statut,"<>Prévu")+SUMIFS(J_Montant,J_Annee,Annee_Travail,J_Mois,4,J_Projet,$C43,J_Type,"Investissement",J_Statut,"<>Annulé",J_Statut,"<>Prévu")) | L43: =IF($C43="",0,N(Objectifs!$J$21)) | M43: =IF($C43="",0,SUMIFS(J_Montant,J_Annee,Annee_Travail,J_Mois,5,J_Projet,$C43,J_Type,"Épargne",J_Statut,"<>Annulé",J_Statut,"<>Prévu")+SUMIFS(J_Montant,J_Annee,Annee_Travail,J_Mois,5,J_Projet,$C43,J_Type,"Investissement",J_Statut,"<>Annulé",J_Statut,"<>Prévu")) | N43: =IF($C43="",0,N(Objectifs!$J$21)) | O43: =IF($C43="",0,SUMIFS(J_Montant,J_Annee,Annee_Travail,J_Mois,6,J_Projet,$C43,J_Type,"Épargne",J_Statut,"<>Annulé",J_Statut,"<>Prévu")+SUMIFS(J_Montant,J_Annee,Annee_Travail,J_Mois,6,J_Projet,$C43,J_Type,"Investissement",J_Statut,"<>Annulé",J_Statut,"<>Prévu")) | P43: =IF($C43="",0,N(Objectifs!$J$21)) | Q43: =IF($C43="",0,SUMIFS(J_Montant,J_Annee,Annee_Travail,J_Mois,7,J_Projet,$C43,J_Type,"Épargne",J_Statut,"<>Annulé",J_Statut,"<>Prévu")+SUMIFS(J_Montant,J_Annee,Annee_Travail,J_Mois,7,J_Projet,$C43,J_Type,"Investissement",J_Statut,"<>Annulé",J_Statut,"<>Prévu")) | R43: =IF($C43="",0,N(Objectifs!$J$21)) | S43: =IF($C43="",0,SUMIFS(J_Montant,J_Annee,Annee_Travail,J_Mois,8,J_Projet,$C43,J_Type,"Épargne",J_Statut,"<>Annulé",J_Statut,"<>Prévu")+SUMIFS(J_Montant,J_Annee,Annee_Travail,J_Mois,8,J_Projet,$C43,J_Type,"Investissement",J_Statut,"<>Annulé",J_Statut,"<>Prévu")) | T43: =IF($C43="",0,N(Objectifs!$J$21)) | U43: =IF($C43="",0,SUMIFS(J_Montant,J_Annee,Annee_Travail,J_Mois,9,J_Projet,$C43,J_Type,"Épargne",J_Statut,"<>Annulé",J_Statut,"<>Prévu")+SUMIFS(J_Montant,J_Annee,Annee_Travail,J_Mois,9,J_Projet,$C43,J_Type,"Investissement",J_Statut,"<>Annulé",J_Statut,"<>Prévu")) | V43: =IF($C43="",0,N(Objectifs!$J$21)) | W43: =IF($C43="",0,SUMIFS(J_Montant,J_Annee,Annee_Travail,J_Mois,10,J_Projet,$C43,J_Type,"Épargne",J_Statut,"<>Annulé",J_Statut,"<>Prévu")+SUMIFS(J_Montant,J_Annee,Annee_Travail,J_Mois,10,J_Projet,$C43,J_Type,"Investissement",J_Statut,"<>Annulé",J_Statut,"<>Prévu")) | X43: =IF($C43="",0,N(Objectifs!$J$21)) | Y43: =IF($C43="",0,SUMIFS(J_Montant,J_Annee,Annee_Travail,J_Mois,11,J_Projet,$C43,J_Type,"Épargne",J_Statut,"<>Annulé",J_Statut,"<>Prévu")+SUMIFS(J_Montant,J_Annee,Annee_Travail,J_Mois,11,J_Projet,$C43,J_Type,"Investissement",J_Statut,"<>Annulé",J_Statut,"<>Prévu")) | Z43: =IF($C43="",0,N(Objectifs!$J$21)) | AA43: =IF($C43="",0,SUMIFS(J_Montant,J_Annee,Annee_Travail,J_Mois,12,J_Projet,$C43,J_Type,"Épargne",J_Statut,"<>Annulé",J_Statut,"<>Prévu")+SUMIFS(J_Montant,J_Annee,Annee_Travail,J_Mois,12,J_Projet,$C43,J_Type,"Investissement",J_Statut,"<>Annulé",J_Statut,"<>Prévu")) | AB43: =D43+F43+H43+J43+L43+N43+P43+R43+T43+V43+X43+Z43 | AC43: =E43+G43+I43+K43+M43+O43+Q43+S43+U43+W43+Y43+AA43 | AD43: =$AB43-$AC43 | AE43: =IFERROR($AC43/$AB43,0)
B44: 13 | C44: Épargne / investissement non affecté à un objectif | D44: =0 | E44: =MAX(0,SUMIFS(J_Montant,J_Annee,Annee_Travail,J_Mois,1,J_Type,"Épargne",J_Statut,"<>Annulé",J_Statut,"<>Prévu")+SUMIFS(J_Montant,J_Annee,Annee_Travail,J_Mois,1,J_Type,"Investissement",J_Statut,"<>Annulé",J_Statut,"<>Prévu")-SUM(E32:E43)) | F44: =0 | G44: =MAX(0,SUMIFS(J_Montant,J_Annee,Annee_Travail,J_Mois,2,J_Type,"Épargne",J_Statut,"<>Annulé",J_Statut,"<>Prévu")+SUMIFS(J_Montant,J_Annee,Annee_Travail,J_Mois,2,J_Type,"Investissement",J_Statut,"<>Annulé",J_Statut,"<>Prévu")-SUM(G32:G43)) | H44: =0 | I44: =MAX(0,SUMIFS(J_Montant,J_Annee,Annee_Travail,J_Mois,3,J_Type,"Épargne",J_Statut,"<>Annulé",J_Statut,"<>Prévu")+SUMIFS(J_Montant,J_Annee,Annee_Travail,J_Mois,3,J_Type,"Investissement",J_Statut,"<>Annulé",J_Statut,"<>Prévu")-SUM(I32:I43)) | J44: =0 | K44: =MAX(0,SUMIFS(J_Montant,J_Annee,Annee_Travail,J_Mois,4,J_Type,"Épargne",J_Statut,"<>Annulé",J_Statut,"<>Prévu")+SUMIFS(J_Montant,J_Annee,Annee_Travail,J_Mois,4,J_Type,"Investissement",J_Statut,"<>Annulé",J_Statut,"<>Prévu")-SUM(K32:K43)) | L44: =0 | M44: =MAX(0,SUMIFS(J_Montant,J_Annee,Annee_Travail,J_Mois,5,J_Type,"Épargne",J_Statut,"<>Annulé",J_Statut,"<>Prévu")+SUMIFS(J_Montant,J_Annee,Annee_Travail,J_Mois,5,J_Type,"Investissement",J_Statut,"<>Annulé",J_Statut,"<>Prévu")-SUM(M32:M43)) | N44: =0 | O44: =MAX(0,SUMIFS(J_Montant,J_Annee,Annee_Travail,J_Mois,6,J_Type,"Épargne",J_Statut,"<>Annulé",J_Statut,"<>Prévu")+SUMIFS(J_Montant,J_Annee,Annee_Travail,J_Mois,6,J_Type,"Investissement",J_Statut,"<>Annulé",J_Statut,"<>Prévu")-SUM(O32:O43)) | P44: =0 | Q44: =MAX(0,SUMIFS(J_Montant,J_Annee,Annee_Travail,J_Mois,7,J_Type,"Épargne",J_Statut,"<>Annulé",J_Statut,"<>Prévu")+SUMIFS(J_Montant,J_Annee,Annee_Travail,J_Mois,7,J_Type,"Investissement",J_Statut,"<>Annulé",J_Statut,"<>Prévu")-SUM(Q32:Q43)) | R44: =0 | S44: =MAX(0,SUMIFS(J_Montant,J_Annee,Annee_Travail,J_Mois,8,J_Type,"Épargne",J_Statut,"<>Annulé",J_Statut,"<>Prévu")+SUMIFS(J_Montant,J_Annee,Annee_Travail,J_Mois,8,J_Type,"Investissement",J_Statut,"<>Annulé",J_Statut,"<>Prévu")-SUM(S32:S43)) | T44: =0 | U44: =MAX(0,SUMIFS(J_Montant,J_Annee,Annee_Travail,J_Mois,9,J_Type,"Épargne",J_Statut,"<>Annulé",J_Statut,"<>Prévu")+SUMIFS(J_Montant,J_Annee,Annee_Travail,J_Mois,9,J_Type,"Investissement",J_Statut,"<>Annulé",J_Statut,"<>Prévu")-SUM(U32:U43)) | V44: =0 | W44: =MAX(0,SUMIFS(J_Montant,J_Annee,Annee_Travail,J_Mois,10,J_Type,"Épargne",J_Statut,"<>Annulé",J_Statut,"<>Prévu")+SUMIFS(J_Montant,J_Annee,Annee_Travail,J_Mois,10,J_Type,"Investissement",J_Statut,"<>Annulé",J_Statut,"<>Prévu")-SUM(W32:W43)) | X44: =0 | Y44: =MAX(0,SUMIFS(J_Montant,J_Annee,Annee_Travail,J_Mois,11,J_Type,"Épargne",J_Statut,"<>Annulé",J_Statut,"<>Prévu")+SUMIFS(J_Montant,J_Annee,Annee_Travail,J_Mois,11,J_Type,"Investissement",J_Statut,"<>Annulé",J_Statut,"<>Prévu")-SUM(Y32:Y43)) | Z44: =0 | AA44: =MAX(0,SUMIFS(J_Montant,J_Annee,Annee_Travail,J_Mois,12,J_Type,"Épargne",J_Statut,"<>Annulé",J_Statut,"<>Prévu")+SUMIFS(J_Montant,J_Annee,Annee_Travail,J_Mois,12,J_Type,"Investissement",J_Statut,"<>Annulé",J_Statut,"<>Prévu")-SUM(AA32:AA43)) | AB44: =D44+F44+H44+J44+L44+N44+P44+R44+T44+V44+X44+Z44 | AC44: =E44+G44+I44+K44+M44+O44+Q44+S44+U44+W44+Y44+AA44 | AD44: =$AB44-$AC44 | AE44: =IFERROR($AC44/$AB44,0)
C45: TOTAL ÉPARGNE & PROVISIONS | D45: =SUM(D32:D44) | E45: =SUM(E32:E44) | F45: =SUM(F32:F44) | G45: =SUM(G32:G44) | H45: =SUM(H32:H44) | I45: =SUM(I32:I44) | J45: =SUM(J32:J44) | K45: =SUM(K32:K44) | ... AA45: =SUM(AA32:AA44) | AB45: =D45+F45+H45+J45+L45+N45+P45+R45+T45+V45+X45+Z45 | AC45: =E45+G45+I45+K45+M45+O45+Q45+S45+U45+W45+Y45+AA45 | AD45: =$AB45-$AC45 | AE45: =IFERROR($AC45/$AB45,0)
B47: C ▸ CRÉDITS & DETTES (remboursements)
B48: 1 | C48: =IF(Dettes!$C$10="","",Dettes!$C$10) | D48: =IF($C48="",0,N(Dettes!$I$10)) | E48: =IF($C48="",0,SUMIFS(J_Montant,J_Annee,Annee_Travail,J_Mois,1,J_Projet,$C48,J_Type,"Remboursement crédit",J_Statut,"<>Annulé",J_Statut,"<>Prévu")) | F48: =IF($C48="",0,N(Dettes!$I$10)) | G48: =IF($C48="",0,SUMIFS(J_Montant,J_Annee,Annee_Travail,J_Mois,2,J_Projet,$C48,J_Type,"Remboursement crédit",J_Statut,"<>Annulé",J_Statut,"<>Prévu")) | H48: =IF($C48="",0,N(Dettes!$I$10)) | I48: =IF($C48="",0,SUMIFS(J_Montant,J_Annee,Annee_Travail,J_Mois,3,J_Projet,$C48,J_Type,"Remboursement crédit",J_Statut,"<>Annulé",J_Statut,"<>Prévu")) | J48: =IF($C48="",0,N(Dettes!$I$10)) | K48: =IF($C48="",0,SUMIFS(J_Montant,J_Annee,Annee_Travail,J_Mois,4,J_Projet,$C48,J_Type,"Remboursement crédit",J_Statut,"<>Annulé",J_Statut,"<>Prévu")) | L48: =IF($C48="",0,N(Dettes!$I$10)) | M48: =IF($C48="",0,SUMIFS(J_Montant,J_Annee,Annee_Travail,J_Mois,5,J_Projet,$C48,J_Type,"Remboursement crédit",J_Statut,"<>Annulé",J_Statut,"<>Prévu")) | N48: =IF($C48="",0,N(Dettes!$I$10)) | O48: =IF($C48="",0,SUMIFS(J_Montant,J_Annee,Annee_Travail,J_Mois,6,J_Projet,$C48,J_Type,"Remboursement crédit",J_Statut,"<>Annulé",J_Statut,"<>Prévu")) | P48: =IF($C48="",0,N(Dettes!$I$10)) | Q48: =IF($C48="",0,SUMIFS(J_Montant,J_Annee,Annee_Travail,J_Mois,7,J_Projet,$C48,J_Type,"Remboursement crédit",J_Statut,"<>Annulé",J_Statut,"<>Prévu")) | R48: =IF($C48="",0,N(Dettes!$I$10)) | S48: =IF($C48="",0,SUMIFS(J_Montant,J_Annee,Annee_Travail,J_Mois,8,J_Projet,$C48,J_Type,"Remboursement crédit",J_Statut,"<>Annulé",J_Statut,"<>Prévu")) | T48: =IF($C48="",0,N(Dettes!$I$10)) | U48: =IF($C48="",0,SUMIFS(J_Montant,J_Annee,Annee_Travail,J_Mois,9,J_Projet,$C48,J_Type,"Remboursement crédit",J_Statut,"<>Annulé",J_Statut,"<>Prévu")) | V48: =IF($C48="",0,N(Dettes!$I$10)) | W48: =IF($C48="",0,SUMIFS(J_Montant,J_Annee,Annee_Travail,J_Mois,10,J_Projet,$C48,J_Type,"Remboursement crédit",J_Statut,"<>Annulé",J_Statut,"<>Prévu")) | X48: =IF($C48="",0,N(Dettes!$I$10)) | Y48: =IF($C48="",0,SUMIFS(J_Montant,J_Annee,Annee_Travail,J_Mois,11,J_Projet,$C48,J_Type,"Remboursement crédit",J_Statut,"<>Annulé",J_Statut,"<>Prévu")) | Z48: =IF($C48="",0,N(Dettes!$I$10)) | AA48: =IF($C48="",0,SUMIFS(J_Montant,J_Annee,Annee_Travail,J_Mois,12,J_Projet,$C48,J_Type,"Remboursement crédit",J_Statut,"<>Annulé",J_Statut,"<>Prévu")) | AB48: =D48+F48+H48+J48+L48+N48+P48+R48+T48+V48+X48+Z48 | AC48: =E48+G48+I48+K48+M48+O48+Q48+S48+U48+W48+Y48+AA48 | AD48: =$AB48-$AC48 | AE48: =IFERROR($AC48/$AB48,0)
B49: 2 | C49: =IF(Dettes!$C$11="","",Dettes!$C$11) | D49: =IF($C49="",0,N(Dettes!$I$11)) | E49: =IF($C49="",0,SUMIFS(J_Montant,J_Annee,Annee_Travail,J_Mois,1,J_Projet,$C49,J_Type,"Remboursement crédit",J_Statut,"<>Annulé",J_Statut,"<>Prévu")) | F49: =IF($C49="",0,N(Dettes!$I$11)) | G49: =IF($C49="",0,SUMIFS(J_Montant,J_Annee,Annee_Travail,J_Mois,2,J_Projet,$C49,J_Type,"Remboursement crédit",J_Statut,"<>Annulé",J_Statut,"<>Prévu")) | H49: =IF($C49="",0,N(Dettes!$I$11)) | I49: =IF($C49="",0,SUMIFS(J_Montant,J_Annee,Annee_Travail,J_Mois,3,J_Projet,$C49,J_Type,"Remboursement crédit",J_Statut,"<>Annulé",J_Statut,"<>Prévu")) | J49: =IF($C49="",0,N(Dettes!$I$11)) | K49: =IF($C49="",0,SUMIFS(J_Montant,J_Annee,Annee_Travail,J_Mois,4,J_Projet,$C49,J_Type,"Remboursement crédit",J_Statut,"<>Annulé",J_Statut,"<>Prévu")) | L49: =IF($C49="",0,N(Dettes!$I$11)) | M49: =IF($C49="",0,SUMIFS(J_Montant,J_Annee,Annee_Travail,J_Mois,5,J_Projet,$C49,J_Type,"Remboursement crédit",J_Statut,"<>Annulé",J_Statut,"<>Prévu")) | N49: =IF($C49="",0,N(Dettes!$I$11)) | O49: =IF($C49="",0,SUMIFS(J_Montant,J_Annee,Annee_Travail,J_Mois,6,J_Projet,$C49,J_Type,"Remboursement crédit",J_Statut,"<>Annulé",J_Statut,"<>Prévu")) | P49: =IF($C49="",0,N(Dettes!$I$11)) | Q49: =IF($C49="",0,SUMIFS(J_Montant,J_Annee,Annee_Travail,J_Mois,7,J_Projet,$C49,J_Type,"Remboursement crédit",J_Statut,"<>Annulé",J_Statut,"<>Prévu")) | R49: =IF($C49="",0,N(Dettes!$I$11)) | S49: =IF($C49="",0,SUMIFS(J_Montant,J_Annee,Annee_Travail,J_Mois,8,J_Projet,$C49,J_Type,"Remboursement crédit",J_Statut,"<>Annulé",J_Statut,"<>Prévu")) | T49: =IF($C49="",0,N(Dettes!$I$11)) | U49: =IF($C49="",0,SUMIFS(J_Montant,J_Annee,Annee_Travail,J_Mois,9,J_Projet,$C49,J_Type,"Remboursement crédit",J_Statut,"<>Annulé",J_Statut,"<>Prévu")) | V49: =IF($C49="",0,N(Dettes!$I$11)) | W49: =IF($C49="",0,SUMIFS(J_Montant,J_Annee,Annee_Travail,J_Mois,10,J_Projet,$C49,J_Type,"Remboursement crédit",J_Statut,"<>Annulé",J_Statut,"<>Prévu")) | X49: =IF($C49="",0,N(Dettes!$I$11)) | Y49: =IF($C49="",0,SUMIFS(J_Montant,J_Annee,Annee_Travail,J_Mois,11,J_Projet,$C49,J_Type,"Remboursement crédit",J_Statut,"<>Annulé",J_Statut,"<>Prévu")) | Z49: =IF($C49="",0,N(Dettes!$I$11)) | AA49: =IF($C49="",0,SUMIFS(J_Montant,J_Annee,Annee_Travail,J_Mois,12,J_Projet,$C49,J_Type,"Remboursement crédit",J_Statut,"<>Annulé",J_Statut,"<>Prévu")) | AB49: =D49+F49+H49+J49+L49+N49+P49+R49+T49+V49+X49+Z49 | AC49: =E49+G49+I49+K49+M49+O49+Q49+S49+U49+W49+Y49+AA49 | AD49: =$AB49-$AC49 | AE49: =IFERROR($AC49/$AB49,0)
B50: 3 | C50: =IF(Dettes!$C$12="","",Dettes!$C$12) | D50: =IF($C50="",0,N(Dettes!$I$12)) | E50: =IF($C50="",0,SUMIFS(J_Montant,J_Annee,Annee_Travail,J_Mois,1,J_Projet,$C50,J_Type,"Remboursement crédit",J_Statut,"<>Annulé",J_Statut,"<>Prévu")) | F50: =IF($C50="",0,N(Dettes!$I$12)) | G50: =IF($C50="",0,SUMIFS(J_Montant,J_Annee,Annee_Travail,J_Mois,2,J_Projet,$C50,J_Type,"Remboursement crédit",J_Statut,"<>Annulé",J_Statut,"<>Prévu")) | H50: =IF($C50="",0,N(Dettes!$I$12)) | I50: =IF($C50="",0,SUMIFS(J_Montant,J_Annee,Annee_Travail,J_Mois,3,J_Projet,$C50,J_Type,"Remboursement crédit",J_Statut,"<>Annulé",J_Statut,"<>Prévu")) | J50: =IF($C50="",0,N(Dettes!$I$12)) | K50: =IF($C50="",0,SUMIFS(J_Montant,J_Annee,Annee_Travail,J_Mois,4,J_Projet,$C50,J_Type,"Remboursement crédit",J_Statut,"<>Annulé",J_Statut,"<>Prévu")) | L50: =IF($C50="",0,N(Dettes!$I$12)) | M50: =IF($C50="",0,SUMIFS(J_Montant,J_Annee,Annee_Travail,J_Mois,5,J_Projet,$C50,J_Type,"Remboursement crédit",J_Statut,"<>Annulé",J_Statut,"<>Prévu")) | N50: =IF($C50="",0,N(Dettes!$I$12)) | O50: =IF($C50="",0,SUMIFS(J_Montant,J_Annee,Annee_Travail,J_Mois,6,J_Projet,$C50,J_Type,"Remboursement crédit",J_Statut,"<>Annulé",J_Statut,"<>Prévu")) | P50: =IF($C50="",0,N(Dettes!$I$12)) | Q50: =IF($C50="",0,SUMIFS(J_Montant,J_Annee,Annee_Travail,J_Mois,7,J_Projet,$C50,J_Type,"Remboursement crédit",J_Statut,"<>Annulé",J_Statut,"<>Prévu")) | R50: =IF($C50="",0,N(Dettes!$I$12)) | S50: =IF($C50="",0,SUMIFS(J_Montant,J_Annee,Annee_Travail,J_Mois,8,J_Projet,$C50,J_Type,"Remboursement crédit",J_Statut,"<>Annulé",J_Statut,"<>Prévu")) | T50: =IF($C50="",0,N(Dettes!$I$12)) | U50: =IF($C50="",0,SUMIFS(J_Montant,J_Annee,Annee_Travail,J_Mois,9,J_Projet,$C50,J_Type,"Remboursement crédit",J_Statut,"<>Annulé",J_Statut,"<>Prévu")) | V50: =IF($C50="",0,N(Dettes!$I$12)) | W50: =IF($C50="",0,SUMIFS(J_Montant,J_Annee,Annee_Travail,J_Mois,10,J_Projet,$C50,J_Type,"Remboursement crédit",J_Statut,"<>Annulé",J_Statut,"<>Prévu")) | X50: =IF($C50="",0,N(Dettes!$I$12)) | Y50: =IF($C50="",0,SUMIFS(J_Montant,J_Annee,Annee_Travail,J_Mois,11,J_Projet,$C50,J_Type,"Remboursement crédit",J_Statut,"<>Annulé",J_Statut,"<>Prévu")) | Z50: =IF($C50="",0,N(Dettes!$I$12)) | AA50: =IF($C50="",0,SUMIFS(J_Montant,J_Annee,Annee_Travail,J_Mois,12,J_Projet,$C50,J_Type,"Remboursement crédit",J_Statut,"<>Annulé",J_Statut,"<>Prévu")) | AB50: =D50+F50+H50+J50+L50+N50+P50+R50+T50+V50+X50+Z50 | AC50: =E50+G50+I50+K50+M50+O50+Q50+S50+U50+W50+Y50+AA50 | AD50: =$AB50-$AC50 | AE50: =IFERROR($AC50/$AB50,0)
B51: 4 | C51: =IF(Dettes!$C$13="","",Dettes!$C$13) | D51: =IF($C51="",0,N(Dettes!$I$13)) | E51: =IF($C51="",0,SUMIFS(J_Montant,J_Annee,Annee_Travail,J_Mois,1,J_Projet,$C51,J_Type,"Remboursement crédit",J_Statut,"<>Annulé",J_Statut,"<>Prévu")) | F51: =IF($C51="",0,N(Dettes!$I$13)) | G51: =IF($C51="",0,SUMIFS(J_Montant,J_Annee,Annee_Travail,J_Mois,2,J_Projet,$C51,J_Type,"Remboursement crédit",J_Statut,"<>Annulé",J_Statut,"<>Prévu")) | H51: =IF($C51="",0,N(Dettes!$I$13)) | I51: =IF($C51="",0,SUMIFS(J_Montant,J_Annee,Annee_Travail,J_Mois,3,J_Projet,$C51,J_Type,"Remboursement crédit",J_Statut,"<>Annulé",J_Statut,"<>Prévu")) | J51: =IF($C51="",0,N(Dettes!$I$13)) | K51: =IF($C51="",0,SUMIFS(J_Montant,J_Annee,Annee_Travail,J_Mois,4,J_Projet,$C51,J_Type,"Remboursement crédit",J_Statut,"<>Annulé",J_Statut,"<>Prévu")) | L51: =IF($C51="",0,N(Dettes!$I$13)) | M51: =IF($C51="",0,SUMIFS(J_Montant,J_Annee,Annee_Travail,J_Mois,5,J_Projet,$C51,J_Type,"Remboursement crédit",J_Statut,"<>Annulé",J_Statut,"<>Prévu")) | N51: =IF($C51="",0,N(Dettes!$I$13)) | O51: =IF($C51="",0,SUMIFS(J_Montant,J_Annee,Annee_Travail,J_Mois,6,J_Projet,$C51,J_Type,"Remboursement crédit",J_Statut,"<>Annulé",J_Statut,"<>Prévu")) | P51: =IF($C51="",0,N(Dettes!$I$13)) | Q51: =IF($C51="",0,SUMIFS(J_Montant,J_Annee,Annee_Travail,J_Mois,7,J_Projet,$C51,J_Type,"Remboursement crédit",J_Statut,"<>Annulé",J_Statut,"<>Prévu")) | R51: =IF($C51="",0,N(Dettes!$I$13)) | S51: =IF($C51="",0,SUMIFS(J_Montant,J_Annee,Annee_Travail,J_Mois,8,J_Projet,$C51,J_Type,"Remboursement crédit",J_Statut,"<>Annulé",J_Statut,"<>Prévu")) | T51: =IF($C51="",0,N(Dettes!$I$13)) | U51: =IF($C51="",0,SUMIFS(J_Montant,J_Annee,Annee_Travail,J_Mois,9,J_Projet,$C51,J_Type,"Remboursement crédit",J_Statut,"<>Annulé",J_Statut,"<>Prévu")) | V51: =IF($C51="",0,N(Dettes!$I$13)) | W51: =IF($C51="",0,SUMIFS(J_Montant,J_Annee,Annee_Travail,J_Mois,10,J_Projet,$C51,J_Type,"Remboursement crédit",J_Statut,"<>Annulé",J_Statut,"<>Prévu")) | X51: =IF($C51="",0,N(Dettes!$I$13)) | Y51: =IF($C51="",0,SUMIFS(J_Montant,J_Annee,Annee_Travail,J_Mois,11,J_Projet,$C51,J_Type,"Remboursement crédit",J_Statut,"<>Annulé",J_Statut,"<>Prévu")) | Z51: =IF($C51="",0,N(Dettes!$I$13)) | AA51: =IF($C51="",0,SUMIFS(J_Montant,J_Annee,Annee_Travail,J_Mois,12,J_Projet,$C51,J_Type,"Remboursement crédit",J_Statut,"<>Annulé",J_Statut,"<>Prévu")) | AB51: =D51+F51+H51+J51+L51+N51+P51+R51+T51+V51+X51+Z51 | AC51: =E51+G51+I51+K51+M51+O51+Q51+S51+U51+W51+Y51+AA51 | AD51: =$AB51-$AC51 | AE51: =IFERROR($AC51/$AB51,0)
B52: 5 | C52: =IF(Dettes!$C$14="","",Dettes!$C$14) | D52: =IF($C52="",0,N(Dettes!$I$14)) | E52: =IF($C52="",0,SUMIFS(J_Montant,J_Annee,Annee_Travail,J_Mois,1,J_Projet,$C52,J_Type,"Remboursement crédit",J_Statut,"<>Annulé",J_Statut,"<>Prévu")) | F52: =IF($C52="",0,N(Dettes!$I$14)) | G52: =IF($C52="",0,SUMIFS(J_Montant,J_Annee,Annee_Travail,J_Mois,2,J_Projet,$C52,J_Type,"Remboursement crédit",J_Statut,"<>Annulé",J_Statut,"<>Prévu")) | H52: =IF($C52="",0,N(Dettes!$I$14)) | I52: =IF($C52="",0,SUMIFS(J_Montant,J_Annee,Annee_Travail,J_Mois,3,J_Projet,$C52,J_Type,"Remboursement crédit",J_Statut,"<>Annulé",J_Statut,"<>Prévu")) | J52: =IF($C52="",0,N(Dettes!$I$14)) | K52: =IF($C52="",0,SUMIFS(J_Montant,J_Annee,Annee_Travail,J_Mois,4,J_Projet,$C52,J_Type,"Remboursement crédit",J_Statut,"<>Annulé",J_Statut,"<>Prévu")) | L52: =IF($C52="",0,N(Dettes!$I$14)) | M52: =IF($C52="",0,SUMIFS(J_Montant,J_Annee,Annee_Travail,J_Mois,5,J_Projet,$C52,J_Type,"Remboursement crédit",J_Statut,"<>Annulé",J_Statut,"<>Prévu")) | N52: =IF($C52="",0,N(Dettes!$I$14)) | O52: =IF($C52="",0,SUMIFS(J_Montant,J_Annee,Annee_Travail,J_Mois,6,J_Projet,$C52,J_Type,"Remboursement crédit",J_Statut,"<>Annulé",J_Statut,"<>Prévu")) | P52: =IF($C52="",0,N(Dettes!$I$14)) | Q52: =IF($C52="",0,SUMIFS(J_Montant,J_Annee,Annee_Travail,J_Mois,7,J_Projet,$C52,J_Type,"Remboursement crédit",J_Statut,"<>Annulé",J_Statut,"<>Prévu")) | R52: =IF($C52="",0,N(Dettes!$I$14)) | S52: =IF($C52="",0,SUMIFS(J_Montant,J_Annee,Annee_Travail,J_Mois,8,J_Projet,$C52,J_Type,"Remboursement crédit",J_Statut,"<>Annulé",J_Statut,"<>Prévu")) | T52: =IF($C52="",0,N(Dettes!$I$14)) | U52: =IF($C52="",0,SUMIFS(J_Montant,J_Annee,Annee_Travail,J_Mois,9,J_Projet,$C52,J_Type,"Remboursement crédit",J_Statut,"<>Annulé",J_Statut,"<>Prévu")) | V52: =IF($C52="",0,N(Dettes!$I$14)) | W52: =IF($C52="",0,SUMIFS(J_Montant,J_Annee,Annee_Travail,J_Mois,10,J_Projet,$C52,J_Type,"Remboursement crédit",J_Statut,"<>Annulé",J_Statut,"<>Prévu")) | X52: =IF($C52="",0,N(Dettes!$I$14)) | Y52: =IF($C52="",0,SUMIFS(J_Montant,J_Annee,Annee_Travail,J_Mois,11,J_Projet,$C52,J_Type,"Remboursement crédit",J_Statut,"<>Annulé",J_Statut,"<>Prévu")) | Z52: =IF($C52="",0,N(Dettes!$I$14)) | AA52: =IF($C52="",0,SUMIFS(J_Montant,J_Annee,Annee_Travail,J_Mois,12,J_Projet,$C52,J_Type,"Remboursement crédit",J_Statut,"<>Annulé",J_Statut,"<>Prévu")) | AB52: =D52+F52+H52+J52+L52+N52+P52+R52+T52+V52+X52+Z52 | AC52: =E52+G52+I52+K52+M52+O52+Q52+S52+U52+W52+Y52+AA52 | AD52: =$AB52-$AC52 | AE52: =IFERROR($AC52/$AB52,0)
B53: 6 | C53: =IF(Dettes!$C$15="","",Dettes!$C$15) | D53: =IF($C53="",0,N(Dettes!$I$15)) | E53: =IF($C53="",0,SUMIFS(J_Montant,J_Annee,Annee_Travail,J_Mois,1,J_Projet,$C53,J_Type,"Remboursement crédit",J_Statut,"<>Annulé",J_Statut,"<>Prévu")) | F53: =IF($C53="",0,N(Dettes!$I$15)) | G53: =IF($C53="",0,SUMIFS(J_Montant,J_Annee,Annee_Travail,J_Mois,2,J_Projet,$C53,J_Type,"Remboursement crédit",J_Statut,"<>Annulé",J_Statut,"<>Prévu")) | H53: =IF($C53="",0,N(Dettes!$I$15)) | I53: =IF($C53="",0,SUMIFS(J_Montant,J_Annee,Annee_Travail,J_Mois,3,J_Projet,$C53,J_Type,"Remboursement crédit",J_Statut,"<>Annulé",J_Statut,"<>Prévu")) | J53: =IF($C53="",0,N(Dettes!$I$15)) | K53: =IF($C53="",0,SUMIFS(J_Montant,J_Annee,Annee_Travail,J_Mois,4,J_Projet,$C53,J_Type,"Remboursement crédit",J_Statut,"<>Annulé",J_Statut,"<>Prévu")) | L53: =IF($C53="",0,N(Dettes!$I$15)) | M53: =IF($C53="",0,SUMIFS(J_Montant,J_Annee,Annee_Travail,J_Mois,5,J_Projet,$C53,J_Type,"Remboursement crédit",J_Statut,"<>Annulé",J_Statut,"<>Prévu")) | N53: =IF($C53="",0,N(Dettes!$I$15)) | O53: =IF($C53="",0,SUMIFS(J_Montant,J_Annee,Annee_Travail,J_Mois,6,J_Projet,$C53,J_Type,"Remboursement crédit",J_Statut,"<>Annulé",J_Statut,"<>Prévu")) | P53: =IF($C53="",0,N(Dettes!$I$15)) | Q53: =IF($C53="",0,SUMIFS(J_Montant,J_Annee,Annee_Travail,J_Mois,7,J_Projet,$C53,J_Type,"Remboursement crédit",J_Statut,"<>Annulé",J_Statut,"<>Prévu")) | R53: =IF($C53="",0,N(Dettes!$I$15)) | S53: =IF($C53="",0,SUMIFS(J_Montant,J_Annee,Annee_Travail,J_Mois,8,J_Projet,$C53,J_Type,"Remboursement crédit",J_Statut,"<>Annulé",J_Statut,"<>Prévu")) | T53: =IF($C53="",0,N(Dettes!$I$15)) | U53: =IF($C53="",0,SUMIFS(J_Montant,J_Annee,Annee_Travail,J_Mois,9,J_Projet,$C53,J_Type,"Remboursement crédit",J_Statut,"<>Annulé",J_Statut,"<>Prévu")) | V53: =IF($C53="",0,N(Dettes!$I$15)) | W53: =IF($C53="",0,SUMIFS(J_Montant,J_Annee,Annee_Travail,J_Mois,10,J_Projet,$C53,J_Type,"Remboursement crédit",J_Statut,"<>Annulé",J_Statut,"<>Prévu")) | X53: =IF($C53="",0,N(Dettes!$I$15)) | Y53: =IF($C53="",0,SUMIFS(J_Montant,J_Annee,Annee_Travail,J_Mois,11,J_Projet,$C53,J_Type,"Remboursement crédit",J_Statut,"<>Annulé",J_Statut,"<>Prévu")) | Z53: =IF($C53="",0,N(Dettes!$I$15)) | AA53: =IF($C53="",0,SUMIFS(J_Montant,J_Annee,Annee_Travail,J_Mois,12,J_Projet,$C53,J_Type,"Remboursement crédit",J_Statut,"<>Annulé",J_Statut,"<>Prévu")) | AB53: =D53+F53+H53+J53+L53+N53+P53+R53+T53+V53+X53+Z53 | AC53: =E53+G53+I53+K53+M53+O53+Q53+S53+U53+W53+Y53+AA53 | AD53: =$AB53-$AC53 | AE53: =IFERROR($AC53/$AB53,0)
B54: 7 | C54: =IF(Dettes!$C$16="","",Dettes!$C$16) | D54: =IF($C54="",0,N(Dettes!$I$16)) | E54: =IF($C54="",0,SUMIFS(J_Montant,J_Annee,Annee_Travail,J_Mois,1,J_Projet,$C54,J_Type,"Remboursement crédit",J_Statut,"<>Annulé",J_Statut,"<>Prévu")) | F54: =IF($C54="",0,N(Dettes!$I$16)) | G54: =IF($C54="",0,SUMIFS(J_Montant,J_Annee,Annee_Travail,J_Mois,2,J_Projet,$C54,J_Type,"Remboursement crédit",J_Statut,"<>Annulé",J_Statut,"<>Prévu")) | H54: =IF($C54="",0,N(Dettes!$I$16)) | I54: =IF($C54="",0,SUMIFS(J_Montant,J_Annee,Annee_Travail,J_Mois,3,J_Projet,$C54,J_Type,"Remboursement crédit",J_Statut,"<>Annulé",J_Statut,"<>Prévu")) | J54: =IF($C54="",0,N(Dettes!$I$16)) | K54: =IF($C54="",0,SUMIFS(J_Montant,J_Annee,Annee_Travail,J_Mois,4,J_Projet,$C54,J_Type,"Remboursement crédit",J_Statut,"<>Annulé",J_Statut,"<>Prévu")) | L54: =IF($C54="",0,N(Dettes!$I$16)) | M54: =IF($C54="",0,SUMIFS(J_Montant,J_Annee,Annee_Travail,J_Mois,5,J_Projet,$C54,J_Type,"Remboursement crédit",J_Statut,"<>Annulé",J_Statut,"<>Prévu")) | N54: =IF($C54="",0,N(Dettes!$I$16)) | O54: =IF($C54="",0,SUMIFS(J_Montant,J_Annee,Annee_Travail,J_Mois,6,J_Projet,$C54,J_Type,"Remboursement crédit",J_Statut,"<>Annulé",J_Statut,"<>Prévu")) | P54: =IF($C54="",0,N(Dettes!$I$16)) | Q54: =IF($C54="",0,SUMIFS(J_Montant,J_Annee,Annee_Travail,J_Mois,7,J_Projet,$C54,J_Type,"Remboursement crédit",J_Statut,"<>Annulé",J_Statut,"<>Prévu")) | R54: =IF($C54="",0,N(Dettes!$I$16)) | S54: =IF($C54="",0,SUMIFS(J_Montant,J_Annee,Annee_Travail,J_Mois,8,J_Projet,$C54,J_Type,"Remboursement crédit",J_Statut,"<>Annulé",J_Statut,"<>Prévu")) | T54: =IF($C54="",0,N(Dettes!$I$16)) | U54: =IF($C54="",0,SUMIFS(J_Montant,J_Annee,Annee_Travail,J_Mois,9,J_Projet,$C54,J_Type,"Remboursement crédit",J_Statut,"<>Annulé",J_Statut,"<>Prévu")) | V54: =IF($C54="",0,N(Dettes!$I$16)) | W54: =IF($C54="",0,SUMIFS(J_Montant,J_Annee,Annee_Travail,J_Mois,10,J_Projet,$C54,J_Type,"Remboursement crédit",J_Statut,"<>Annulé",J_Statut,"<>Prévu")) | X54: =IF($C54="",0,N(Dettes!$I$16)) | Y54: =IF($C54="",0,SUMIFS(J_Montant,J_Annee,Annee_Travail,J_Mois,11,J_Projet,$C54,J_Type,"Remboursement crédit",J_Statut,"<>Annulé",J_Statut,"<>Prévu")) | Z54: =IF($C54="",0,N(Dettes!$I$16)) | AA54: =IF($C54="",0,SUMIFS(J_Montant,J_Annee,Annee_Travail,J_Mois,12,J_Projet,$C54,J_Type,"Remboursement crédit",J_Statut,"<>Annulé",J_Statut,"<>Prévu")) | AB54: =D54+F54+H54+J54+L54+N54+P54+R54+T54+V54+X54+Z54 | AC54: =E54+G54+I54+K54+M54+O54+Q54+S54+U54+W54+Y54+AA54 | AD54: =$AB54-$AC54 | AE54: =IFERROR($AC54/$AB54,0)
B55: 8 | C55: =IF(Dettes!$C$17="","",Dettes!$C$17) | D55: =IF($C55="",0,N(Dettes!$I$17)) | E55: =IF($C55="",0,SUMIFS(J_Montant,J_Annee,Annee_Travail,J_Mois,1,J_Projet,$C55,J_Type,"Remboursement crédit",J_Statut,"<>Annulé",J_Statut,"<>Prévu")) | F55: =IF($C55="",0,N(Dettes!$I$17)) | G55: =IF($C55="",0,SUMIFS(J_Montant,J_Annee,Annee_Travail,J_Mois,2,J_Projet,$C55,J_Type,"Remboursement crédit",J_Statut,"<>Annulé",J_Statut,"<>Prévu")) | H55: =IF($C55="",0,N(Dettes!$I$17)) | I55: =IF($C55="",0,SUMIFS(J_Montant,J_Annee,Annee_Travail,J_Mois,3,J_Projet,$C55,J_Type,"Remboursement crédit",J_Statut,"<>Annulé",J_Statut,"<>Prévu")) | J55: =IF($C55="",0,N(Dettes!$I$17)) | K55: =IF($C55="",0,SUMIFS(J_Montant,J_Annee,Annee_Travail,J_Mois,4,J_Projet,$C55,J_Type,"Remboursement crédit",J_Statut,"<>Annulé",J_Statut,"<>Prévu")) | L55: =IF($C55="",0,N(Dettes!$I$17)) | M55: =IF($C55="",0,SUMIFS(J_Montant,J_Annee,Annee_Travail,J_Mois,5,J_Projet,$C55,J_Type,"Remboursement crédit",J_Statut,"<>Annulé",J_Statut,"<>Prévu")) | N55: =IF($C55="",0,N(Dettes!$I$17)) | O55: =IF($C55="",0,SUMIFS(J_Montant,J_Annee,Annee_Travail,J_Mois,6,J_Projet,$C55,J_Type,"Remboursement crédit",J_Statut,"<>Annulé",J_Statut,"<>Prévu")) | P55: =IF($C55="",0,N(Dettes!$I$17)) | Q55: =IF($C55="",0,SUMIFS(J_Montant,J_Annee,Annee_Travail,J_Mois,7,J_Projet,$C55,J_Type,"Remboursement crédit",J_Statut,"<>Annulé",J_Statut,"<>Prévu")) | R55: =IF($C55="",0,N(Dettes!$I$17)) | S55: =IF($C55="",0,SUMIFS(J_Montant,J_Annee,Annee_Travail,J_Mois,8,J_Projet,$C55,J_Type,"Remboursement crédit",J_Statut,"<>Annulé",J_Statut,"<>Prévu")) | T55: =IF($C55="",0,N(Dettes!$I$17)) | U55: =IF($C55="",0,SUMIFS(J_Montant,J_Annee,Annee_Travail,J_Mois,9,J_Projet,$C55,J_Type,"Remboursement crédit",J_Statut,"<>Annulé",J_Statut,"<>Prévu")) | V55: =IF($C55="",0,N(Dettes!$I$17)) | W55: =IF($C55="",0,SUMIFS(J_Montant,J_Annee,Annee_Travail,J_Mois,10,J_Projet,$C55,J_Type,"Remboursement crédit",J_Statut,"<>Annulé",J_Statut,"<>Prévu")) | X55: =IF($C55="",0,N(Dettes!$I$17)) | Y55: =IF($C55="",0,SUMIFS(J_Montant,J_Annee,Annee_Travail,J_Mois,11,J_Projet,$C55,J_Type,"Remboursement crédit",J_Statut,"<>Annulé",J_Statut,"<>Prévu")) | Z55: =IF($C55="",0,N(Dettes!$I$17)) | AA55: =IF($C55="",0,SUMIFS(J_Montant,J_Annee,Annee_Travail,J_Mois,12,J_Projet,$C55,J_Type,"Remboursement crédit",J_Statut,"<>Annulé",J_Statut,"<>Prévu")) | AB55: =D55+F55+H55+J55+L55+N55+P55+R55+T55+V55+X55+Z55 | AC55: =E55+G55+I55+K55+M55+O55+Q55+S55+U55+W55+Y55+AA55 | AD55: =$AB55-$AC55 | AE55: =IFERROR($AC55/$AB55,0)
B56: 9 | C56: =IF(Dettes!$C$18="","",Dettes!$C$18) | D56: =IF($C56="",0,N(Dettes!$I$18)) | E56: =IF($C56="",0,SUMIFS(J_Montant,J_Annee,Annee_Travail,J_Mois,1,J_Projet,$C56,J_Type,"Remboursement crédit",J_Statut,"<>Annulé",J_Statut,"<>Prévu")) | F56: =IF($C56="",0,N(Dettes!$I$18)) | G56: =IF($C56="",0,SUMIFS(J_Montant,J_Annee,Annee_Travail,J_Mois,2,J_Projet,$C56,J_Type,"Remboursement crédit",J_Statut,"<>Annulé",J_Statut,"<>Prévu")) | H56: =IF($C56="",0,N(Dettes!$I$18)) | I56: =IF($C56="",0,SUMIFS(J_Montant,J_Annee,Annee_Travail,J_Mois,3,J_Projet,$C56,J_Type,"Remboursement crédit",J_Statut,"<>Annulé",J_Statut,"<>Prévu")) | J56: =IF($C56="",0,N(Dettes!$I$18)) | K56: =IF($C56="",0,SUMIFS(J_Montant,J_Annee,Annee_Travail,J_Mois,4,J_Projet,$C56,J_Type,"Remboursement crédit",J_Statut,"<>Annulé",J_Statut,"<>Prévu")) | L56: =IF($C56="",0,N(Dettes!$I$18)) | M56: =IF($C56="",0,SUMIFS(J_Montant,J_Annee,Annee_Travail,J_Mois,5,J_Projet,$C56,J_Type,"Remboursement crédit",J_Statut,"<>Annulé",J_Statut,"<>Prévu")) | N56: =IF($C56="",0,N(Dettes!$I$18)) | O56: =IF($C56="",0,SUMIFS(J_Montant,J_Annee,Annee_Travail,J_Mois,6,J_Projet,$C56,J_Type,"Remboursement crédit",J_Statut,"<>Annulé",J_Statut,"<>Prévu")) | P56: =IF($C56="",0,N(Dettes!$I$18)) | Q56: =IF($C56="",0,SUMIFS(J_Montant,J_Annee,Annee_Travail,J_Mois,7,J_Projet,$C56,J_Type,"Remboursement crédit",J_Statut,"<>Annulé",J_Statut,"<>Prévu")) | R56: =IF($C56="",0,N(Dettes!$I$18)) | S56: =IF($C56="",0,SUMIFS(J_Montant,J_Annee,Annee_Travail,J_Mois,8,J_Projet,$C56,J_Type,"Remboursement crédit",J_Statut,"<>Annulé",J_Statut,"<>Prévu")) | T56: =IF($C56="",0,N(Dettes!$I$18)) | U56: =IF($C56="",0,SUMIFS(J_Montant,J_Annee,Annee_Travail,J_Mois,9,J_Projet,$C56,J_Type,"Remboursement crédit",J_Statut,"<>Annulé",J_Statut,"<>Prévu")) | V56: =IF($C56="",0,N(Dettes!$I$18)) | W56: =IF($C56="",0,SUMIFS(J_Montant,J_Annee,Annee_Travail,J_Mois,10,J_Projet,$C56,J_Type,"Remboursement crédit",J_Statut,"<>Annulé",J_Statut,"<>Prévu")) | X56: =IF($C56="",0,N(Dettes!$I$18)) | Y56: =IF($C56="",0,SUMIFS(J_Montant,J_Annee,Annee_Travail,J_Mois,11,J_Projet,$C56,J_Type,"Remboursement crédit",J_Statut,"<>Annulé",J_Statut,"<>Prévu")) | Z56: =IF($C56="",0,N(Dettes!$I$18)) | AA56: =IF($C56="",0,SUMIFS(J_Montant,J_Annee,Annee_Travail,J_Mois,12,J_Projet,$C56,J_Type,"Remboursement crédit",J_Statut,"<>Annulé",J_Statut,"<>Prévu")) | AB56: =D56+F56+H56+J56+L56+N56+P56+R56+T56+V56+X56+Z56 | AC56: =E56+G56+I56+K56+M56+O56+Q56+S56+U56+W56+Y56+AA56 | AD56: =$AB56-$AC56 | AE56: =IFERROR($AC56/$AB56,0)
B57: 10 | C57: =IF(Dettes!$C$19="","",Dettes!$C$19) | D57: =IF($C57="",0,N(Dettes!$I$19)) | E57: =IF($C57="",0,SUMIFS(J_Montant,J_Annee,Annee_Travail,J_Mois,1,J_Projet,$C57,J_Type,"Remboursement crédit",J_Statut,"<>Annulé",J_Statut,"<>Prévu")) | F57: =IF($C57="",0,N(Dettes!$I$19)) | G57: =IF($C57="",0,SUMIFS(J_Montant,J_Annee,Annee_Travail,J_Mois,2,J_Projet,$C57,J_Type,"Remboursement crédit",J_Statut,"<>Annulé",J_Statut,"<>Prévu")) | H57: =IF($C57="",0,N(Dettes!$I$19)) | I57: =IF($C57="",0,SUMIFS(J_Montant,J_Annee,Annee_Travail,J_Mois,3,J_Projet,$C57,J_Type,"Remboursement crédit",J_Statut,"<>Annulé",J_Statut,"<>Prévu")) | J57: =IF($C57="",0,N(Dettes!$I$19)) | K57: =IF($C57="",0,SUMIFS(J_Montant,J_Annee,Annee_Travail,J_Mois,4,J_Projet,$C57,J_Type,"Remboursement crédit",J_Statut,"<>Annulé",J_Statut,"<>Prévu")) | L57: =IF($C57="",0,N(Dettes!$I$19)) | M57: =IF($C57="",0,SUMIFS(J_Montant,J_Annee,Annee_Travail,J_Mois,5,J_Projet,$C57,J_Type,"Remboursement crédit",J_Statut,"<>Annulé",J_Statut,"<>Prévu")) | N57: =IF($C57="",0,N(Dettes!$I$19)) | O57: =IF($C57="",0,SUMIFS(J_Montant,J_Annee,Annee_Travail,J_Mois,6,J_Projet,$C57,J_Type,"Remboursement crédit",J_Statut,"<>Annulé",J_Statut,"<>Prévu")) | P57: =IF($C57="",0,N(Dettes!$I$19)) | Q57: =IF($C57="",0,SUMIFS(J_Montant,J_Annee,Annee_Travail,J_Mois,7,J_Projet,$C57,J_Type,"Remboursement crédit",J_Statut,"<>Annulé",J_Statut,"<>Prévu")) | R57: =IF($C57="",0,N(Dettes!$I$19)) | S57: =IF($C57="",0,SUMIFS(J_Montant,J_Annee,Annee_Travail,J_Mois,8,J_Projet,$C57,J_Type,"Remboursement crédit",J_Statut,"<>Annulé",J_Statut,"<>Prévu")) | T57: =IF($C57="",0,N(Dettes!$I$19)) | U57: =IF($C57="",0,SUMIFS(J_Montant,J_Annee,Annee_Travail,J_Mois,9,J_Projet,$C57,J_Type,"Remboursement crédit",J_Statut,"<>Annulé",J_Statut,"<>Prévu")) | V57: =IF($C57="",0,N(Dettes!$I$19)) | W57: =IF($C57="",0,SUMIFS(J_Montant,J_Annee,Annee_Travail,J_Mois,10,J_Projet,$C57,J_Type,"Remboursement crédit",J_Statut,"<>Annulé",J_Statut,"<>Prévu")) | X57: =IF($C57="",0,N(Dettes!$I$19)) | Y57: =IF($C57="",0,SUMIFS(J_Montant,J_Annee,Annee_Travail,J_Mois,11,J_Projet,$C57,J_Type,"Remboursement crédit",J_Statut,"<>Annulé",J_Statut,"<>Prévu")) | Z57: =IF($C57="",0,N(Dettes!$I$19)) | AA57: =IF($C57="",0,SUMIFS(J_Montant,J_Annee,Annee_Travail,J_Mois,12,J_Projet,$C57,J_Type,"Remboursement crédit",J_Statut,"<>Annulé",J_Statut,"<>Prévu")) | AB57: =D57+F57+H57+J57+L57+N57+P57+R57+T57+V57+X57+Z57 | AC57: =E57+G57+I57+K57+M57+O57+Q57+S57+U57+W57+Y57+AA57 | AD57: =$AB57-$AC57 | AE57: =IFERROR($AC57/$AB57,0)
B58: 11 | C58: Autres remboursements non rattachés à un crédit | D58: =0 | E58: =MAX(0,SUMIFS(J_Montant,J_Annee,Annee_Travail,J_Mois,1,J_Type,"Remboursement crédit",J_Statut,"<>Annulé",J_Statut,"<>Prévu")-SUM(E48:E57)) | F58: =0 | G58: =MAX(0,SUMIFS(J_Montant,J_Annee,Annee_Travail,J_Mois,2,J_Type,"Remboursement crédit",J_Statut,"<>Annulé",J_Statut,"<>Prévu")-SUM(G48:G57)) | H58: =0 | I58: =MAX(0,SUMIFS(J_Montant,J_Annee,Annee_Travail,J_Mois,3,J_Type,"Remboursement crédit",J_Statut,"<>Annulé",J_Statut,"<>Prévu")-SUM(I48:I57)) | J58: =0 | K58: =MAX(0,SUMIFS(J_Montant,J_Annee,Annee_Travail,J_Mois,4,J_Type,"Remboursement crédit",J_Statut,"<>Annulé",J_Statut,"<>Prévu")-SUM(K48:K57)) | L58: =0 | M58: =MAX(0,SUMIFS(J_Montant,J_Annee,Annee_Travail,J_Mois,5,J_Type,"Remboursement crédit",J_Statut,"<>Annulé",J_Statut,"<>Prévu")-SUM(M48:M57)) | N58: =0 | O58: =MAX(0,SUMIFS(J_Montant,J_Annee,Annee_Travail,J_Mois,6,J_Type,"Remboursement crédit",J_Statut,"<>Annulé",J_Statut,"<>Prévu")-SUM(O48:O57)) | P58: =0 | Q58: =MAX(0,SUMIFS(J_Montant,J_Annee,Annee_Travail,J_Mois,7,J_Type,"Remboursement crédit",J_Statut,"<>Annulé",J_Statut,"<>Prévu")-SUM(Q48:Q57)) | R58: =0 | S58: =MAX(0,SUMIFS(J_Montant,J_Annee,Annee_Travail,J_Mois,8,J_Type,"Remboursement crédit",J_Statut,"<>Annulé",J_Statut,"<>Prévu")-SUM(S48:S57)) | T58: =0 | U58: =MAX(0,SUMIFS(J_Montant,J_Annee,Annee_Travail,J_Mois,9,J_Type,"Remboursement crédit",J_Statut,"<>Annulé",J_Statut,"<>Prévu")-SUM(U48:U57)) | V58: =0 | W58: =MAX(0,SUMIFS(J_Montant,J_Annee,Annee_Travail,J_Mois,10,J_Type,"Remboursement crédit",J_Statut,"<>Annulé",J_Statut,"<>Prévu")-SUM(W48:W57)) | X58: =0 | Y58: =MAX(0,SUMIFS(J_Montant,J_Annee,Annee_Travail,J_Mois,11,J_Type,"Remboursement crédit",J_Statut,"<>Annulé",J_Statut,"<>Prévu")-SUM(Y48:Y57)) | Z58: =0 | AA58: =MAX(0,SUMIFS(J_Montant,J_Annee,Annee_Travail,J_Mois,12,J_Type,"Remboursement crédit",J_Statut,"<>Annulé",J_Statut,"<>Prévu")-SUM(AA48:AA57)) | AB58: =D58+F58+H58+J58+L58+N58+P58+R58+T58+V58+X58+Z58 | AC58: =E58+G58+I58+K58+M58+O58+Q58+S58+U58+W58+Y58+AA58 | AD58: =$AB58-$AC58 | AE58: =IFERROR($AC58/$AB58,0)
C59: TOTAL CRÉDITS & DETTES | D59: =SUM(D48:D58) | E59: =SUM(E48:E58) | F59: =SUM(F48:F58) | G59: =SUM(G48:G58) | H59: =SUM(H48:H58) | I59: =SUM(I48:I58) | J59: =SUM(J48:J58) | K59: =SUM(K48:K58) | ... AA59: =SUM(AA48:AA58) | AB59: =D59+F59+H59+J59+L59+N59+P59+R59+T59+V59+X59+Z59 | AC59: =E59+G59+I59+K59+M59+O59+Q59+S59+U59+W59+Y59+AA59 | AD59: =$AB59-$AC59 | AE59: =IFERROR($AC59/$AB59,0)
B61: D ▸ DÉPENSES COURANTES (module Général)
B62: 1 | C62: Loyer | D62: =IF($C62="",0,SUMIFS(P_M1,P_Annee,Annee_Travail,P_Cat,$C62,P_Type,"Dépense",P_Module,"Général")) | E62: =IF($C62="",0,SUMIFS(J_Montant,J_Annee,Annee_Travail,J_Mois,1,J_Module,"Général",J_Cat,$C62,J_Type,"Dépense",J_Statut,"<>Annulé",J_Statut,"<>Prévu")) | F62: =IF($C62="",0,SUMIFS(P_M2,P_Annee,Annee_Travail,P_Cat,$C62,P_Type,"Dépense",P_Module,"Général")) | G62: =IF($C62="",0,SUMIFS(J_Montant,J_Annee,Annee_Travail,J_Mois,2,J_Module,"Général",J_Cat,$C62,J_Type,"Dépense",J_Statut,"<>Annulé",J_Statut,"<>Prévu")) | H62: =IF($C62="",0,SUMIFS(P_M3,P_Annee,Annee_Travail,P_Cat,$C62,P_Type,"Dépense",P_Module,"Général")) | I62: =IF($C62="",0,SUMIFS(J_Montant,J_Annee,Annee_Travail,J_Mois,3,J_Module,"Général",J_Cat,$C62,J_Type,"Dépense",J_Statut,"<>Annulé",J_Statut,"<>Prévu")) | J62: =IF($C62="",0,SUMIFS(P_M4,P_Annee,Annee_Travail,P_Cat,$C62,P_Type,"Dépense",P_Module,"Général")) | K62: =IF($C62="",0,SUMIFS(J_Montant,J_Annee,Annee_Travail,J_Mois,4,J_Module,"Général",J_Cat,$C62,J_Type,"Dépense",J_Statut,"<>Annulé",J_Statut,"<>Prévu")) | L62: =IF($C62="",0,SUMIFS(P_M5,P_Annee,Annee_Travail,P_Cat,$C62,P_Type,"Dépense",P_Module,"Général")) | M62: =IF($C62="",0,SUMIFS(J_Montant,J_Annee,Annee_Travail,J_Mois,5,J_Module,"Général",J_Cat,$C62,J_Type,"Dépense",J_Statut,"<>Annulé",J_Statut,"<>Prévu")) | N62: =IF($C62="",0,SUMIFS(P_M6,P_Annee,Annee_Travail,P_Cat,$C62,P_Type,"Dépense",P_Module,"Général")) | O62: =IF($C62="",0,SUMIFS(J_Montant,J_Annee,Annee_Travail,J_Mois,6,J_Module,"Général",J_Cat,$C62,J_Type,"Dépense",J_Statut,"<>Annulé",J_Statut,"<>Prévu")) | P62: =IF($C62="",0,SUMIFS(P_M7,P_Annee,Annee_Travail,P_Cat,$C62,P_Type,"Dépense",P_Module,"Général")) | Q62: =IF($C62="",0,SUMIFS(J_Montant,J_Annee,Annee_Travail,J_Mois,7,J_Module,"Général",J_Cat,$C62,J_Type,"Dépense",J_Statut,"<>Annulé",J_Statut,"<>Prévu")) | R62: =IF($C62="",0,SUMIFS(P_M8,P_Annee,Annee_Travail,P_Cat,$C62,P_Type,"Dépense",P_Module,"Général")) | S62: =IF($C62="",0,SUMIFS(J_Montant,J_Annee,Annee_Travail,J_Mois,8,J_Module,"Général",J_Cat,$C62,J_Type,"Dépense",J_Statut,"<>Annulé",J_Statut,"<>Prévu")) | T62: =IF($C62="",0,SUMIFS(P_M9,P_Annee,Annee_Travail,P_Cat,$C62,P_Type,"Dépense",P_Module,"Général")) | U62: =IF($C62="",0,SUMIFS(J_Montant,J_Annee,Annee_Travail,J_Mois,9,J_Module,"Général",J_Cat,$C62,J_Type,"Dépense",J_Statut,"<>Annulé",J_Statut,"<>Prévu")) | V62: =IF($C62="",0,SUMIFS(P_M10,P_Annee,Annee_Travail,P_Cat,$C62,P_Type,"Dépense",P_Module,"Général")) | W62: =IF($C62="",0,SUMIFS(J_Montant,J_Annee,Annee_Travail,J_Mois,10,J_Module,"Général",J_Cat,$C62,J_Type,"Dépense",J_Statut,"<>Annulé",J_Statut,"<>Prévu")) | X62: =IF($C62="",0,SUMIFS(P_M11,P_Annee,Annee_Travail,P_Cat,$C62,P_Type,"Dépense",P_Module,"Général")) | Y62: =IF($C62="",0,SUMIFS(J_Montant,J_Annee,Annee_Travail,J_Mois,11,J_Module,"Général",J_Cat,$C62,J_Type,"Dépense",J_Statut,"<>Annulé",J_Statut,"<>Prévu")) | Z62: =IF($C62="",0,SUMIFS(P_M12,P_Annee,Annee_Travail,P_Cat,$C62,P_Type,"Dépense",P_Module,"Général")) | AA62: =IF($C62="",0,SUMIFS(J_Montant,J_Annee,Annee_Travail,J_Mois,12,J_Module,"Général",J_Cat,$C62,J_Type,"Dépense",J_Statut,"<>Annulé",J_Statut,"<>Prévu")) | AB62: =D62+F62+H62+J62+L62+N62+P62+R62+T62+V62+X62+Z62 | AC62: =E62+G62+I62+K62+M62+O62+Q62+S62+U62+W62+Y62+AA62 | AD62: =$AB62-$AC62 | AE62: =IFERROR($AC62/$AB62,0)
B63: 2 | C63: Électricité | D63: =IF($C63="",0,SUMIFS(P_M1,P_Annee,Annee_Travail,P_Cat,$C63,P_Type,"Dépense",P_Module,"Général")) | E63: =IF($C63="",0,SUMIFS(J_Montant,J_Annee,Annee_Travail,J_Mois,1,J_Module,"Général",J_Cat,$C63,J_Type,"Dépense",J_Statut,"<>Annulé",J_Statut,"<>Prévu")) | F63: =IF($C63="",0,SUMIFS(P_M2,P_Annee,Annee_Travail,P_Cat,$C63,P_Type,"Dépense",P_Module,"Général")) | G63: =IF($C63="",0,SUMIFS(J_Montant,J_Annee,Annee_Travail,J_Mois,2,J_Module,"Général",J_Cat,$C63,J_Type,"Dépense",J_Statut,"<>Annulé",J_Statut,"<>Prévu")) | H63: =IF($C63="",0,SUMIFS(P_M3,P_Annee,Annee_Travail,P_Cat,$C63,P_Type,"Dépense",P_Module,"Général")) | I63: =IF($C63="",0,SUMIFS(J_Montant,J_Annee,Annee_Travail,J_Mois,3,J_Module,"Général",J_Cat,$C63,J_Type,"Dépense",J_Statut,"<>Annulé",J_Statut,"<>Prévu")) | J63: =IF($C63="",0,SUMIFS(P_M4,P_Annee,Annee_Travail,P_Cat,$C63,P_Type,"Dépense",P_Module,"Général")) | K63: =IF($C63="",0,SUMIFS(J_Montant,J_Annee,Annee_Travail,J_Mois,4,J_Module,"Général",J_Cat,$C63,J_Type,"Dépense",J_Statut,"<>Annulé",J_Statut,"<>Prévu")) | L63: =IF($C63="",0,SUMIFS(P_M5,P_Annee,Annee_Travail,P_Cat,$C63,P_Type,"Dépense",P_Module,"Général")) | M63: =IF($C63="",0,SUMIFS(J_Montant,J_Annee,Annee_Travail,J_Mois,5,J_Module,"Général",J_Cat,$C63,J_Type,"Dépense",J_Statut,"<>Annulé",J_Statut,"<>Prévu")) | N63: =IF($C63="",0,SUMIFS(P_M6,P_Annee,Annee_Travail,P_Cat,$C63,P_Type,"Dépense",P_Module,"Général")) | O63: =IF($C63="",0,SUMIFS(J_Montant,J_Annee,Annee_Travail,J_Mois,6,J_Module,"Général",J_Cat,$C63,J_Type,"Dépense",J_Statut,"<>Annulé",J_Statut,"<>Prévu")) | P63: =IF($C63="",0,SUMIFS(P_M7,P_Annee,Annee_Travail,P_Cat,$C63,P_Type,"Dépense",P_Module,"Général")) | Q63: =IF($C63="",0,SUMIFS(J_Montant,J_Annee,Annee_Travail,J_Mois,7,J_Module,"Général",J_Cat,$C63,J_Type,"Dépense",J_Statut,"<>Annulé",J_Statut,"<>Prévu")) | R63: =IF($C63="",0,SUMIFS(P_M8,P_Annee,Annee_Travail,P_Cat,$C63,P_Type,"Dépense",P_Module,"Général")) | S63: =IF($C63="",0,SUMIFS(J_Montant,J_Annee,Annee_Travail,J_Mois,8,J_Module,"Général",J_Cat,$C63,J_Type,"Dépense",J_Statut,"<>Annulé",J_Statut,"<>Prévu")) | T63: =IF($C63="",0,SUMIFS(P_M9,P_Annee,Annee_Travail,P_Cat,$C63,P_Type,"Dépense",P_Module,"Général")) | U63: =IF($C63="",0,SUMIFS(J_Montant,J_Annee,Annee_Travail,J_Mois,9,J_Module,"Général",J_Cat,$C63,J_Type,"Dépense",J_Statut,"<>Annulé",J_Statut,"<>Prévu")) | V63: =IF($C63="",0,SUMIFS(P_M10,P_Annee,Annee_Travail,P_Cat,$C63,P_Type,"Dépense",P_Module,"Général")) | W63: =IF($C63="",0,SUMIFS(J_Montant,J_Annee,Annee_Travail,J_Mois,10,J_Module,"Général",J_Cat,$C63,J_Type,"Dépense",J_Statut,"<>Annulé",J_Statut,"<>Prévu")) | X63: =IF($C63="",0,SUMIFS(P_M11,P_Annee,Annee_Travail,P_Cat,$C63,P_Type,"Dépense",P_Module,"Général")) | Y63: =IF($C63="",0,SUMIFS(J_Montant,J_Annee,Annee_Travail,J_Mois,11,J_Module,"Général",J_Cat,$C63,J_Type,"Dépense",J_Statut,"<>Annulé",J_Statut,"<>Prévu")) | Z63: =IF($C63="",0,SUMIFS(P_M12,P_Annee,Annee_Travail,P_Cat,$C63,P_Type,"Dépense",P_Module,"Général")) | AA63: =IF($C63="",0,SUMIFS(J_Montant,J_Annee,Annee_Travail,J_Mois,12,J_Module,"Général",J_Cat,$C63,J_Type,"Dépense",J_Statut,"<>Annulé",J_Statut,"<>Prévu")) | AB63: =D63+F63+H63+J63+L63+N63+P63+R63+T63+V63+X63+Z63 | AC63: =E63+G63+I63+K63+M63+O63+Q63+S63+U63+W63+Y63+AA63 | AD63: =$AB63-$AC63 | AE63: =IFERROR($AC63/$AB63,0)
B64: 3 | C64: Eau | D64: =IF($C64="",0,SUMIFS(P_M1,P_Annee,Annee_Travail,P_Cat,$C64,P_Type,"Dépense",P_Module,"Général")) | E64: =IF($C64="",0,SUMIFS(J_Montant,J_Annee,Annee_Travail,J_Mois,1,J_Module,"Général",J_Cat,$C64,J_Type,"Dépense",J_Statut,"<>Annulé",J_Statut,"<>Prévu")) | F64: =IF($C64="",0,SUMIFS(P_M2,P_Annee,Annee_Travail,P_Cat,$C64,P_Type,"Dépense",P_Module,"Général")) | G64: =IF($C64="",0,SUMIFS(J_Montant,J_Annee,Annee_Travail,J_Mois,2,J_Module,"Général",J_Cat,$C64,J_Type,"Dépense",J_Statut,"<>Annulé",J_Statut,"<>Prévu")) | H64: =IF($C64="",0,SUMIFS(P_M3,P_Annee,Annee_Travail,P_Cat,$C64,P_Type,"Dépense",P_Module,"Général")) | I64: =IF($C64="",0,SUMIFS(J_Montant,J_Annee,Annee_Travail,J_Mois,3,J_Module,"Général",J_Cat,$C64,J_Type,"Dépense",J_Statut,"<>Annulé",J_Statut,"<>Prévu")) | J64: =IF($C64="",0,SUMIFS(P_M4,P_Annee,Annee_Travail,P_Cat,$C64,P_Type,"Dépense",P_Module,"Général")) | K64: =IF($C64="",0,SUMIFS(J_Montant,J_Annee,Annee_Travail,J_Mois,4,J_Module,"Général",J_Cat,$C64,J_Type,"Dépense",J_Statut,"<>Annulé",J_Statut,"<>Prévu")) | L64: =IF($C64="",0,SUMIFS(P_M5,P_Annee,Annee_Travail,P_Cat,$C64,P_Type,"Dépense",P_Module,"Général")) | M64: =IF($C64="",0,SUMIFS(J_Montant,J_Annee,Annee_Travail,J_Mois,5,J_Module,"Général",J_Cat,$C64,J_Type,"Dépense",J_Statut,"<>Annulé",J_Statut,"<>Prévu")) | N64: =IF($C64="",0,SUMIFS(P_M6,P_Annee,Annee_Travail,P_Cat,$C64,P_Type,"Dépense",P_Module,"Général")) | O64: =IF($C64="",0,SUMIFS(J_Montant,J_Annee,Annee_Travail,J_Mois,6,J_Module,"Général",J_Cat,$C64,J_Type,"Dépense",J_Statut,"<>Annulé",J_Statut,"<>Prévu")) | P64: =IF($C64="",0,SUMIFS(P_M7,P_Annee,Annee_Travail,P_Cat,$C64,P_Type,"Dépense",P_Module,"Général")) | Q64: =IF($C64="",0,SUMIFS(J_Montant,J_Annee,Annee_Travail,J_Mois,7,J_Module,"Général",J_Cat,$C64,J_Type,"Dépense",J_Statut,"<>Annulé",J_Statut,"<>Prévu")) | R64: =IF($C64="",0,SUMIFS(P_M8,P_Annee,Annee_Travail,P_Cat,$C64,P_Type,"Dépense",P_Module,"Général")) | S64: =IF($C64="",0,SUMIFS(J_Montant,J_Annee,Annee_Travail,J_Mois,8,J_Module,"Général",J_Cat,$C64,J_Type,"Dépense",J_Statut,"<>Annulé",J_Statut,"<>Prévu")) | T64: =IF($C64="",0,SUMIFS(P_M9,P_Annee,Annee_Travail,P_Cat,$C64,P_Type,"Dépense",P_Module,"Général")) | U64: =IF($C64="",0,SUMIFS(J_Montant,J_Annee,Annee_Travail,J_Mois,9,J_Module,"Général",J_Cat,$C64,J_Type,"Dépense",J_Statut,"<>Annulé",J_Statut,"<>Prévu")) | V64: =IF($C64="",0,SUMIFS(P_M10,P_Annee,Annee_Travail,P_Cat,$C64,P_Type,"Dépense",P_Module,"Général")) | W64: =IF($C64="",0,SUMIFS(J_Montant,J_Annee,Annee_Travail,J_Mois,10,J_Module,"Général",J_Cat,$C64,J_Type,"Dépense",J_Statut,"<>Annulé",J_Statut,"<>Prévu")) | X64: =IF($C64="",0,SUMIFS(P_M11,P_Annee,Annee_Travail,P_Cat,$C64,P_Type,"Dépense",P_Module,"Général")) | Y64: =IF($C64="",0,SUMIFS(J_Montant,J_Annee,Annee_Travail,J_Mois,11,J_Module,"Général",J_Cat,$C64,J_Type,"Dépense",J_Statut,"<>Annulé",J_Statut,"<>Prévu")) | Z64: =IF($C64="",0,SUMIFS(P_M12,P_Annee,Annee_Travail,P_Cat,$C64,P_Type,"Dépense",P_Module,"Général")) | AA64: =IF($C64="",0,SUMIFS(J_Montant,J_Annee,Annee_Travail,J_Mois,12,J_Module,"Général",J_Cat,$C64,J_Type,"Dépense",J_Statut,"<>Annulé",J_Statut,"<>Prévu")) | AB64: =D64+F64+H64+J64+L64+N64+P64+R64+T64+V64+X64+Z64 | AC64: =E64+G64+I64+K64+M64+O64+Q64+S64+U64+W64+Y64+AA64 | AD64: =$AB64-$AC64 | AE64: =IFERROR($AC64/$AB64,0)
B65: 4 | C65: Gaz / Bouteille | D65: =IF($C65="",0,SUMIFS(P_M1,P_Annee,Annee_Travail,P_Cat,$C65,P_Type,"Dépense",P_Module,"Général")) | E65: =IF($C65="",0,SUMIFS(J_Montant,J_Annee,Annee_Travail,J_Mois,1,J_Module,"Général",J_Cat,$C65,J_Type,"Dépense",J_Statut,"<>Annulé",J_Statut,"<>Prévu")) | F65: =IF($C65="",0,SUMIFS(P_M2,P_Annee,Annee_Travail,P_Cat,$C65,P_Type,"Dépense",P_Module,"Général")) | G65: =IF($C65="",0,SUMIFS(J_Montant,J_Annee,Annee_Travail,J_Mois,2,J_Module,"Général",J_Cat,$C65,J_Type,"Dépense",J_Statut,"<>Annulé",J_Statut,"<>Prévu")) | H65: =IF($C65="",0,SUMIFS(P_M3,P_Annee,Annee_Travail,P_Cat,$C65,P_Type,"Dépense",P_Module,"Général")) | I65: =IF($C65="",0,SUMIFS(J_Montant,J_Annee,Annee_Travail,J_Mois,3,J_Module,"Général",J_Cat,$C65,J_Type,"Dépense",J_Statut,"<>Annulé",J_Statut,"<>Prévu")) | J65: =IF($C65="",0,SUMIFS(P_M4,P_Annee,Annee_Travail,P_Cat,$C65,P_Type,"Dépense",P_Module,"Général")) | K65: =IF($C65="",0,SUMIFS(J_Montant,J_Annee,Annee_Travail,J_Mois,4,J_Module,"Général",J_Cat,$C65,J_Type,"Dépense",J_Statut,"<>Annulé",J_Statut,"<>Prévu")) | L65: =IF($C65="",0,SUMIFS(P_M5,P_Annee,Annee_Travail,P_Cat,$C65,P_Type,"Dépense",P_Module,"Général")) | M65: =IF($C65="",0,SUMIFS(J_Montant,J_Annee,Annee_Travail,J_Mois,5,J_Module,"Général",J_Cat,$C65,J_Type,"Dépense",J_Statut,"<>Annulé",J_Statut,"<>Prévu")) | N65: =IF($C65="",0,SUMIFS(P_M6,P_Annee,Annee_Travail,P_Cat,$C65,P_Type,"Dépense",P_Module,"Général")) | O65: =IF($C65="",0,SUMIFS(J_Montant,J_Annee,Annee_Travail,J_Mois,6,J_Module,"Général",J_Cat,$C65,J_Type,"Dépense",J_Statut,"<>Annulé",J_Statut,"<>Prévu")) | P65: =IF($C65="",0,SUMIFS(P_M7,P_Annee,Annee_Travail,P_Cat,$C65,P_Type,"Dépense",P_Module,"Général")) | Q65: =IF($C65="",0,SUMIFS(J_Montant,J_Annee,Annee_Travail,J_Mois,7,J_Module,"Général",J_Cat,$C65,J_Type,"Dépense",J_Statut,"<>Annulé",J_Statut,"<>Prévu")) | R65: =IF($C65="",0,SUMIFS(P_M8,P_Annee,Annee_Travail,P_Cat,$C65,P_Type,"Dépense",P_Module,"Général")) | S65: =IF($C65="",0,SUMIFS(J_Montant,J_Annee,Annee_Travail,J_Mois,8,J_Module,"Général",J_Cat,$C65,J_Type,"Dépense",J_Statut,"<>Annulé",J_Statut,"<>Prévu")) | T65: =IF($C65="",0,SUMIFS(P_M9,P_Annee,Annee_Travail,P_Cat,$C65,P_Type,"Dépense",P_Module,"Général")) | U65: =IF($C65="",0,SUMIFS(J_Montant,J_Annee,Annee_Travail,J_Mois,9,J_Module,"Général",J_Cat,$C65,J_Type,"Dépense",J_Statut,"<>Annulé",J_Statut,"<>Prévu")) | V65: =IF($C65="",0,SUMIFS(P_M10,P_Annee,Annee_Travail,P_Cat,$C65,P_Type,"Dépense",P_Module,"Général")) | W65: =IF($C65="",0,SUMIFS(J_Montant,J_Annee,Annee_Travail,J_Mois,10,J_Module,"Général",J_Cat,$C65,J_Type,"Dépense",J_Statut,"<>Annulé",J_Statut,"<>Prévu")) | X65: =IF($C65="",0,SUMIFS(P_M11,P_Annee,Annee_Travail,P_Cat,$C65,P_Type,"Dépense",P_Module,"Général")) | Y65: =IF($C65="",0,SUMIFS(J_Montant,J_Annee,Annee_Travail,J_Mois,11,J_Module,"Général",J_Cat,$C65,J_Type,"Dépense",J_Statut,"<>Annulé",J_Statut,"<>Prévu")) | Z65: =IF($C65="",0,SUMIFS(P_M12,P_Annee,Annee_Travail,P_Cat,$C65,P_Type,"Dépense",P_Module,"Général")) | AA65: =IF($C65="",0,SUMIFS(J_Montant,J_Annee,Annee_Travail,J_Mois,12,J_Module,"Général",J_Cat,$C65,J_Type,"Dépense",J_Statut,"<>Annulé",J_Statut,"<>Prévu")) | AB65: =D65+F65+H65+J65+L65+N65+P65+R65+T65+V65+X65+Z65 | AC65: =E65+G65+I65+K65+M65+O65+Q65+S65+U65+W65+Y65+AA65 | AD65: =$AB65-$AC65 | AE65: =IFERROR($AC65/$AB65,0)
B66: 5 | C66: Internet / Box | D66: =IF($C66="",0,SUMIFS(P_M1,P_Annee,Annee_Travail,P_Cat,$C66,P_Type,"Dépense",P_Module,"Général")) | E66: =IF($C66="",0,SUMIFS(J_Montant,J_Annee,Annee_Travail,J_Mois,1,J_Module,"Général",J_Cat,$C66,J_Type,"Dépense",J_Statut,"<>Annulé",J_Statut,"<>Prévu")) | F66: =IF($C66="",0,SUMIFS(P_M2,P_Annee,Annee_Travail,P_Cat,$C66,P_Type,"Dépense",P_Module,"Général")) | G66: =IF($C66="",0,SUMIFS(J_Montant,J_Annee,Annee_Travail,J_Mois,2,J_Module,"Général",J_Cat,$C66,J_Type,"Dépense",J_Statut,"<>Annulé",J_Statut,"<>Prévu")) | H66: =IF($C66="",0,SUMIFS(P_M3,P_Annee,Annee_Travail,P_Cat,$C66,P_Type,"Dépense",P_Module,"Général")) | I66: =IF($C66="",0,SUMIFS(J_Montant,J_Annee,Annee_Travail,J_Mois,3,J_Module,"Général",J_Cat,$C66,J_Type,"Dépense",J_Statut,"<>Annulé",J_Statut,"<>Prévu")) | J66: =IF($C66="",0,SUMIFS(P_M4,P_Annee,Annee_Travail,P_Cat,$C66,P_Type,"Dépense",P_Module,"Général")) | K66: =IF($C66="",0,SUMIFS(J_Montant,J_Annee,Annee_Travail,J_Mois,4,J_Module,"Général",J_Cat,$C66,J_Type,"Dépense",J_Statut,"<>Annulé",J_Statut,"<>Prévu")) | L66: =IF($C66="",0,SUMIFS(P_M5,P_Annee,Annee_Travail,P_Cat,$C66,P_Type,"Dépense",P_Module,"Général")) | M66: =IF($C66="",0,SUMIFS(J_Montant,J_Annee,Annee_Travail,J_Mois,5,J_Module,"Général",J_Cat,$C66,J_Type,"Dépense",J_Statut,"<>Annulé",J_Statut,"<>Prévu")) | N66: =IF($C66="",0,SUMIFS(P_M6,P_Annee,Annee_Travail,P_Cat,$C66,P_Type,"Dépense",P_Module,"Général")) | O66: =IF($C66="",0,SUMIFS(J_Montant,J_Annee,Annee_Travail,J_Mois,6,J_Module,"Général",J_Cat,$C66,J_Type,"Dépense",J_Statut,"<>Annulé",J_Statut,"<>Prévu")) | P66: =IF($C66="",0,SUMIFS(P_M7,P_Annee,Annee_Travail,P_Cat,$C66,P_Type,"Dépense",P_Module,"Général")) | Q66: =IF($C66="",0,SUMIFS(J_Montant,J_Annee,Annee_Travail,J_Mois,7,J_Module,"Général",J_Cat,$C66,J_Type,"Dépense",J_Statut,"<>Annulé",J_Statut,"<>Prévu")) | R66: =IF($C66="",0,SUMIFS(P_M8,P_Annee,Annee_Travail,P_Cat,$C66,P_Type,"Dépense",P_Module,"Général")) | S66: =IF($C66="",0,SUMIFS(J_Montant,J_Annee,Annee_Travail,J_Mois,8,J_Module,"Général",J_Cat,$C66,J_Type,"Dépense",J_Statut,"<>Annulé",J_Statut,"<>Prévu")) | T66: =IF($C66="",0,SUMIFS(P_M9,P_Annee,Annee_Travail,P_Cat,$C66,P_Type,"Dépense",P_Module,"Général")) | U66: =IF($C66="",0,SUMIFS(J_Montant,J_Annee,Annee_Travail,J_Mois,9,J_Module,"Général",J_Cat,$C66,J_Type,"Dépense",J_Statut,"<>Annulé",J_Statut,"<>Prévu")) | V66: =IF($C66="",0,SUMIFS(P_M10,P_Annee,Annee_Travail,P_Cat,$C66,P_Type,"Dépense",P_Module,"Général")) | W66: =IF($C66="",0,SUMIFS(J_Montant,J_Annee,Annee_Travail,J_Mois,10,J_Module,"Général",J_Cat,$C66,J_Type,"Dépense",J_Statut,"<>Annulé",J_Statut,"<>Prévu")) | X66: =IF($C66="",0,SUMIFS(P_M11,P_Annee,Annee_Travail,P_Cat,$C66,P_Type,"Dépense",P_Module,"Général")) | Y66: =IF($C66="",0,SUMIFS(J_Montant,J_Annee,Annee_Travail,J_Mois,11,J_Module,"Général",J_Cat,$C66,J_Type,"Dépense",J_Statut,"<>Annulé",J_Statut,"<>Prévu")) | Z66: =IF($C66="",0,SUMIFS(P_M12,P_Annee,Annee_Travail,P_Cat,$C66,P_Type,"Dépense",P_Module,"Général")) | AA66: =IF($C66="",0,SUMIFS(J_Montant,J_Annee,Annee_Travail,J_Mois,12,J_Module,"Général",J_Cat,$C66,J_Type,"Dépense",J_Statut,"<>Annulé",J_Statut,"<>Prévu")) | AB66: =D66+F66+H66+J66+L66+N66+P66+R66+T66+V66+X66+Z66 | AC66: =E66+G66+I66+K66+M66+O66+Q66+S66+U66+W66+Y66+AA66 | AD66: =$AB66-$AC66 | AE66: =IFERROR($AC66/$AB66,0)
B67: 6 | C67: Téléphone | D67: =IF($C67="",0,SUMIFS(P_M1,P_Annee,Annee_Travail,P_Cat,$C67,P_Type,"Dépense",P_Module,"Général")) | E67: =IF($C67="",0,SUMIFS(J_Montant,J_Annee,Annee_Travail,J_Mois,1,J_Module,"Général",J_Cat,$C67,J_Type,"Dépense",J_Statut,"<>Annulé",J_Statut,"<>Prévu")) | F67: =IF($C67="",0,SUMIFS(P_M2,P_Annee,Annee_Travail,P_Cat,$C67,P_Type,"Dépense",P_Module,"Général")) | G67: =IF($C67="",0,SUMIFS(J_Montant,J_Annee,Annee_Travail,J_Mois,2,J_Module,"Général",J_Cat,$C67,J_Type,"Dépense",J_Statut,"<>Annulé",J_Statut,"<>Prévu")) | H67: =IF($C67="",0,SUMIFS(P_M3,P_Annee,Annee_Travail,P_Cat,$C67,P_Type,"Dépense",P_Module,"Général")) | I67: =IF($C67="",0,SUMIFS(J_Montant,J_Annee,Annee_Travail,J_Mois,3,J_Module,"Général",J_Cat,$C67,J_Type,"Dépense",J_Statut,"<>Annulé",J_Statut,"<>Prévu")) | J67: =IF($C67="",0,SUMIFS(P_M4,P_Annee,Annee_Travail,P_Cat,$C67,P_Type,"Dépense",P_Module,"Général")) | K67: =IF($C67="",0,SUMIFS(J_Montant,J_Annee,Annee_Travail,J_Mois,4,J_Module,"Général",J_Cat,$C67,J_Type,"Dépense",J_Statut,"<>Annulé",J_Statut,"<>Prévu")) | L67: =IF($C67="",0,SUMIFS(P_M5,P_Annee,Annee_Travail,P_Cat,$C67,P_Type,"Dépense",P_Module,"Général")) | M67: =IF($C67="",0,SUMIFS(J_Montant,J_Annee,Annee_Travail,J_Mois,5,J_Module,"Général",J_Cat,$C67,J_Type,"Dépense",J_Statut,"<>Annulé",J_Statut,"<>Prévu")) | N67: =IF($C67="",0,SUMIFS(P_M6,P_Annee,Annee_Travail,P_Cat,$C67,P_Type,"Dépense",P_Module,"Général")) | O67: =IF($C67="",0,SUMIFS(J_Montant,J_Annee,Annee_Travail,J_Mois,6,J_Module,"Général",J_Cat,$C67,J_Type,"Dépense",J_Statut,"<>Annulé",J_Statut,"<>Prévu")) | P67: =IF($C67="",0,SUMIFS(P_M7,P_Annee,Annee_Travail,P_Cat,$C67,P_Type,"Dépense",P_Module,"Général")) | Q67: =IF($C67="",0,SUMIFS(J_Montant,J_Annee,Annee_Travail,J_Mois,7,J_Module,"Général",J_Cat,$C67,J_Type,"Dépense",J_Statut,"<>Annulé",J_Statut,"<>Prévu")) | R67: =IF($C67="",0,SUMIFS(P_M8,P_Annee,Annee_Travail,P_Cat,$C67,P_Type,"Dépense",P_Module,"Général")) | S67: =IF($C67="",0,SUMIFS(J_Montant,J_Annee,Annee_Travail,J_Mois,8,J_Module,"Général",J_Cat,$C67,J_Type,"Dépense",J_Statut,"<>Annulé",J_Statut,"<>Prévu")) | T67: =IF($C67="",0,SUMIFS(P_M9,P_Annee,Annee_Travail,P_Cat,$C67,P_Type,"Dépense",P_Module,"Général")) | U67: =IF($C67="",0,SUMIFS(J_Montant,J_Annee,Annee_Travail,J_Mois,9,J_Module,"Général",J_Cat,$C67,J_Type,"Dépense",J_Statut,"<>Annulé",J_Statut,"<>Prévu")) | V67: =IF($C67="",0,SUMIFS(P_M10,P_Annee,Annee_Travail,P_Cat,$C67,P_Type,"Dépense",P_Module,"Général")) | W67: =IF($C67="",0,SUMIFS(J_Montant,J_Annee,Annee_Travail,J_Mois,10,J_Module,"Général",J_Cat,$C67,J_Type,"Dépense",J_Statut,"<>Annulé",J_Statut,"<>Prévu")) | X67: =IF($C67="",0,SUMIFS(P_M11,P_Annee,Annee_Travail,P_Cat,$C67,P_Type,"Dépense",P_Module,"Général")) | Y67: =IF($C67="",0,SUMIFS(J_Montant,J_Annee,Annee_Travail,J_Mois,11,J_Module,"Général",J_Cat,$C67,J_Type,"Dépense",J_Statut,"<>Annulé",J_Statut,"<>Prévu")) | Z67: =IF($C67="",0,SUMIFS(P_M12,P_Annee,Annee_Travail,P_Cat,$C67,P_Type,"Dépense",P_Module,"Général")) | AA67: =IF($C67="",0,SUMIFS(J_Montant,J_Annee,Annee_Travail,J_Mois,12,J_Module,"Général",J_Cat,$C67,J_Type,"Dépense",J_Statut,"<>Annulé",J_Statut,"<>Prévu")) | AB67: =D67+F67+H67+J67+L67+N67+P67+R67+T67+V67+X67+Z67 | AC67: =E67+G67+I67+K67+M67+O67+Q67+S67+U67+W67+Y67+AA67 | AD67: =$AB67-$AC67 | AE67: =IFERROR($AC67/$AB67,0)
B68: 7 | C68: Charges de copropriété | D68: =IF($C68="",0,SUMIFS(P_M1,P_Annee,Annee_Travail,P_Cat,$C68,P_Type,"Dépense",P_Module,"Général")) | E68: =IF($C68="",0,SUMIFS(J_Montant,J_Annee,Annee_Travail,J_Mois,1,J_Module,"Général",J_Cat,$C68,J_Type,"Dépense",J_Statut,"<>Annulé",J_Statut,"<>Prévu")) | F68: =IF($C68="",0,SUMIFS(P_M2,P_Annee,Annee_Travail,P_Cat,$C68,P_Type,"Dépense",P_Module,"Général")) | G68: =IF($C68="",0,SUMIFS(J_Montant,J_Annee,Annee_Travail,J_Mois,2,J_Module,"Général",J_Cat,$C68,J_Type,"Dépense",J_Statut,"<>Annulé",J_Statut,"<>Prévu")) | H68: =IF($C68="",0,SUMIFS(P_M3,P_Annee,Annee_Travail,P_Cat,$C68,P_Type,"Dépense",P_Module,"Général")) | I68: =IF($C68="",0,SUMIFS(J_Montant,J_Annee,Annee_Travail,J_Mois,3,J_Module,"Général",J_Cat,$C68,J_Type,"Dépense",J_Statut,"<>Annulé",J_Statut,"<>Prévu")) | J68: =IF($C68="",0,SUMIFS(P_M4,P_Annee,Annee_Travail,P_Cat,$C68,P_Type,"Dépense",P_Module,"Général")) | K68: =IF($C68="",0,SUMIFS(J_Montant,J_Annee,Annee_Travail,J_Mois,4,J_Module,"Général",J_Cat,$C68,J_Type,"Dépense",J_Statut,"<>Annulé",J_Statut,"<>Prévu")) | L68: =IF($C68="",0,SUMIFS(P_M5,P_Annee,Annee_Travail,P_Cat,$C68,P_Type,"Dépense",P_Module,"Général")) | M68: =IF($C68="",0,SUMIFS(J_Montant,J_Annee,Annee_Travail,J_Mois,5,J_Module,"Général",J_Cat,$C68,J_Type,"Dépense",J_Statut,"<>Annulé",J_Statut,"<>Prévu")) | N68: =IF($C68="",0,SUMIFS(P_M6,P_Annee,Annee_Travail,P_Cat,$C68,P_Type,"Dépense",P_Module,"Général")) | O68: =IF($C68="",0,SUMIFS(J_Montant,J_Annee,Annee_Travail,J_Mois,6,J_Module,"Général",J_Cat,$C68,J_Type,"Dépense",J_Statut,"<>Annulé",J_Statut,"<>Prévu")) | P68: =IF($C68="",0,SUMIFS(P_M7,P_Annee,Annee_Travail,P_Cat,$C68,P_Type,"Dépense",P_Module,"Général")) | Q68: =IF($C68="",0,SUMIFS(J_Montant,J_Annee,Annee_Travail,J_Mois,7,J_Module,"Général",J_Cat,$C68,J_Type,"Dépense",J_Statut,"<>Annulé",J_Statut,"<>Prévu")) | R68: =IF($C68="",0,SUMIFS(P_M8,P_Annee,Annee_Travail,P_Cat,$C68,P_Type,"Dépense",P_Module,"Général")) | S68: =IF($C68="",0,SUMIFS(J_Montant,J_Annee,Annee_Travail,J_Mois,8,J_Module,"Général",J_Cat,$C68,J_Type,"Dépense",J_Statut,"<>Annulé",J_Statut,"<>Prévu")) | T68: =IF($C68="",0,SUMIFS(P_M9,P_Annee,Annee_Travail,P_Cat,$C68,P_Type,"Dépense",P_Module,"Général")) | U68: =IF($C68="",0,SUMIFS(J_Montant,J_Annee,Annee_Travail,J_Mois,9,J_Module,"Général",J_Cat,$C68,J_Type,"Dépense",J_Statut,"<>Annulé",J_Statut,"<>Prévu")) | V68: =IF($C68="",0,SUMIFS(P_M10,P_Annee,Annee_Travail,P_Cat,$C68,P_Type,"Dépense",P_Module,"Général")) | W68: =IF($C68="",0,SUMIFS(J_Montant,J_Annee,Annee_Travail,J_Mois,10,J_Module,"Général",J_Cat,$C68,J_Type,"Dépense",J_Statut,"<>Annulé",J_Statut,"<>Prévu")) | X68: =IF($C68="",0,SUMIFS(P_M11,P_Annee,Annee_Travail,P_Cat,$C68,P_Type,"Dépense",P_Module,"Général")) | Y68: =IF($C68="",0,SUMIFS(J_Montant,J_Annee,Annee_Travail,J_Mois,11,J_Module,"Général",J_Cat,$C68,J_Type,"Dépense",J_Statut,"<>Annulé",J_Statut,"<>Prévu")) | Z68: =IF($C68="",0,SUMIFS(P_M12,P_Annee,Annee_Travail,P_Cat,$C68,P_Type,"Dépense",P_Module,"Général")) | AA68: =IF($C68="",0,SUMIFS(J_Montant,J_Annee,Annee_Travail,J_Mois,12,J_Module,"Général",J_Cat,$C68,J_Type,"Dépense",J_Statut,"<>Annulé",J_Statut,"<>Prévu")) | AB68: =D68+F68+H68+J68+L68+N68+P68+R68+T68+V68+X68+Z68 | AC68: =E68+G68+I68+K68+M68+O68+Q68+S68+U68+W68+Y68+AA68 | AD68: =$AB68-$AC68 | AE68: =IFERROR($AC68/$AB68,0)
B69: 8 | C69: Entretien & réparations logement | D69: =IF($C69="",0,SUMIFS(P_M1,P_Annee,Annee_Travail,P_Cat,$C69,P_Type,"Dépense",P_Module,"Général")) | E69: =IF($C69="",0,SUMIFS(J_Montant,J_Annee,Annee_Travail,J_Mois,1,J_Module,"Général",J_Cat,$C69,J_Type,"Dépense",J_Statut,"<>Annulé",J_Statut,"<>Prévu")) | F69: =IF($C69="",0,SUMIFS(P_M2,P_Annee,Annee_Travail,P_Cat,$C69,P_Type,"Dépense",P_Module,"Général")) | G69: =IF($C69="",0,SUMIFS(J_Montant,J_Annee,Annee_Travail,J_Mois,2,J_Module,"Général",J_Cat,$C69,J_Type,"Dépense",J_Statut,"<>Annulé",J_Statut,"<>Prévu")) | H69: =IF($C69="",0,SUMIFS(P_M3,P_Annee,Annee_Travail,P_Cat,$C69,P_Type,"Dépense",P_Module,"Général")) | I69: =IF($C69="",0,SUMIFS(J_Montant,J_Annee,Annee_Travail,J_Mois,3,J_Module,"Général",J_Cat,$C69,J_Type,"Dépense",J_Statut,"<>Annulé",J_Statut,"<>Prévu")) | J69: =IF($C69="",0,SUMIFS(P_M4,P_Annee,Annee_Travail,P_Cat,$C69,P_Type,"Dépense",P_Module,"Général")) | K69: =IF($C69="",0,SUMIFS(J_Montant,J_Annee,Annee_Travail,J_Mois,4,J_Module,"Général",J_Cat,$C69,J_Type,"Dépense",J_Statut,"<>Annulé",J_Statut,"<>Prévu")) | L69: =IF($C69="",0,SUMIFS(P_M5,P_Annee,Annee_Travail,P_Cat,$C69,P_Type,"Dépense",P_Module,"Général")) | M69: =IF($C69="",0,SUMIFS(J_Montant,J_Annee,Annee_Travail,J_Mois,5,J_Module,"Général",J_Cat,$C69,J_Type,"Dépense",J_Statut,"<>Annulé",J_Statut,"<>Prévu")) | N69: =IF($C69="",0,SUMIFS(P_M6,P_Annee,Annee_Travail,P_Cat,$C69,P_Type,"Dépense",P_Module,"Général")) | O69: =IF($C69="",0,SUMIFS(J_Montant,J_Annee,Annee_Travail,J_Mois,6,J_Module,"Général",J_Cat,$C69,J_Type,"Dépense",J_Statut,"<>Annulé",J_Statut,"<>Prévu")) | P69: =IF($C69="",0,SUMIFS(P_M7,P_Annee,Annee_Travail,P_Cat,$C69,P_Type,"Dépense",P_Module,"Général")) | Q69: =IF($C69="",0,SUMIFS(J_Montant,J_Annee,Annee_Travail,J_Mois,7,J_Module,"Général",J_Cat,$C69,J_Type,"Dépense",J_Statut,"<>Annulé",J_Statut,"<>Prévu")) | R69: =IF($C69="",0,SUMIFS(P_M8,P_Annee,Annee_Travail,P_Cat,$C69,P_Type,"Dépense",P_Module,"Général")) | S69: =IF($C69="",0,SUMIFS(J_Montant,J_Annee,Annee_Travail,J_Mois,8,J_Module,"Général",J_Cat,$C69,J_Type,"Dépense",J_Statut,"<>Annulé",J_Statut,"<>Prévu")) | T69: =IF($C69="",0,SUMIFS(P_M9,P_Annee,Annee_Travail,P_Cat,$C69,P_Type,"Dépense",P_Module,"Général")) | U69: =IF($C69="",0,SUMIFS(J_Montant,J_Annee,Annee_Travail,J_Mois,9,J_Module,"Général",J_Cat,$C69,J_Type,"Dépense",J_Statut,"<>Annulé",J_Statut,"<>Prévu")) | V69: =IF($C69="",0,SUMIFS(P_M10,P_Annee,Annee_Travail,P_Cat,$C69,P_Type,"Dépense",P_Module,"Général")) | W69: =IF($C69="",0,SUMIFS(J_Montant,J_Annee,Annee_Travail,J_Mois,10,J_Module,"Général",J_Cat,$C69,J_Type,"Dépense",J_Statut,"<>Annulé",J_Statut,"<>Prévu")) | X69: =IF($C69="",0,SUMIFS(P_M11,P_Annee,Annee_Travail,P_Cat,$C69,P_Type,"Dépense",P_Module,"Général")) | Y69: =IF($C69="",0,SUMIFS(J_Montant,J_Annee,Annee_Travail,J_Mois,11,J_Module,"Général",J_Cat,$C69,J_Type,"Dépense",J_Statut,"<>Annulé",J_Statut,"<>Prévu")) | Z69: =IF($C69="",0,SUMIFS(P_M12,P_Annee,Annee_Travail,P_Cat,$C69,P_Type,"Dépense",P_Module,"Général")) | AA69: =IF($C69="",0,SUMIFS(J_Montant,J_Annee,Annee_Travail,J_Mois,12,J_Module,"Général",J_Cat,$C69,J_Type,"Dépense",J_Statut,"<>Annulé",J_Statut,"<>Prévu")) | AB69: =D69+F69+H69+J69+L69+N69+P69+R69+T69+V69+X69+Z69 | AC69: =E69+G69+I69+K69+M69+O69+Q69+S69+U69+W69+Y69+AA69 | AD69: =$AB69-$AC69 | AE69: =IFERROR($AC69/$AB69,0)
